Workbook

Sheet ダッシュボード
A1: 介護校 マーケティング 週次分析ダッシュボード
A2: 実測ベース立て直し版 ／ 数値の出どこ：スプレッドシート管理（手入力） ／ 毎週「週次データ」タブに貼って更新
A4: ① 目標設定（ここを編集／黄色セルが前提）
A5: 契約単価（FC取り分・円） | B5: 800000 | C5: ← 1契約あたりの介護校売上
A6: 許容CPA上限（円） | B6: 307000 | C6: ← 1成約あたり広告費の上限ライン
A7: 目標CPL（円） | B7: 3000
A8: 目標 商談化率 | B8: 0.08 | C8: ← 第1段の目標（現状4%の2倍）
A9: 目標 成約率 | B9: 0.2 | C9: ← 第1段の目標（現状12%→）
A10: 目標 月予算（円） | B10: 1050000 | C10: ← 現状75万から微増で運用
A12: ② 現状（実測） vs 目標（第1段）
A13: 指標 | B13: 現状（実測・月換算） | C13: 目標（第1段） | D13: 判定
A14: 広告費 / 月（円） | B14: 755563 | C14: =$B$10 -> 1050000
A15: CV（リード）/ 月（件） | B15: 276 | C15: =$B$10/$B$7 -> 350
A16: 歩留まり（商談化率） | B16: 0.04 | C16: =$B$8 -> 0.08 | D16: =IF(B16>=C16,"◎ 達成",IF(B16>=C16*0.75,"△ あと一歩","✗ 未達")) -> ✗ 未達
A17: 商談 / 月（件） | B17: =B15*B16 -> 11.04 | C17: =C15*C16 -> 28
A18: 成約率 | B18: 0.12 | C18: =$B$9 -> 0.2 | D18: =IF(B18>=C18,"◎ 達成",IF(B18>=C18*0.75,"△ あと一歩","✗ 未達")) -> ✗ 未達
A19: 成約 / 月（件） | B19: =B17*B18 -> 1.3248 | C19: =C17*C18 -> 5.6 | D19: =IF(B19>=C19,"◎ 達成",IF(B19>=C19*0.75,"△ あと一歩","✗ 未達")) -> ✗ 未達
A20: CPL（円） | B20: =B14/B15 -> 2737.5471 | C20: =$B$7 -> 3000
A21: 1成約あたり広告費（円） | B21: =IFERROR(B14/B19,0) -> 570322.31 | C21: =IFERROR(C14/C19,0) -> 187500 | D21: =IF(B21<=C21,"◎ 達成",IF(B21<=C21*1.3,"△ あと一歩","✗ 未達")) -> ✗ 未達
A22: FC売上 / 月（円） | B22: =B19*$B$5 -> 1059840 | C22: =C19*$B$5 -> 4480000
A23: 年FC売上（円） | B23: =B22*12 -> 12718080 | C23: =C22*12 -> 53760000 | D23: =IF(B23>=C23,"◎ 達成",IF(B23>=C23*0.75,"△ あと一歩","✗ 未達")) -> ✗ 未達
A25: ※「現状」列の青字（広告費・リード・商談化率・成約率）は実測値。ここを毎月の実数に更新すると全体が再計算されます。判定は ◎達成／△あと一歩(目標の75%以上)／✗未達。1成約あたり広告費は許容CPA基準で判定。

Sheet 日次入力
A1: 日次入力（毎日1行ずつ入力）
A2: 日付・媒体・キャンペーンを選び、その日の数字を入力。媒体別CPのW10以降に自動集計。商談・成約は実施日で記録。
A3: 日付 | B3: 媒体 | C3: キャンペーン | D3: 消費金額 | E3: IMP | F3: クリック | G3: CV | H3: 商談 | I3: 成約
A4: 46182 | B4: Meta | C4: Metaウェビナー | D4: 16749 | E4: 5791 | F4: 90 | G4: 18 | H4: 0 | I4: 0
A5: 46182 | B5: Meta | C5: Meta介護校 | D5: 19628 | E5: 2821 | F5: 92 | G5: 3 | H5: 0 | I5: 0
A6: 46182 | B6: Meta | C6: MetaClaude | D6: 6308 | E6: 1734 | F6: 55 | G6: 8 | H6: 0 | I6: 0
A7: 46183 | B7: Meta | C7: Metaウェビナー | D7: 15510 | E7: 5433 | F7: 109 | G7: 10 | H7: 0 | I7: 0
A8: 46183 | B8: Meta | C8: Meta介護校 | D8: 19628 | E8: 2821 | F8: 92 | G8: 3 | H8: 0 | I8: 0
A9: 46183 | B9: Meta | C9: MetaClaude | D9: 6717 | E9: 1947 | F9: 71 | G9: 5 | H9: 0 | I9: 0
A10: 46184 | B10: Meta | C10: Metaウェビナー | D10: 4458 | E10: 1593 | F10: 33 | G10: 5 | H10: 0 | I10: 0
A11: 46184 | B11: Meta | C11: Meta介護校 | D11: 17023 | E11: 2691 | F11: 69 | G11: 1 | H11: 0 | I11: 0
A12: 46184 | B12: Meta | C12: MetaClaude | D12: 5818 | E12: 2786 | F12: 66 | G12: 6 | H12: 0 | I12: 0
A13: 46185 | B13: Meta | C13: Meta介護校 | D13: 13326 | E13: 2397 | F13: 68 | G13: 0 | H13: 0 | I13: 0
A14: 46185 | B14: Meta | C14: MetaClaude | D14: 5709 | E14: 3051 | F14: 83 | G14: 2 | H14: 0 | I14: 0
A15: 46186 | B15: Meta | C15: Meta介護校 | D15: 12008 | E15: 2083 | F15: 37 | G15: 5 | H15: 0 | I15: 0
... A41: 46195 | B41: Meta | C41: MetaClaude | D41: 3989 | E41: 1504 | F41: 33 | G41: 1 | H41: 0 | I41: 0

Sheet 週次_媒体別CP
A1: 週次分析：媒体 × キャンペーン別（表側＝時系列）
A2: W1〜W9は確定値。W10以降（緑セル）は『日次入力』タブから自動集計。CPM〜余裕倍率は自動計算。
A4: Meta ／ ウェビナー告知用 （目標CPL ¥3,000）
A5: 週 | B5: 期間 | C5: 消費金額 | D5: IMP | E5: クリック | F5: CV | G5: CTR | H5: CPC | I5: CPM | J5: CVR | K5: CPL | L5: 商談 | M5: 歩留まり | N5: 成約 | O5: 成約率 | P5: 1成約広告費 | Q5: 対許容CPA | R5: 余裕倍率
A6: W1 | B6: 4/7–4/13 | C6: 87849 | D6: 38081 | E6: 612 | F6: 35 | G6: =IFERROR(E6/D6,"") -> 0.016071007 | H6: =IFERROR(C6/E6,"") -> 143.54412 | I6: =IFERROR(C6/D6*1000,"") -> 2306.8985 | J6: =IFERROR(F6/E6,"") -> 0.057189542 | K6: =IFERROR(C6/F6,"") -> 2509.9714 | M6: =IF(L6="","",IFERROR(L6/F6,"")) | O6: =IF(N6="","",IFERROR(N6/L6,"")) | P6: =IF(N6=0,"",IFERROR(C6/N6,"")) | Q6: =IF(N6=0,"",IFERROR(IF(C6/N6<=用語集!$B$22,"◎ 許容内","✗ 超過"),"—")) | R6: =IFERROR(用語集!$B$22/P6,"")
A7: W2 | B7: 4/14–4/20 | C7: 84574 | D7: 32897 | E7: 528 | F7: 34 | G7: =IFERROR(E7/D7,"") -> 0.016050096 | H7: =IFERROR(C7/E7,"") -> 160.17803 | I7: =IFERROR(C7/D7*1000,"") -> 2570.8727 | J7: =IFERROR(F7/E7,"") -> 0.064393939 | K7: =IFERROR(C7/F7,"") -> 2487.4706 | M7: =IF(L7="","",IFERROR(L7/F7,"")) | O7: =IF(N7="","",IFERROR(N7/L7,"")) | P7: =IF(N7=0,"",IFERROR(C7/N7,"")) | Q7: =IF(N7=0,"",IFERROR(IF(C7/N7<=用語集!$B$22,"◎ 許容内","✗ 超過"),"—")) | R7: =IFERROR(用語集!$B$22/P7,"")
A8: W3 | B8: 4/21–4/27 | C8: 77500 | D8: 22541 | E8: 461 | F8: 25 | G8: =IFERROR(E8/D8,"") -> 0.020451621 | H8: =IFERROR(C8/E8,"") -> 168.1128 | I8: =IFERROR(C8/D8*1000,"") -> 3438.1793 | J8: =IFERROR(F8/E8,"") -> 0.054229935 | K8: =IFERROR(C8/F8,"") -> 3100 | M8: =IF(L8="","",IFERROR(L8/F8,"")) | O8: =IF(N8="","",IFERROR(N8/L8,"")) | P8: =IF(N8=0,"",IFERROR(C8/N8,"")) | Q8: =IF(N8=0,"",IFERROR(IF(C8/N8<=用語集!$B$22,"◎ 許容内","✗ 超過"),"—")) | R8: =IFERROR(用語集!$B$22/P8,"")
A9: W4 | B9: 4/28–5/4 | C9: 配信なし | G9: =IFERROR(E9/D9,"") | H9: =IFERROR(C9/E9,"") | I9: =IFERROR(C9/D9*1000,"") | J9: =IFERROR(F9/E9,"") | K9: =IFERROR(C9/F9,"") | M9: =IF(L9="","",IFERROR(L9/F9,"")) | O9: =IF(N9="","",IFERROR(N9/L9,"")) | P9: =IF(N9=0,"",IFERROR(C9/N9,"")) | Q9: =IF(N9=0,"",IFERROR(IF(C9/N9<=用語集!$B$22,"◎ 許容内","✗ 超過"),"—")) | R9: =IFERROR(用語集!$B$22/P9,"")
A10: W5 | B10: 5/5–5/11 | C10: 配信なし | G10: =IFERROR(E10/D10,"") | H10: =IFERROR(C10/E10,"") | I10: =IFERROR(C10/D10*1000,"") | J10: =IFERROR(F10/E10,"") | K10: =IFERROR(C10/F10,"") | M10: =IF(L10="","",IFERROR(L10/F10,"")) | O10: =IF(N10="","",IFERROR(N10/L10,"")) | P10: =IF(N10=0,"",IFERROR(C10/N10,"")) | Q10: =IF(N10=0,"",IFERROR(IF(C10/N10<=用語集!$B$22,"◎ 許容内","✗ 超過"),"—")) | R10: =IFERROR(用語集!$B$22/P10,"")
A11: W6 | B11: 5/12–5/18 | C11: 配信なし | G11: =IFERROR(E11/D11,"") | H11: =IFERROR(C11/E11,"") | I11: =IFERROR(C11/D11*1000,"") | J11: =IFERROR(F11/E11,"") | K11: =IFERROR(C11/F11,"") | M11: =IF(L11="","",IFERROR(L11/F11,"")) | O11: =IF(N11="","",IFERROR(N11/L11,"")) | P11: =IF(N11=0,"",IFERROR(C11/N11,"")) | Q11: =IF(N11=0,"",IFERROR(IF(C11/N11<=用語集!$B$22,"◎ 許容内","✗ 超過"),"—")) | R11: =IFERROR(用語集!$B$22/P11,"")
A12: W7 | B12: 5/19–5/25 | C12: 配信なし | G12: =IFERROR(E12/D12,"") | H12: =IFERROR(C12/E12,"") | I12: =IFERROR(C12/D12*1000,"") | J12: =IFERROR(F12/E12,"") | K12: =IFERROR(C12/F12,"") | M12: =IF(L12="","",IFERROR(L12/F12,"")) | O12: =IF(N12="","",IFERROR(N12/L12,"")) | P12: =IF(N12=0,"",IFERROR(C12/N12,"")) | Q12: =IF(N12=0,"",IFERROR(IF(C12/N12<=用語集!$B$22,"◎ 許容内","✗ 超過"),"—")) | R12: =IFERROR(用語集!$B$22/P12,"")
A13: W8 | B13: 5/26–6/1 | C13: 63871 | D13: 18209 | E13: 469 | F13: 49 | G13: =IFERROR(E13/D13,"") -> 0.025756494 | H13: =IFERROR(C13/E13,"") -> 136.1855 | I13: =IFERROR(C13/D13*1000,"") -> 3507.661 | J13: =IFERROR(F13/E13,"") -> 0.10447761 | K13: =IFERROR(C13/F13,"") -> 1303.4898 | M13: =IF(L13="","",IFERROR(L13/F13,"")) | O13: =IF(N13="","",IFERROR(N13/L13,"")) | P13: =IF(N13=0,"",IFERROR(C13/N13,"")) | Q13: =IF(N13=0,"",IFERROR(IF(C13/N13<=用語集!$B$22,"◎ 許容内","✗ 超過"),"—")) | R13: =IFERROR(用語集!$B$22/P13,"")
A14: W9 | B14: 6/2–6/8 | C14: 103281 | D14: 40922 | E14: 649 | F14: 68 | G14: =IFERROR(E14/D14,"") -> 0.01585944 | H14: =IFERROR(C14/E14,"") -> 159.13867 | I14: =IFERROR(C14/D14*1000,"") -> 2523.8503 | J14: =IFERROR(F14/E14,"") -> 0.10477658 | K14: =IFERROR(C14/F14,"") -> 1518.8382 | M14: =IF(L14="","",IFERROR(L14/F14,"")) | O14: =IF(N14="","",IFERROR(N14/L14,"")) | P14: =IF(N14=0,"",IFERROR(C14/N14,"")) | Q14: =IF(N14=0,"",IFERROR(IF(C14/N14<=用語集!$B$22,"◎ 許容内","✗ 超過"),"—")) | R14: =IFERROR(用語集!$B$22/P14,"")
A15: W10 | B15: 6/9–6/15 | C15: =IF(COUNTIFS(日次入力!$A$4:$A$1500,">="&DATE(2026,6,9),日次入力!$A$4:$A$1500,"<="&DATE(2026,6,15),日次入力!$C$4:$C$1500,"Metaウェビナー")=0,"",SUMIFS(日次入力!$D$4:$D$1500,日次入力!$A$4:$A$1500,">="&DATE(2026,6,9),日次入力!$A$4:$A$1500,"<="&DATE(2026,6,15),日次入力!$C$4:$C$1500,"Metaウェビナー")) -> 36717 | D15: =IF(COUNTIFS(日次入力!$A$4:$A$1500,">="&DATE(2026,6,9),日次入力!$A$4:$A$1500,"<="&DATE(2026,6,15),日次入力!$C$4:$C$1500,"Metaウェビナー")=0,"",SUMIFS(日次入力!$E$4:$E$1500,日次入力!$A$4:$A$1500,">="&DATE(2026,6,9),日次入力!$A$4:$A$1500,"<="&DATE(2026,6,15),日次入力!$C$4:$C$1500,"Metaウェビナー")) -> 12817 | E15: =IF(COUNTIFS(日次入力!$A$4:$A$1500,">="&DATE(2026,6,9),日次入力!$A$4:$A$1500,"<="&DATE(2026,6,15),日次入力!$C$4:$C$1500,"Metaウェビナー")=0,"",SUMIFS(日次入力!$F$4:$F$1500,日次入力!$A$4:$A$1500,">="&DATE(2026,6,9),日次入力!$A$4:$A$1500,"<="&DATE(2026,6,15),日次入力!$C$4:$C$1500,"Metaウェビナー")) -> 232 | F15: =IF(COUNTIFS(日次入力!$A$4:$A$1500,">="&DATE(2026,6,9),日次入力!$A$4:$A$1500,"<="&DATE(2026,6,15),日次入力!$C$4:$C$1500,"Metaウェビナー")=0,"",SUMIFS(日次入力!$G$4:$G$1500,日次入力!$A$4:$A$1500,">="&DATE(2026,6,9),日次入力!$A$4:$A$1500,"<="&DATE(2026,6,15),日次入力!$C$4:$C$1500,"Metaウェビナー")) -> 33 | G15: =IFERROR(E15/D15,"") -> 0.01810096 | H15: =IFERROR(C15/E15,"") -> 158.26293 | I15: =IFERROR(C15/D15*1000,"") -> 2864.7109 | J15: =IFERROR(F15/E15,"") -> 0.14224138 | K15: =IFERROR(C15/F15,"") -> 1112.6364 | L15: =IF(COUNTIFS(日次入力!$A$4:$A$1500,">="&DATE(2026,6,9),日次入力!$A$4:$A$1500,"<="&DATE(2026,6,15),日次入力!$C$4:$C$1500,"Metaウェビナー")=0,"",SUMIFS(日次入力!$H$4:$H$1500,日次入力!$A$4:$A$1500,">="&DATE(2026,6,9),日次入力!$A$4:$A$1500,"<="&DATE(2026,6,15),日次入力!$C$4:$C$1500,"Metaウェビナー")) -> 0 | M15: =IF(L15="","",IFERROR(L15/F15,"")) -> 0 | N15: =IF(COUNTIFS(日次入力!$A$4:$A$1500,">="&DATE(2026,6,9),日次入力!$A$4:$A$1500,"<="&DATE(2026,6,15),日次入力!$C$4:$C$1500,"Metaウェビナー")=0,"",SUMIFS(日次入力!$I$4:$I$1500,日次入力!$A$4:$A$1500,">="&DATE(2026,6,9),日次入力!$A$4:$A$1500,"<="&DATE(2026,6,15),日次入力!$C$4:$C$1500,"Metaウェビナー")) -> 0 | O15: =IF(N15="","",IFERROR(N15/L15,"")) | P15: =IF(N15=0,"",IFERROR(C15/N15,"")) | Q15: =IF(N15=0,"",IFERROR(IF(C15/N15<=用語集!$B$22,"◎ 許容内","✗ 超過"),"—")) | R15: =IFERROR(用語集!$B$22/P15,"")
A16: W11 | B16: 6/16–6/22 | C16: =IF(COUNTIFS(日次入力!$A$4:$A$1500,">="&DATE(2026,6,16),日次入力!$A$4:$A$1500,"<="&DATE(2026,6,22),日次入力!$C$4:$C$1500,"Metaウェビナー")=0,"",SUMIFS(日次入力!$D$4:$D$1500,日次入力!$A$4:$A$1500,">="&DATE(2026,6,16),日次入力!$A$4:$A$1500,"<="&DATE(2026,6,22),日次入力!$C$4:$C$1500,"Metaウェビナー")) -> 91426 | D16: =IF(COUNTIFS(日次入力!$A$4:$A$1500,">="&DATE(2026,6,16),日次入力!$A$4:$A$1500,"<="&DATE(2026,6,22),日次入力!$C$4:$C$1500,"Metaウェビナー")=0,"",SUMIFS(日次入力!$E$4:$E$1500,日次入力!$A$4:$A$1500,">="&DATE(2026,6,16),日次入力!$A$4:$A$1500,"<="&DATE(2026,6,22),日次入力!$C$4:$C$1500,"Metaウェビナー")) -> 31765 | E16: =IF(COUNTIFS(日次入力!$A$4:$A$1500,">="&DATE(2026,6,16),日次入力!$A$4:$A$1500,"<="&DATE(2026,6,22),日次入力!$C$4:$C$1500,"Metaウェビナー")=0,"",SUMIFS(日次入力!$F$4:$F$1500,日次入力!$A$4:$A$1500,">="&DATE(2026,6,16),日次入力!$A$4:$A$1500,"<="&DATE(2026,6,22),日次入力!$C$4:$C$1500,"Metaウェビナー")) -> 461 | F16: =IF(COUNTIFS(日次入力!$A$4:$A$1500,">="&DATE(2026,6,16),日次入力!$A$4:$A$1500,"<="&DATE(2026,6,22),日次入力!$C$4:$C$1500,"Metaウェビナー")=0,"",SUMIFS(日次入力!$G$4:$G$1500,日次入力!$A$4:$A$1500,">="&DATE(2026,6,16),日次入力!$A$4:$A$1500,"<="&DATE(2026,6,22),日次入力!$C$4:$C$1500,"Metaウェビナー")) -> 28 | G16: =IFERROR(E16/D16,"") -> 0.014512829 | H16: =IFERROR(C16/E16,"") -> 198.32104 | I16: =IFERROR(C16/D16*1000,"") -> 2878.1993 | J16: =IFERROR(F16/E16,"") -> 0.060737527 | K16: =IFERROR(C16/F16,"") -> 3265.2143 | L16: =IF(COUNTIFS(日次入力!$A$4:$A$1500,">="&DATE(2026,6,16),日次入力!$A$4:$A$1500,"<="&DATE(2026,6,22),日次入力!$C$4:$C$1500,"Metaウェビナー")=0,"",SUMIFS(日次入力!$H$4:$H$1500,日次入力!$A$4:$A$1500,">="&DATE(2026,6,16),日次入力!$A$4:$A$1500,"<="&DATE(2026,6,22),日次入力!$C$4:$C$1500,"Metaウェビナー")) -> 3 | M16: =IF(L16="","",IFERROR(L16/F16,"")) -> 0.10714286 | N16: =IF(COUNTIFS(日次入力!$A$4:$A$1500,">="&DATE(2026,6,16),日次入力!$A$4:$A$1500,"<="&DATE(2026,6,22),日次入力!$C$4:$C$1500,"Metaウェビナー")=0,"",SUMIFS(日次入力!$I$4:$I$1500,日次入力!$A$4:$A$1500,">="&DATE(2026,6,16),日次入力!$A$4:$A$1500,"<="&DATE(2026,6,22),日次入力!$C$4:$C$1500,"Metaウェビナー")) -> 0 | O16: =IF(N16="","",IFERROR(N16/L16,"")) -> 0 | P16: =IF(N16=0,"",IFERROR(C16/N16,"")) | Q16: =IF(N16=0,"",IFERROR(IF(C16/N16<=用語集!$B$22,"◎ 許容内","✗ 超過"),"—")) | R16: =IFERROR(用語集!$B$22/P16,"")
A17: W12 | B17: 6/23–6/29 | C17: =IF(COUNTIFS(日次入力!$A$4:$A$1500,">="&DATE(2026,6,23),日次入力!$A$4:$A$1500,"<="&DATE(2026,6,29),日次入力!$C$4:$C$1500,"Metaウェビナー")=0,"",SUMIFS(日次入力!$D$4:$D$1500,日次入力!$A$4:$A$1500,">="&DATE(2026,6,23),日次入力!$A$4:$A$1500,"<="&DATE(2026,6,29),日次入力!$C$4:$C$1500,"Metaウェビナー")) | D17: =IF(COUNTIFS(日次入力!$A$4:$A$1500,">="&DATE(2026,6,23),日次入力!$A$4:$A$1500,"<="&DATE(2026,6,29),日次入力!$C$4:$C$1500,"Metaウェビナー")=0,"",SUMIFS(日次入力!$E$4:$E$1500,日次入力!$A$4:$A$1500,">="&DATE(2026,6,23),日次入力!$A$4:$A$1500,"<="&DATE(2026,6,29),日次入力!$C$4:$C$1500,"Metaウェビナー")) | E17: =IF(COUNTIFS(日次入力!$A$4:$A$1500,">="&DATE(2026,6,23),日次入力!$A$4:$A$1500,"<="&DATE(2026,6,29),日次入力!$C$4:$C$1500,"Metaウェビナー")=0,"",SUMIFS(日次入力!$F$4:$F$1500,日次入力!$A$4:$A$1500,">="&DATE(2026,6,23),日次入力!$A$4:$A$1500,"<="&DATE(2026,6,29),日次入力!$C$4:$C$1500,"Metaウェビナー")) | F17: =IF(COUNTIFS(日次入力!$A$4:$A$1500,">="&DATE(2026,6,23),日次入力!$A$4:$A$1500,"<="&DATE(2026,6,29),日次入力!$C$4:$C$1500,"Metaウェビナー")=0,"",SUMIFS(日次入力!$G$4:$G$1500,日次入力!$A$4:$A$1500,">="&DATE(2026,6,23),日次入力!$A$4:$A$1500,"<="&DATE(2026,6,29),日次入力!$C$4:$C$1500,"Metaウェビナー")) | G17: =IFERROR(E17/D17,"") | H17: =IFERROR(C17/E17,"") | I17: =IFERROR(C17/D17*1000,"") | J17: =IFERROR(F17/E17,"") | K17: =IFERROR(C17/F17,"") | L17: =IF(COUNTIFS(日次入力!$A$4:$A$1500,">="&DATE(2026,6,23),日次入力!$A$4:$A$1500,"<="&DATE(2026,6,29),日次入力!$C$4:$C$1500,"Metaウェビナー")=0,"",SUMIFS(日次入力!$H$4:$H$1500,日次入力!$A$4:$A$1500,">="&DATE(2026,6,23),日次入力!$A$4:$A$1500,"<="&DATE(2026,6,29),日次入力!$C$4:$C$1500,"Metaウェビナー")) | M17: =IF(L17="","",IFERROR(L17/F17,"")) | N17: =IF(COUNTIFS(日次入力!$A$4:$A$1500,">="&DATE(2026,6,23),日次入力!$A$4:$A$1500,"<="&DATE(2026,6,29),日次入力!$C$4:$C$1500,"Metaウェビナー")=0,"",SUMIFS(日次入力!$I$4:$I$1500,日次入力!$A$4:$A$1500,">="&DATE(2026,6,23),日次入力!$A$4:$A$1500,"<="&DATE(2026,6,29),日次入力!$C$4:$C$1500,"Metaウェビナー")) | O17: =IF(N17="","",IFERROR(N17/L17,"")) | P17: =IF(N17=0,"",IFERROR(C17/N17,"")) | Q17: =IF(N17=0,"",IFERROR(IF(C17/N17<=用語集!$B$22,"◎ 許容内","✗ 超過"),"—")) -> — | R17: =IFERROR(用語集!$B$22/P17,"")
A18: W13 | B18: 6/30–7/6 | C18: =IF(COUNTIFS(日次入力!$A$4:$A$1500,">="&DATE(2026,6,30),日次入力!$A$4:$A$1500,"<="&DATE(2026,7,6),日次入力!$C$4:$C$1500,"Metaウェビナー")=0,"",SUMIFS(日次入力!$D$4:$D$1500,日次入力!$A$4:$A$1500,">="&DATE(2026,6,30),日次入力!$A$4:$A$1500,"<="&DATE(2026,7,6),日次入力!$C$4:$C$1500,"Metaウェビナー")) | D18: =IF(COUNTIFS(日次入力!$A$4:$A$1500,">="&DATE(2026,6,30),日次入力!$A$4:$A$1500,"<="&DATE(2026,7,6),日次入力!$C$4:$C$1500,"Metaウェビナー")=0,"",SUMIFS(日次入力!$E$4:$E$1500,日次入力!$A$4:$A$1500,">="&DATE(2026,6,30),日次入力!$A$4:$A$1500,"<="&DATE(2026,7,6),日次入力!$C$4:$C$1500,"Metaウェビナー")) | E18: =IF(COUNTIFS(日次入力!$A$4:$A$1500,">="&DATE(2026,6,30),日次入力!$A$4:$A$1500,"<="&DATE(2026,7,6),日次入力!$C$4:$C$1500,"Metaウェビナー")=0,"",SUMIFS(日次入力!$F$4:$F$1500,日次入力!$A$4:$A$1500,">="&DATE(2026,6,30),日次入力!$A$4:$A$1500,"<="&DATE(2026,7,6),日次入力!$C$4:$C$1500,"Metaウェビナー")) | F18: =IF(COUNTIFS(日次入力!$A$4:$A$1500,">="&DATE(2026,6,30),日次入力!$A$4:$A$1500,"<="&DATE(2026,7,6),日次入力!$C$4:$C$1500,"Metaウェビナー")=0,"",SUMIFS(日次入力!$G$4:$G$1500,日次入力!$A$4:$A$1500,">="&DATE(2026,6,30),日次入力!$A$4:$A$1500,"<="&DATE(2026,7,6),日次入力!$C$4:$C$1500,"Metaウェビナー")) | G18: =IFERROR(E18/D18,"") | H18: =IFERROR(C18/E18,"") | I18: =IFERROR(C18/D18*1000,"") | J18: =IFERROR(F18/E18,"") | K18: =IFERROR(C18/F18,"") | L18: =IF(COUNTIFS(日次入力!$A$4:$A$1500,">="&DATE(2026,6,30),日次入力!$A$4:$A$1500,"<="&DATE(2026,7,6),日次入力!$C$4:$C$1500,"Metaウェビナー")=0,"",SUMIFS(日次入力!$H$4:$H$1500,日次入力!$A$4:$A$1500,">="&DATE(2026,6,30),日次入力!$A$4:$A$1500,"<="&DATE(2026,7,6),日次入力!$C$4:$C$1500,"Metaウェビナー")) | M18: =IF(L18="","",IFERROR(L18/F18,"")) | N18: =IF(COUNTIFS(日次入力!$A$4:$A$1500,">="&DATE(2026,6,30),日次入力!$A$4:$A$1500,"<="&DATE(2026,7,6),日次入力!$C$4:$C$1500,"Metaウェビナー")=0,"",SUMIFS(日次入力!$I$4:$I$1500,日次入力!$A$4:$A$1500,">="&DATE(2026,6,30),日次入力!$A$4:$A$1500,"<="&DATE(2026,7,6),日次入力!$C$4:$C$1500,"Metaウェビナー")) | O18: =IF(N18="","",IFERROR(N18/L18,"")) | P18: =IF(N18=0,"",IFERROR(C18/N18,"")) | Q18: =IF(N18=0,"",IFERROR(IF(C18/N18<=用語集!$B$22,"◎ 許容内","✗ 超過"),"—")) -> — | R18: =IFERROR(用語集!$B$22/P18,"")
A19: W14 | B19: 7/7–7/13 | C19: =IF(COUNTIFS(日次入力!$A$4:$A$1500,">="&DATE(2026,7,7),日次入力!$A$4:$A$1500,"<="&DATE(2026,7,13),日次入力!$C$4:$C$1500,"Metaウェビナー")=0,"",SUMIFS(日次入力!$D$4:$D$1500,日次入力!$A$4:$A$1500,">="&DATE(2026,7,7),日次入力!$A$4:$A$1500,"<="&DATE(2026,7,13),日次入力!$C$4:$C$1500,"Metaウェビナー")) | D19: =IF(COUNTIFS(日次入力!$A$4:$A$1500,">="&DATE(2026,7,7),日次入力!$A$4:$A$1500,"<="&DATE(2026,7,13),日次入力!$C$4:$C$1500,"Metaウェビナー")=0,"",SUMIFS(日次入力!$E$4:$E$1500,日次入力!$A$4:$A$1500,">="&DATE(2026,7,7),日次入力!$A$4:$A$1500,"<="&DATE(2026,7,13),日次入力!$C$4:$C$1500,"Metaウェビナー")) | E19: =IF(COUNTIFS(日次入力!$A$4:$A$1500,">="&DATE(2026,7,7),日次入力!$A$4:$A$1500,"<="&DATE(2026,7,13),日次入力!$C$4:$C$1500,"Metaウェビナー")=0,"",SUMIFS(日次入力!$F$4:$F$1500,日次入力!$A$4:$A$1500,">="&DATE(2026,7,7),日次入力!$A$4:$A$1500,"<="&DATE(2026,7,13),日次入力!$C$4:$C$1500,"Metaウェビナー")) | F19: =IF(COUNTIFS(日次入力!$A$4:$A$1500,">="&DATE(2026,7,7),日次入力!$A$4:$A$1500,"<="&DATE(2026,7,13),日次入力!$C$4:$C$1500,"Metaウェビナー")=0,"",SUMIFS(日次入力!$G$4:$G$1500,日次入力!$A$4:$A$1500,">="&DATE(2026,7,7),日次入力!$A$4:$A$1500,"<="&DATE(2026,7,13),日次入力!$C$4:$C$1500,"Metaウェビナー")) | G19: =IFERROR(E19/D19,"") | H19: =IFERROR(C19/E19,"") | I19: =IFERROR(C19/D19*1000,"") | J19: =IFERROR(F19/E19,"") | K19: =IFERROR(C19/F19,"") | L19: =IF(COUNTIFS(日次入力!$A$4:$A$1500,">="&DATE(2026,7,7),日次入力!$A$4:$A$1500,"<="&DATE(2026,7,13),日次入力!$C$4:$C$1500,"Metaウェビナー")=0,"",SUMIFS(日次入力!$H$4:$H$1500,日次入力!$A$4:$A$1500,">="&DATE(2026,7,7),日次入力!$A$4:$A$1500,"<="&DATE(2026,7,13),日次入力!$C$4:$C$1500,"Metaウェビナー")) | M19: =IF(L19="","",IFERROR(L19/F19,"")) | N19: =IF(COUNTIFS(日次入力!$A$4:$A$1500,">="&DATE(2026,7,7),日次入力!$A$4:$A$1500,"<="&DATE(2026,7,13),日次入力!$C$4:$C$1500,"Metaウェビナー")=0,"",SUMIFS(日次入力!$I$4:$I$1500,日次入力!$A$4:$A$1500,">="&DATE(2026,7,7),日次入力!$A$4:$A$1500,"<="&DATE(2026,7,13),日次入力!$C$4:$C$1500,"Metaウェビナー")) | O19: =IF(N19="","",IFERROR(N19/L19,"")) | P19: =IF(N19=0,"",IFERROR(C19/N19,"")) | Q19: =IF(N19=0,"",IFERROR(IF(C19/N19<=用語集!$B$22,"◎ 許容内","✗ 超過"),"—")) -> — | R19: =IFERROR(用語集!$B$22/P19,"")
A20: W15 | B20: 7/14–7/20 | C20: =IF(COUNTIFS(日次入力!$A$4:$A$1500,">="&DATE(2026,7,14),日次入力!$A$4:$A$1500,"<="&DATE(2026,7,20),日次入力!$C$4:$C$1500,"Metaウェビナー")=0,"",SUMIFS(日次入力!$D$4:$D$1500,日次入力!$A$4:$A$1500,">="&DATE(2026,7,14),日次入力!$A$4:$A$1500,"<="&DATE(2026,7,20),日次入力!$C$4:$C$1500,"Metaウェビナー")) | D20: =IF(COUNTIFS(日次入力!$A$4:$A$1500,">="&DATE(2026,7,14),日次入力!$A$4:$A$1500,"<="&DATE(2026,7,20),日次入力!$C$4:$C$1500,"Metaウェビナー")=0,"",SUMIFS(日次入力!$E$4:$E$1500,日次入力!$A$4:$A$1500,">="&DATE(2026,7,14),日次入力!$A$4:$A$1500,"<="&DATE(2026,7,20),日次入力!$C$4:$C$1500,"Metaウェビナー")) | E20: =IF(COUNTIFS(日次入力!$A$4:$A$1500,">="&DATE(2026,7,14),日次入力!$A$4:$A$1500,"<="&DATE(2026,7,20),日次入力!$C$4:$C$1500,"Metaウェビナー")=0,"",SUMIFS(日次入力!$F$4:$F$1500,日次入力!$A$4:$A$1500,">="&DATE(2026,7,14),日次入力!$A$4:$A$1500,"<="&DATE(2026,7,20),日次入力!$C$4:$C$1500,"Metaウェビナー")) | F20: =IF(COUNTIFS(日次入力!$A$4:$A$1500,">="&DATE(2026,7,14),日次入力!$A$4:$A$1500,"<="&DATE(2026,7,20),日次入力!$C$4:$C$1500,"Metaウェビナー")=0,"",SUMIFS(日次入力!$G$4:$G$1500,日次入力!$A$4:$A$1500,">="&DATE(2026,7,14),日次入力!$A$4:$A$1500,"<="&DATE(2026,7,20),日次入力!$C$4:$C$1500,"Metaウェビナー")) | G20: =IFERROR(E20/D20,"") | H20: =IFERROR(C20/E20,"") | I20: =IFERROR(C20/D20*1000,"") | J20: =IFERROR(F20/E20,"") | K20: =IFERROR(C20/F20,"") | L20: =IF(COUNTIFS(日次入力!$A$4:$A$1500,">="&DATE(2026,7,14),日次入力!$A$4:$A$1500,"<="&DATE(2026,7,20),日次入力!$C$4:$C$1500,"Metaウェビナー")=0,"",SUMIFS(日次入力!$H$4:$H$1500,日次入力!$A$4:$A$1500,">="&DATE(2026,7,14),日次入力!$A$4:$A$1500,"<="&DATE(2026,7,20),日次入力!$C$4:$C$1500,"Metaウェビナー")) | M20: =IF(L20="","",IFERROR(L20/F20,"")) | N20: =IF(COUNTIFS(日次入力!$A$4:$A$1500,">="&DATE(2026,7,14),日次入力!$A$4:$A$1500,"<="&DATE(2026,7,20),日次入力!$C$4:$C$1500,"Metaウェビナー")=0,"",SUMIFS(日次入力!$I$4:$I$1500,日次入力!$A$4:$A$1500,">="&DATE(2026,7,14),日次入力!$A$4:$A$1500,"<="&DATE(2026,7,20),日次入力!$C$4:$C$1500,"Metaウェビナー")) | O20: =IF(N20="","",IFERROR(N20/L20,"")) | P20: =IF(N20=0,"",IFERROR(C20/N20,"")) | Q20: =IF(N20=0,"",IFERROR(IF(C20/N20<=用語集!$B$22,"◎ 許容内","✗ 超過"),"—")) -> — | R20: =IFERROR(用語集!$B$22/P20,"")
A21: W16 | B21: 7/21–7/27 | C21: =IF(COUNTIFS(日次入力!$A$4:$A$1500,">="&DATE(2026,7,21),日次入力!$A$4:$A$1500,"<="&DATE(2026,7,27),日次入力!$C$4:$C$1500,"Metaウェビナー")=0,"",SUMIFS(日次入力!$D$4:$D$1500,日次入力!$A$4:$A$1500,">="&DATE(2026,7,21),日次入力!$A$4:$A$1500,"<="&DATE(2026,7,27),日次入力!$C$4:$C$1500,"Metaウェビナー")) | D21: =IF(COUNTIFS(日次入力!$A$4:$A$1500,">="&DATE(2026,7,21),日次入力!$A$4:$A$1500,"<="&DATE(2026,7,27),日次入力!$C$4:$C$1500,"Metaウェビナー")=0,"",SUMIFS(日次入力!$E$4:$E$1500,日次入力!$A$4:$A$1500,">="&DATE(2026,7,21),日次入力!$A$4:$A$1500,"<="&DATE(2026,7,27),日次入力!$C$4:$C$1500,"Metaウェビナー")) | E21: =IF(COUNTIFS(日次入力!$A$4:$A$1500,">="&DATE(2026,7,21),日次入力!$A$4:$A$1500,"<="&DATE(2026,7,27),日次入力!$C$4:$C$1500,"Metaウェビナー")=0,"",SUMIFS(日次入力!$F$4:$F$1500,日次入力!$A$4:$A$1500,">="&DATE(2026,7,21),日次入力!$A$4:$A$1500,"<="&DATE(2026,7,27),日次入力!$C$4:$C$1500,"Metaウェビナー")) | F21: =IF(COUNTIFS(日次入力!$A$4:$A$1500,">="&DATE(2026,7,21),日次入力!$A$4:$A$1500,"<="&DATE(2026,7,27),日次入力!$C$4:$C$1500,"Metaウェビナー")=0,"",SUMIFS(日次入力!$G$4:$G$1500,日次入力!$A$4:$A$1500,">="&DATE(2026,7,21),日次入力!$A$4:$A$1500,"<="&DATE(2026,7,27),日次入力!$C$4:$C$1500,"Metaウェビナー")) | G21: =IFERROR(E21/D21,"") | H21: =IFERROR(C21/E21,"") | I21: =IFERROR(C21/D21*1000,"") | J21: =IFERROR(F21/E21,"") | K21: =IFERROR(C21/F21,"") | L21: =IF(COUNTIFS(日次入力!$A$4:$A$1500,">="&DATE(2026,7,21),日次入力!$A$4:$A$1500,"<="&DATE(2026,7,27),日次入力!$C$4:$C$1500,"Metaウェビナー")=0,"",SUMIFS(日次入力!$H$4:$H$1500,日次入力!$A$4:$A$1500,">="&DATE(2026,7,21),日次入力!$A$4:$A$1500,"<="&DATE(2026,7,27),日次入力!$C$4:$C$1500,"Metaウェビナー")) | M21: =IF(L21="","",IFERROR(L21/F21,"")) | N21: =IF(COUNTIFS(日次入力!$A$4:$A$1500,">="&DATE(2026,7,21),日次入力!$A$4:$A$1500,"<="&DATE(2026,7,27),日次入力!$C$4:$C$1500,"Metaウェビナー")=0,"",SUMIFS(日次入力!$I$4:$I$1500,日次入力!$A$4:$A$1500,">="&DATE(2026,7,21),日次入力!$A$4:$A$1500,"<="&DATE(2026,7,27),日次入力!$C$4:$C$1500,"Metaウェビナー")) | O21: =IF(N21="","",IFERROR(N21/L21,"")) | P21: =IF(N21=0,"",IFERROR(C21/N21,"")) | Q21: =IF(N21=0,"",IFERROR(IF(C21/N21<=用語集!$B$22,"◎ 許容内","✗ 超過"),"—")) -> — | R21: =IFERROR(用語集!$B$22/P21,"")
A22: W17 | B22: 7/28–8/3 | C22: =IF(COUNTIFS(日次入力!$A$4:$A$1500,">="&DATE(2026,7,28),日次入力!$A$4:$A$1500,"<="&DATE(2026,8,3),日次入力!$C$4:$C$1500,"Metaウェビナー")=0,"",SUMIFS(日次入力!$D$4:$D$1500,日次入力!$A$4:$A$1500,">="&DATE(2026,7,28),日次入力!$A$4:$A$1500,"<="&DATE(2026,8,3),日次入力!$C$4:$C$1500,"Metaウェビナー")) | D22: =IF(COUNTIFS(日次入力!$A$4:$A$1500,">="&DATE(2026,7,28),日次入力!$A$4:$A$1500,"<="&DATE(2026,8,3),日次入力!$C$4:$C$1500,"Metaウェビナー")=0,"",SUMIFS(日次入力!$E$4:$E$1500,日次入力!$A$4:$A$1500,">="&DATE(2026,7,28),日次入力!$A$4:$A$1500,"<="&DATE(2026,8,3),日次入力!$C$4:$C$1500,"Metaウェビナー")) | E22: =IF(COUNTIFS(日次入力!$A$4:$A$1500,">="&DATE(2026,7,28),日次入力!$A$4:$A$1500,"<="&DATE(2026,8,3),日次入力!$C$4:$C$1500,"Metaウェビナー")=0,"",SUMIFS(日次入力!$F$4:$F$1500,日次入力!$A$4:$A$1500,">="&DATE(2026,7,28),日次入力!$A$4:$A$1500,"<="&DATE(2026,8,3),日次入力!$C$4:$C$1500,"Metaウェビナー")) | F22: =IF(COUNTIFS(日次入力!$A$4:$A$1500,">="&DATE(2026,7,28),日次入力!$A$4:$A$1500,"<="&DATE(2026,8,3),日次入力!$C$4:$C$1500,"Metaウェビナー")=0,"",SUMIFS(日次入力!$G$4:$G$1500,日次入力!$A$4:$A$1500,">="&DATE(2026,7,28),日次入力!$A$4:$A$1500,"<="&DATE(2026,8,3),日次入力!$C$4:$C$1500,"Metaウェビナー")) | G22: =IFERROR(E22/D22,"") | H22: =IFERROR(C22/E22,"") | I22: =IFERROR(C22/D22*1000,"") | J22: =IFERROR(F22/E22,"") | K22: =IFERROR(C22/F22,"") | L22: =IF(COUNTIFS(日次入力!$A$4:$A$1500,">="&DATE(2026,7,28),日次入力!$A$4:$A$1500,"<="&DATE(2026,8,3),日次入力!$C$4:$C$1500,"Metaウェビナー")=0,"",SUMIFS(日次入力!$H$4:$H$1500,日次入力!$A$4:$A$1500,">="&DATE(2026,7,28),日次入力!$A$4:$A$1500,"<="&DATE(2026,8,3),日次入力!$C$4:$C$1500,"Metaウェビナー")) | M22: =IF(L22="","",IFERROR(L22/F22,"")) | N22: =IF(COUNTIFS(日次入力!$A$4:$A$1500,">="&DATE(2026,7,28),日次入力!$A$4:$A$1500,"<="&DATE(2026,8,3),日次入力!$C$4:$C$1500,"Metaウェビナー")=0,"",SUMIFS(日次入力!$I$4:$I$1500,日次入力!$A$4:$A$1500,">="&DATE(2026,7,28),日次入力!$A$4:$A$1500,"<="&DATE(2026,8,3),日次入力!$C$4:$C$1500,"Metaウェビナー")) | O22: =IF(N22="","",IFERROR(N22/L22,"")) | P22: =IF(N22=0,"",IFERROR(C22/N22,"")) | Q22: =IF(N22=0,"",IFERROR(IF(C22/N22<=用語集!$B$22,"◎ 許容内","✗ 超過"),"—")) -> — | R22: =IFERROR(用語集!$B$22/P22,"")
A23: W18 | B23: 8/4–8/10 | C23: =IF(COUNTIFS(日次入力!$A$4:$A$1500,">="&DATE(2026,8,4),日次入力!$A$4:$A$1500,"<="&DATE(2026,8,10),日次入力!$C$4:$C$1500,"Metaウェビナー")=0,"",SUMIFS(日次入力!$D$4:$D$1500,日次入力!$A$4:$A$1500,">="&DATE(2026,8,4),日次入力!$A$4:$A$1500,"<="&DATE(2026,8,10),日次入力!$C$4:$C$1500,"Metaウェビナー")) | D23: =IF(COUNTIFS(日次入力!$A$4:$A$1500,">="&DATE(2026,8,4),日次入力!$A$4:$A$1500,"<="&DATE(2026,8,10),日次入力!$C$4:$C$1500,"Metaウェビナー")=0,"",SUMIFS(日次入力!$E$4:$E$1500,日次入力!$A$4:$A$1500,">="&DATE(2026,8,4),日次入力!$A$4:$A$1500,"<="&DATE(2026,8,10),日次入力!$C$4:$C$1500,"Metaウェビナー")) | E23: =IF(COUNTIFS(日次入力!$A$4:$A$1500,">="&DATE(2026,8,4),日次入力!$A$4:$A$1500,"<="&DATE(2026,8,10),日次入力!$C$4:$C$1500,"Metaウェビナー")=0,"",SUMIFS(日次入力!$F$4:$F$1500,日次入力!$A$4:$A$1500,">="&DATE(2026,8,4),日次入力!$A$4:$A$1500,"<="&DATE(2026,8,10),日次入力!$C$4:$C$1500,"Metaウェビナー")) | F23: =IF(COUNTIFS(日次入力!$A$4:$A$1500,">="&DATE(2026,8,4),日次入力!$A$4:$A$1500,"<="&DATE(2026,8,10),日次入力!$C$4:$C$1500,"Metaウェビナー")=0,"",SUMIFS(日次入力!$G$4:$G$1500,日次入力!$A$4:$A$1500,">="&DATE(2026,8,4),日次入力!$A$4:$A$1500,"<="&DATE(2026,8,10),日次入力!$C$4:$C$1500,"Metaウェビナー")) | G23: =IFERROR(E23/D23,"") | H23: =IFERROR(C23/E23,"") | I23: =IFERROR(C23/D23*1000,"") | J23: =IFERROR(F23/E23,"") | K23: =IFERROR(C23/F23,"") | L23: =IF(COUNTIFS(日次入力!$A$4:$A$1500,">="&DATE(2026,8,4),日次入力!$A$4:$A$1500,"<="&DATE(2026,8,10),日次入力!$C$4:$C$1500,"Metaウェビナー")=0,"",SUMIFS(日次入力!$H$4:$H$1500,日次入力!$A$4:$A$1500,">="&DATE(2026,8,4),日次入力!$A$4:$A$1500,"<="&DATE(2026,8,10),日次入力!$C$4:$C$1500,"Metaウェビナー")) | M23: =IF(L23="","",IFERROR(L23/F23,"")) | N23: =IF(COUNTIFS(日次入力!$A$4:$A$1500,">="&DATE(2026,8,4),日次入力!$A$4:$A$1500,"<="&DATE(2026,8,10),日次入力!$C$4:$C$1500,"Metaウェビナー")=0,"",SUMIFS(日次入力!$I$4:$I$1500,日次入力!$A$4:$A$1500,">="&DATE(2026,8,4),日次入力!$A$4:$A$1500,"<="&DATE(2026,8,10),日次入力!$C$4:$C$1500,"Metaウェビナー")) | O23: =IF(N23="","",IFERROR(N23/L23,"")) | P23: =IF(N23=0,"",IFERROR(C23/N23,"")) | Q23: =IF(N23=0,"",IFERROR(IF(C23/N23<=用語集!$B$22,"◎ 許容内","✗ 超過"),"—")) -> — | R23: =IFERROR(用語集!$B$22/P23,"")
A24: W19 | B24: 8/11–8/17 | C24: =IF(COUNTIFS(日次入力!$A$4:$A$1500,">="&DATE(2026,8,11),日次入力!$A$4:$A$1500,"<="&DATE(2026,8,17),日次入力!$C$4:$C$1500,"Metaウェビナー")=0,"",SUMIFS(日次入力!$D$4:$D$1500,日次入力!$A$4:$A$1500,">="&DATE(2026,8,11),日次入力!$A$4:$A$1500,"<="&DATE(2026,8,17),日次入力!$C$4:$C$1500,"Metaウェビナー")) | D24: =IF(COUNTIFS(日次入力!$A$4:$A$1500,">="&DATE(2026,8,11),日次入力!$A$4:$A$1500,"<="&DATE(2026,8,17),日次入力!$C$4:$C$1500,"Metaウェビナー")=0,"",SUMIFS(日次入力!$E$4:$E$1500,日次入力!$A$4:$A$1500,">="&DATE(2026,8,11),日次入力!$A$4:$A$1500,"<="&DATE(2026,8,17),日次入力!$C$4:$C$1500,"Metaウェビナー")) | E24: =IF(COUNTIFS(日次入力!$A$4:$A$1500,">="&DATE(2026,8,11),日次入力!$A$4:$A$1500,"<="&DATE(2026,8,17),日次入力!$C$4:$C$1500,"Metaウェビナー")=0,"",SUMIFS(日次入力!$F$4:$F$1500,日次入力!$A$4:$A$1500,">="&DATE(2026,8,11),日次入力!$A$4:$A$1500,"<="&DATE(2026,8,17),日次入力!$C$4:$C$1500,"Metaウェビナー")) | F24: =IF(COUNTIFS(日次入力!$A$4:$A$1500,">="&DATE(2026,8,11),日次入力!$A$4:$A$1500,"<="&DATE(2026,8,17),日次入力!$C$4:$C$1500,"Metaウェビナー")=0,"",SUMIFS(日次入力!$G$4:$G$1500,日次入力!$A$4:$A$1500,">="&DATE(2026,8,11),日次入力!$A$4:$A$1500,"<="&DATE(2026,8,17),日次入力!$C$4:$C$1500,"Metaウェビナー")) | G24: =IFERROR(E24/D24,"") | H24: =IFERROR(C24/E24,"") | I24: =IFERROR(C24/D24*1000,"") | J24: =IFERROR(F24/E24,"") | K24: =IFERROR(C24/F24,"") | L24: =IF(COUNTIFS(日次入力!$A$4:$A$1500,">="&DATE(2026,8,11),日次入力!$A$4:$A$1500,"<="&DATE(2026,8,17),日次入力!$C$4:$C$1500,"Metaウェビナー")=0,"",SUMIFS(日次入力!$H$4:$H$1500,日次入力!$A$4:$A$1500,">="&DATE(2026,8,11),日次入力!$A$4:$A$1500,"<="&DATE(2026,8,17),日次入力!$C$4:$C$1500,"Metaウェビナー")) | M24: =IF(L24="","",IFERROR(L24/F24,"")) | N24: =IF(COUNTIFS(日次入力!$A$4:$A$1500,">="&DATE(2026,8,11),日次入力!$A$4:$A$1500,"<="&DATE(2026,8,17),日次入力!$C$4:$C$1500,"Metaウェビナー")=0,"",SUMIFS(日次入力!$I$4:$I$1500,日次入力!$A$4:$A$1500,">="&DATE(2026,8,11),日次入力!$A$4:$A$1500,"<="&DATE(2026,8,17),日次入力!$C$4:$C$1500,"Metaウェビナー")) | O24: =IF(N24="","",IFERROR(N24/L24,"")) | P24: =IF(N24=0,"",IFERROR(C24/N24,"")) | Q24: =IF(N24=0,"",IFERROR(IF(C24/N24<=用語集!$B$22,"◎ 許容内","✗ 超過"),"—")) -> — | R24: =IFERROR(用語集!$B$22/P24,"")
A25: W20 | B25: 8/18–8/24 | C25: =IF(COUNTIFS(日次入力!$A$4:$A$1500,">="&DATE(2026,8,18),日次入力!$A$4:$A$1500,"<="&DATE(2026,8,24),日次入力!$C$4:$C$1500,"Metaウェビナー")=0,"",SUMIFS(日次入力!$D$4:$D$1500,日次入力!$A$4:$A$1500,">="&DATE(2026,8,18),日次入力!$A$4:$A$1500,"<="&DATE(2026,8,24),日次入力!$C$4:$C$1500,"Metaウェビナー")) | D25: =IF(COUNTIFS(日次入力!$A$4:$A$1500,">="&DATE(2026,8,18),日次入力!$A$4:$A$1500,"<="&DATE(2026,8,24),日次入力!$C$4:$C$1500,"Metaウェビナー")=0,"",SUMIFS(日次入力!$E$4:$E$1500,日次入力!$A$4:$A$1500,">="&DATE(2026,8,18),日次入力!$A$4:$A$1500,"<="&DATE(2026,8,24),日次入力!$C$4:$C$1500,"Metaウェビナー")) | E25: =IF(COUNTIFS(日次入力!$A$4:$A$1500,">="&DATE(2026,8,18),日次入力!$A$4:$A$1500,"<="&DATE(2026,8,24),日次入力!$C$4:$C$1500,"Metaウェビナー")=0,"",SUMIFS(日次入力!$F$4:$F$1500,日次入力!$A$4:$A$1500,">="&DATE(2026,8,18),日次入力!$A$4:$A$1500,"<="&DATE(2026,8,24),日次入力!$C$4:$C$1500,"Metaウェビナー")) | F25: =IF(COUNTIFS(日次入力!$A$4:$A$1500,">="&DATE(2026,8,18),日次入力!$A$4:$A$1500,"<="&DATE(2026,8,24),日次入力!$C$4:$C$1500,"Metaウェビナー")=0,"",SUMIFS(日次入力!$G$4:$G$1500,日次入力!$A$4:$A$1500,">="&DATE(2026,8,18),日次入力!$A$4:$A$1500,"<="&DATE(2026,8,24),日次入力!$C$4:$C$1500,"Metaウェビナー")) | G25: =IFERROR(E25/D25,"") | H25: =IFERROR(C25/E25,"") | I25: =IFERROR(C25/D25*1000,"") | J25: =IFERROR(F25/E25,"") | K25: =IFERROR(C25/F25,"") | L25: =IF(COUNTIFS(日次入力!$A$4:$A$1500,">="&DATE(2026,8,18),日次入力!$A$4:$A$1500,"<="&DATE(2026,8,24),日次入力!$C$4:$C$1500,"Metaウェビナー")=0,"",SUMIFS(日次入力!$H$4:$H$1500,日次入力!$A$4:$A$1500,">="&DATE(2026,8,18),日次入力!$A$4:$A$1500,"<="&DATE(2026,8,24),日次入力!$C$4:$C$1500,"Metaウェビナー")) | M25: =IF(L25="","",IFERROR(L25/F25,"")) | N25: =IF(COUNTIFS(日次入力!$A$4:$A$1500,">="&DATE(2026,8,18),日次入力!$A$4:$A$1500,"<="&DATE(2026,8,24),日次入力!$C$4:$C$1500,"Metaウェビナー")=0,"",SUMIFS(日次入力!$I$4:$I$1500,日次入力!$A$4:$A$1500,">="&DATE(2026,8,18),日次入力!$A$4:$A$1500,"<="&DATE(2026,8,24),日次入力!$C$4:$C$1500,"Metaウェビナー")) | O25: =IF(N25="","",IFERROR(N25/L25,"")) | P25: =IF(N25=0,"",IFERROR(C25/N25,"")) | Q25: =IF(N25=0,"",IFERROR(IF(C25/N25<=用語集!$B$22,"◎ 許容内","✗ 超過"),"—")) -> — | R25: =IFERROR(用語集!$B$22/P25,"")
A26: W21 | B26: 8/25–8/31 | C26: =IF(COUNTIFS(日次入力!$A$4:$A$1500,">="&DATE(2026,8,25),日次入力!$A$4:$A$1500,"<="&DATE(2026,8,31),日次入力!$C$4:$C$1500,"Metaウェビナー")=0,"",SUMIFS(日次入力!$D$4:$D$1500,日次入力!$A$4:$A$1500,">="&DATE(2026,8,25),日次入力!$A$4:$A$1500,"<="&DATE(2026,8,31),日次入力!$C$4:$C$1500,"Metaウェビナー")) | D26: =IF(COUNTIFS(日次入力!$A$4:$A$1500,">="&DATE(2026,8,25),日次入力!$A$4:$A$1500,"<="&DATE(2026,8,31),日次入力!$C$4:$C$1500,"Metaウェビナー")=0,"",SUMIFS(日次入力!$E$4:$E$1500,日次入力!$A$4:$A$1500,">="&DATE(2026,8,25),日次入力!$A$4:$A$1500,"<="&DATE(2026,8,31),日次入力!$C$4:$C$1500,"Metaウェビナー")) | E26: =IF(COUNTIFS(日次入力!$A$4:$A$1500,">="&DATE(2026,8,25),日次入力!$A$4:$A$1500,"<="&DATE(2026,8,31),日次入力!$C$4:$C$1500,"Metaウェビナー")=0,"",SUMIFS(日次入力!$F$4:$F$1500,日次入力!$A$4:$A$1500,">="&DATE(2026,8,25),日次入力!$A$4:$A$1500,"<="&DATE(2026,8,31),日次入力!$C$4:$C$1500,"Metaウェビナー")) | F26: =IF(COUNTIFS(日次入力!$A$4:$A$1500,">="&DATE(2026,8,25),日次入力!$A$4:$A$1500,"<="&DATE(2026,8,31),日次入力!$C$4:$C$1500,"Metaウェビナー")=0,"",SUMIFS(日次入力!$G$4:$G$1500,日次入力!$A$4:$A$1500,">="&DATE(2026,8,25),日次入力!$A$4:$A$1500,"<="&DATE(2026,8,31),日次入力!$C$4:$C$1500,"Metaウェビナー")) | G26: =IFERROR(E26/D26,"") | H26: =IFERROR(C26/E26,"") | I26: =IFERROR(C26/D26*1000,"") | J26: =IFERROR(F26/E26,"") | K26: =IFERROR(C26/F26,"") | L26: =IF(COUNTIFS(日次入力!$A$4:$A$1500,">="&DATE(2026,8,25),日次入力!$A$4:$A$1500,"<="&DATE(2026,8,31),日次入力!$C$4:$C$1500,"Metaウェビナー")=0,"",SUMIFS(日次入力!$H$4:$H$1500,日次入力!$A$4:$A$1500,">="&DATE(2026,8,25),日次入力!$A$4:$A$1500,"<="&DATE(2026,8,31),日次入力!$C$4:$C$1500,"Metaウェビナー")) | M26: =IF(L26="","",IFERROR(L26/F26,"")) | N26: =IF(COUNTIFS(日次入力!$A$4:$A$1500,">="&DATE(2026,8,25),日次入力!$A$4:$A$1500,"<="&DATE(2026,8,31),日次入力!$C$4:$C$1500,"Metaウェビナー")=0,"",SUMIFS(日次入力!$I$4:$I$1500,日次入力!$A$4:$A$1500,">="&DATE(2026,8,25),日次入力!$A$4:$A$1500,"<="&DATE(2026,8,31),日次入力!$C$4:$C$1500,"Metaウェビナー")) | O26: =IF(N26="","",IFERROR(N26/L26,"")) | P26: =IF(N26=0,"",IFERROR(C26/N26,"")) | Q26: =IF(N26=0,"",IFERROR(IF(C26/N26<=用語集!$B$22,"◎ 許容内","✗ 超過"),"—")) -> — | R26: =IFERROR(用語集!$B$22/P26,"")
A27: W22 | B27: 9/1–9/7 | C27: =IF(COUNTIFS(日次入力!$A$4:$A$1500,">="&DATE(2026,9,1),日次入力!$A$4:$A$1500,"<="&DATE(2026,9,7),日次入力!$C$4:$C$1500,"Metaウェビナー")=0,"",SUMIFS(日次入力!$D$4:$D$1500,日次入力!$A$4:$A$1500,">="&DATE(2026,9,1),日次入力!$A$4:$A$1500,"<="&DATE(2026,9,7),日次入力!$C$4:$C$1500,"Metaウェビナー")) | D27: =IF(COUNTIFS(日次入力!$A$4:$A$1500,">="&DATE(2026,9,1),日次入力!$A$4:$A$1500,"<="&DATE(2026,9,7),日次入力!$C$4:$C$1500,"Metaウェビナー")=0,"",SUMIFS(日次入力!$E$4:$E$1500,日次入力!$A$4:$A$1500,">="&DATE(2026,9,1),日次入力!$A$4:$A$1500,"<="&DATE(2026,9,7),日次入力!$C$4:$C$1500,"Metaウェビナー")) | E27: =IF(COUNTIFS(日次入力!$A$4:$A$1500,">="&DATE(2026,9,1),日次入力!$A$4:$A$1500,"<="&DATE(2026,9,7),日次入力!$C$4:$C$1500,"Metaウェビナー")=0,"",SUMIFS(日次入力!$F$4:$F$1500,日次入力!$A$4:$A$1500,">="&DATE(2026,9,1),日次入力!$A$4:$A$1500,"<="&DATE(2026,9,7),日次入力!$C$4:$C$1500,"Metaウェビナー")) | F27: =IF(COUNTIFS(日次入力!$A$4:$A$1500,">="&DATE(2026,9,1),日次入力!$A$4:$A$1500,"<="&DATE(2026,9,7),日次入力!$C$4:$C$1500,"Metaウェビナー")=0,"",SUMIFS(日次入力!$G$4:$G$1500,日次入力!$A$4:$A$1500,">="&DATE(2026,9,1),日次入力!$A$4:$A$1500,"<="&DATE(2026,9,7),日次入力!$C$4:$C$1500,"Metaウェビナー")) | G27: =IFERROR(E27/D27,"") | H27: =IFERROR(C27/E27,"") | I27: =IFERROR(C27/D27*1000,"") | J27: =IFERROR(F27/E27,"") | K27: =IFERROR(C27/F27,"") | L27: =IF(COUNTIFS(日次入力!$A$4:$A$1500,">="&DATE(2026,9,1),日次入力!$A$4:$A$1500,"<="&DATE(2026,9,7),日次入力!$C$4:$C$1500,"Metaウェビナー")=0,"",SUMIFS(日次入力!$H$4:$H$1500,日次入力!$A$4:$A$1500,">="&DATE(2026,9,1),日次入力!$A$4:$A$1500,"<="&DATE(2026,9,7),日次入力!$C$4:$C$1500,"Metaウェビナー")) | M27: =IF(L27="","",IFERROR(L27/F27,"")) | N27: =IF(COUNTIFS(日次入力!$A$4:$A$1500,">="&DATE(2026,9,1),日次入力!$A$4:$A$1500,"<="&DATE(2026,9,7),日次入力!$C$4:$C$1500,"Metaウェビナー")=0,"",SUMIFS(日次入力!$I$4:$I$1500,日次入力!$A$4:$A$1500,">="&DATE(2026,9,1),日次入力!$A$4:$A$1500,"<="&DATE(2026,9,7),日次入力!$C$4:$C$1500,"Metaウェビナー")) | O27: =IF(N27="","",IFERROR(N27/L27,"")) | P27: =IF(N27=0,"",IFERROR(C27/N27,"")) | Q27: =IF(N27=0,"",IFERROR(IF(C27/N27<=用語集!$B$22,"◎ 許容内","✗ 超過"),"—")) -> — | R27: =IFERROR(用語集!$B$22/P27,"")
A28: W23 | B28: 9/8–9/14 | C28: =IF(COUNTIFS(日次入力!$A$4:$A$1500,">="&DATE(2026,9,8),日次入力!$A$4:$A$1500,"<="&DATE(2026,9,14),日次入力!$C$4:$C$1500,"Metaウェビナー")=0,"",SUMIFS(日次入力!$D$4:$D$1500,日次入力!$A$4:$A$1500,">="&DATE(2026,9,8),日次入力!$A$4:$A$1500,"<="&DATE(2026,9,14),日次入力!$C$4:$C$1500,"Metaウェビナー")) | D28: =IF(COUNTIFS(日次入力!$A$4:$A$1500,">="&DATE(2026,9,8),日次入力!$A$4:$A$1500,"<="&DATE(2026,9,14),日次入力!$C$4:$C$1500,"Metaウェビナー")=0,"",SUMIFS(日次入力!$E$4:$E$1500,日次入力!$A$4:$A$1500,">="&DATE(2026,9,8),日次入力!$A$4:$A$1500,"<="&DATE(2026,9,14),日次入力!$C$4:$C$1500,"Metaウェビナー")) | E28: =IF(COUNTIFS(日次入力!$A$4:$A$1500,">="&DATE(2026,9,8),日次入力!$A$4:$A$1500,"<="&DATE(2026,9,14),日次入力!$C$4:$C$1500,"Metaウェビナー")=0,"",SUMIFS(日次入力!$F$4:$F$1500,日次入力!$A$4:$A$1500,">="&DATE(2026,9,8),日次入力!$A$4:$A$1500,"<="&DATE(2026,9,14),日次入力!$C$4:$C$1500,"Metaウェビナー")) | F28: =IF(COUNTIFS(日次入力!$A$4:$A$1500,">="&DATE(2026,9,8),日次入力!$A$4:$A$1500,"<="&DATE(2026,9,14),日次入力!$C$4:$C$1500,"Metaウェビナー")=0,"",SUMIFS(日次入力!$G$4:$G$1500,日次入力!$A$4:$A$1500,">="&DATE(2026,9,8),日次入力!$A$4:$A$1500,"<="&DATE(2026,9,14),日次入力!$C$4:$C$1500,"Metaウェビナー")) | G28: =IFERROR(E28/D28,"") | H28: =IFERROR(C28/E28,"") | I28: =IFERROR(C28/D28*1000,"") | J28: =IFERROR(F28/E28,"") | K28: =IFERROR(C28/F28,"") | L28: =IF(COUNTIFS(日次入力!$A$4:$A$1500,">="&DATE(2026,9,8),日次入力!$A$4:$A$1500,"<="&DATE(2026,9,14),日次入力!$C$4:$C$1500,"Metaウェビナー")=0,"",SUMIFS(日次入力!$H$4:$H$1500,日次入力!$A$4:$A$1500,">="&DATE(2026,9,8),日次入力!$A$4:$A$1500,"<="&DATE(2026,9,14),日次入力!$C$4:$C$1500,"Metaウェビナー")) | M28: =IF(L28="","",IFERROR(L28/F28,"")) | N28: =IF(COUNTIFS(日次入力!$A$4:$A$1500,">="&DATE(2026,9,8),日次入力!$A$4:$A$1500,"<="&DATE(2026,9,14),日次入力!$C$4:$C$1500,"Metaウェビナー")=0,"",SUMIFS(日次入力!$I$4:$I$1500,日次入力!$A$4:$A$1500,">="&DATE(2026,9,8),日次入力!$A$4:$A$1500,"<="&DATE(2026,9,14),日次入力!$C$4:$C$1500,"Metaウェビナー")) | O28: =IF(N28="","",IFERROR(N28/L28,"")) | P28: =IF(N28=0,"",IFERROR(C28/N28,"")) | Q28: =IF(N28=0,"",IFERROR(IF(C28/N28<=用語集!$B$22,"◎ 許容内","✗ 超過"),"—")) -> — | R28: =IFERROR(用語集!$B$22/P28,"")
A29: W24 | B29: 9/15–9/21 | C29: =IF(COUNTIFS(日次入力!$A$4:$A$1500,">="&DATE(2026,9,15),日次入力!$A$4:$A$1500,"<="&DATE(2026,9,21),日次入力!$C$4:$C$1500,"Metaウェビナー")=0,"",SUMIFS(日次入力!$D$4:$D$1500,日次入力!$A$4:$A$1500,">="&DATE(2026,9,15),日次入力!$A$4:$A$1500,"<="&DATE(2026,9,21),日次入力!$C$4:$C$1500,"Metaウェビナー")) | D29: =IF(COUNTIFS(日次入力!$A$4:$A$1500,">="&DATE(2026,9,15),日次入力!$A$4:$A$1500,"<="&DATE(2026,9,21),日次入力!$C$4:$C$1500,"Metaウェビナー")=0,"",SUMIFS(日次入力!$E$4:$E$1500,日次入力!$A$4:$A$1500,">="&DATE(2026,9,15),日次入力!$A$4:$A$1500,"<="&DATE(2026,9,21),日次入力!$C$4:$C$1500,"Metaウェビナー")) | E29: =IF(COUNTIFS(日次入力!$A$4:$A$1500,">="&DATE(2026,9,15),日次入力!$A$4:$A$1500,"<="&DATE(2026,9,21),日次入力!$C$4:$C$1500,"Metaウェビナー")=0,"",SUMIFS(日次入力!$F$4:$F$1500,日次入力!$A$4:$A$1500,">="&DATE(2026,9,15),日次入力!$A$4:$A$1500,"<="&DATE(2026,9,21),日次入力!$C$4:$C$1500,"Metaウェビナー")) | F29: =IF(COUNTIFS(日次入力!$A$4:$A$1500,">="&DATE(2026,9,15),日次入力!$A$4:$A$1500,"<="&DATE(2026,9,21),日次入力!$C$4:$C$1500,"Metaウェビナー")=0,"",SUMIFS(日次入力!$G$4:$G$1500,日次入力!$A$4:$A$1500,">="&DATE(2026,9,15),日次入力!$A$4:$A$1500,"<="&DATE(2026,9,21),日次入力!$C$4:$C$1500,"Metaウェビナー")) | G29: =IFERROR(E29/D29,"") | H29: =IFERROR(C29/E29,"") | I29: =IFERROR(C29/D29*1000,"") | J29: =IFERROR(F29/E29,"") | K29: =IFERROR(C29/F29,"") | L29: =IF(COUNTIFS(日次入力!$A$4:$A$1500,">="&DATE(2026,9,15),日次入力!$A$4:$A$1500,"<="&DATE(2026,9,21),日次入力!$C$4:$C$1500,"Metaウェビナー")=0,"",SUMIFS(日次入力!$H$4:$H$1500,日次入力!$A$4:$A$1500,">="&DATE(2026,9,15),日次入力!$A$4:$A$1500,"<="&DATE(2026,9,21),日次入力!$C$4:$C$1500,"Metaウェビナー")) | M29: =IF(L29="","",IFERROR(L29/F29,"")) | N29: =IF(COUNTIFS(日次入力!$A$4:$A$1500,">="&DATE(2026,9,15),日次入力!$A$4:$A$1500,"<="&DATE(2026,9,21),日次入力!$C$4:$C$1500,"Metaウェビナー")=0,"",SUMIFS(日次入力!$I$4:$I$1500,日次入力!$A$4:$A$1500,">="&DATE(2026,9,15),日次入力!$A$4:$A$1500,"<="&DATE(2026,9,21),日次入力!$C$4:$C$1500,"Metaウェビナー")) | O29: =IF(N29="","",IFERROR(N29/L29,"")) | P29: =IF(N29=0,"",IFERROR(C29/N29,"")) | Q29: =IF(N29=0,"",IFERROR(IF(C29/N29<=用語集!$B$22,"◎ 許容内","✗ 超過"),"—")) -> — | R29: =IFERROR(用語集!$B$22/P29,"")
A30: W25 | B30: 9/22–9/28 | C30: =IF(COUNTIFS(日次入力!$A$4:$A$1500,">="&DATE(2026,9,22),日次入力!$A$4:$A$1500,"<="&DATE(2026,9,28),日次入力!$C$4:$C$1500,"Metaウェビナー")=0,"",SUMIFS(日次入力!$D$4:$D$1500,日次入力!$A$4:$A$1500,">="&DATE(2026,9,22),日次入力!$A$4:$A$1500,"<="&DATE(2026,9,28),日次入力!$C$4:$C$1500,"Metaウェビナー")) | D30: =IF(COUNTIFS(日次入力!$A$4:$A$1500,">="&DATE(2026,9,22),日次入力!$A$4:$A$1500,"<="&DATE(2026,9,28),日次入力!$C$4:$C$1500,"Metaウェビナー")=0,"",SUMIFS(日次入力!$E$4:$E$1500,日次入力!$A$4:$A$1500,">="&DATE(2026,9,22),日次入力!$A$4:$A$1500,"<="&DATE(2026,9,28),日次入力!$C$4:$C$1500,"Metaウェビナー")) | E30: =IF(COUNTIFS(日次入力!$A$4:$A$1500,">="&DATE(2026,9,22),日次入力!$A$4:$A$1500,"<="&DATE(2026,9,28),日次入力!$C$4:$C$1500,"Metaウェビナー")=0,"",SUMIFS(日次入力!$F$4:$F$1500,日次入力!$A$4:$A$1500,">="&DATE(2026,9,22),日次入力!$A$4:$A$1500,"<="&DATE(2026,9,28),日次入力!$C$4:$C$1500,"Metaウェビナー")) | F30: =IF(COUNTIFS(日次入力!$A$4:$A$1500,">="&DATE(2026,9,22),日次入力!$A$4:$A$1500,"<="&DATE(2026,9,28),日次入力!$C$4:$C$1500,"Metaウェビナー")=0,"",SUMIFS(日次入力!$G$4:$G$1500,日次入力!$A$4:$A$1500,">="&DATE(2026,9,22),日次入力!$A$4:$A$1500,"<="&DATE(2026,9,28),日次入力!$C$4:$C$1500,"Metaウェビナー")) | G30: =IFERROR(E30/D30,"") | H30: =IFERROR(C30/E30,"") | I30: =IFERROR(C30/D30*1000,"") | J30: =IFERROR(F30/E30,"") | K30: =IFERROR(C30/F30,"") | L30: =IF(COUNTIFS(日次入力!$A$4:$A$1500,">="&DATE(2026,9,22),日次入力!$A$4:$A$1500,"<="&DATE(2026,9,28),日次入力!$C$4:$C$1500,"Metaウェビナー")=0,"",SUMIFS(日次入力!$H$4:$H$1500,日次入力!$A$4:$A$1500,">="&DATE(2026,9,22),日次入力!$A$4:$A$1500,"<="&DATE(2026,9,28),日次入力!$C$4:$C$1500,"Metaウェビナー")) | M30: =IF(L30="","",IFERROR(L30/F30,"")) | N30: =IF(COUNTIFS(日次入力!$A$4:$A$1500,">="&DATE(2026,9,22),日次入力!$A$4:$A$1500,"<="&DATE(2026,9,28),日次入力!$C$4:$C$1500,"Metaウェビナー")=0,"",SUMIFS(日次入力!$I$4:$I$1500,日次入力!$A$4:$A$1500,">="&DATE(2026,9,22),日次入力!$A$4:$A$1500,"<="&DATE(2026,9,28),日次入力!$C$4:$C$1500,"Metaウェビナー")) | O30: =IF(N30="","",IFERROR(N30/L30,"")) | P30: =IF(N30=0,"",IFERROR(C30/N30,"")) | Q30: =IF(N30=0,"",IFERROR(IF(C30/N30<=用語集!$B$22,"◎ 許容内","✗ 超過"),"—")) -> — | R30: =IFERROR(用語集!$B$22/P30,"")
A31: W26 | B31: 9/29–10/5 | C31: =IF(COUNTIFS(日次入力!$A$4:$A$1500,">="&DATE(2026,9,29),日次入力!$A$4:$A$1500,"<="&DATE(2026,10,5),日次入力!$C$4:$C$1500,"Metaウェビナー")=0,"",SUMIFS(日次入力!$D$4:$D$1500,日次入力!$A$4:$A$1500,">="&DATE(2026,9,29),日次入力!$A$4:$A$1500,"<="&DATE(2026,10,5),日次入力!$C$4:$C$1500,"Metaウェビナー")) | D31: =IF(COUNTIFS(日次入力!$A$4:$A$1500,">="&DATE(2026,9,29),日次入力!$A$4:$A$1500,"<="&DATE(2026,10,5),日次入力!$C$4:$C$1500,"Metaウェビナー")=0,"",SUMIFS(日次入力!$E$4:$E$1500,日次入力!$A$4:$A$1500,">="&DATE(2026,9,29),日次入力!$A$4:$A$1500,"<="&DATE(2026,10,5),日次入力!$C$4:$C$1500,"Metaウェビナー")) | E31: =IF(COUNTIFS(日次入力!$A$4:$A$1500,">="&DATE(2026,9,29),日次入力!$A$4:$A$1500,"<="&DATE(2026,10,5),日次入力!$C$4:$C$1500,"Metaウェビナー")=0,"",SUMIFS(日次入力!$F$4:$F$1500,日次入力!$A$4:$A$1500,">="&DATE(2026,9,29),日次入力!$A$4:$A$1500,"<="&DATE(2026,10,5),日次入力!$C$4:$C$1500,"Metaウェビナー")) | F31: =IF(COUNTIFS(日次入力!$A$4:$A$1500,">="&DATE(2026,9,29),日次入力!$A$4:$A$1500,"<="&DATE(2026,10,5),日次入力!$C$4:$C$1500,"Metaウェビナー")=0,"",SUMIFS(日次入力!$G$4:$G$1500,日次入力!$A$4:$A$1500,">="&DATE(2026,9,29),日次入力!$A$4:$A$1500,"<="&DATE(2026,10,5),日次入力!$C$4:$C$1500,"Metaウェビナー")) | G31: =IFERROR(E31/D31,"") | H31: =IFERROR(C31/E31,"") | I31: =IFERROR(C31/D31*1000,"") | J31: =IFERROR(F31/E31,"") | K31: =IFERROR(C31/F31,"") | L31: =IF(COUNTIFS(日次入力!$A$4:$A$1500,">="&DATE(2026,9,29),日次入力!$A$4:$A$1500,"<="&DATE(2026,10,5),日次入力!$C$4:$C$1500,"Metaウェビナー")=0,"",SUMIFS(日次入力!$H$4:$H$1500,日次入力!$A$4:$A$1500,">="&DATE(2026,9,29),日次入力!$A$4:$A$1500,"<="&DATE(2026,10,5),日次入力!$C$4:$C$1500,"Metaウェビナー")) | M31: =IF(L31="","",IFERROR(L31/F31,"")) | N31: =IF(COUNTIFS(日次入力!$A$4:$A$1500,">="&DATE(2026,9,29),日次入力!$A$4:$A$1500,"<="&DATE(2026,10,5),日次入力!$C$4:$C$1500,"Metaウェビナー")=0,"",SUMIFS(日次入力!$I$4:$I$1500,日次入力!$A$4:$A$1500,">="&DATE(2026,9,29),日次入力!$A$4:$A$1500,"<="&DATE(2026,10,5),日次入力!$C$4:$C$1500,"Metaウェビナー")) | O31: =IF(N31="","",IFERROR(N31/L31,"")) | P31: =IF(N31=0,"",IFERROR(C31/N31,"")) | Q31: =IF(N31=0,"",IFERROR(IF(C31/N31<=用語集!$B$22,"◎ 許容内","✗ 超過"),"—")) -> — | R31: =IFERROR(用語集!$B$22/P31,"")
A32: W27 | B32: 10/6–10/12 | C32: =IF(COUNTIFS(日次入力!$A$4:$A$1500,">="&DATE(2026,10,6),日次入力!$A$4:$A$1500,"<="&DATE(2026,10,12),日次入力!$C$4:$C$1500,"Metaウェビナー")=0,"",SUMIFS(日次入力!$D$4:$D$1500,日次入力!$A$4:$A$1500,">="&DATE(2026,10,6),日次入力!$A$4:$A$1500,"<="&DATE(2026,10,12),日次入力!$C$4:$C$1500,"Metaウェビナー")) | D32: =IF(COUNTIFS(日次入力!$A$4:$A$1500,">="&DATE(2026,10,6),日次入力!$A$4:$A$1500,"<="&DATE(2026,10,12),日次入力!$C$4:$C$1500,"Metaウェビナー")=0,"",SUMIFS(日次入力!$E$4:$E$1500,日次入力!$A$4:$A$1500,">="&DATE(2026,10,6),日次入力!$A$4:$A$1500,"<="&DATE(2026,10,12),日次入力!$C$4:$C$1500,"Metaウェビナー")) | E32: =IF(COUNTIFS(日次入力!$A$4:$A$1500,">="&DATE(2026,10,6),日次入力!$A$4:$A$1500,"<="&DATE(2026,10,12),日次入力!$C$4:$C$1500,"Metaウェビナー")=0,"",SUMIFS(日次入力!$F$4:$F$1500,日次入力!$A$4:$A$1500,">="&DATE(2026,10,6),日次入力!$A$4:$A$1500,"<="&DATE(2026,10,12),日次入力!$C$4:$C$1500,"Metaウェビナー")) | F32: =IF(COUNTIFS(日次入力!$A$4:$A$1500,">="&DATE(2026,10,6),日次入力!$A$4:$A$1500,"<="&DATE(2026,10,12),日次入力!$C$4:$C$1500,"Metaウェビナー")=0,"",SUMIFS(日次入力!$G$4:$G$1500,日次入力!$A$4:$A$1500,">="&DATE(2026,10,6),日次入力!$A$4:$A$1500,"<="&DATE(2026,10,12),日次入力!$C$4:$C$1500,"Metaウェビナー")) | G32: =IFERROR(E32/D32,"") | H32: =IFERROR(C32/E32,"") | I32: =IFERROR(C32/D32*1000,"") | J32: =IFERROR(F32/E32,"") | K32: =IFERROR(C32/F32,"") | L32: =IF(COUNTIFS(日次入力!$A$4:$A$1500,">="&DATE(2026,10,6),日次入力!$A$4:$A$1500,"<="&DATE(2026,10,12),日次入力!$C$4:$C$1500,"Metaウェビナー")=0,"",SUMIFS(日次入力!$H$4:$H$1500,日次入力!$A$4:$A$1500,">="&DATE(2026,10,6),日次入力!$A$4:$A$1500,"<="&DATE(2026,10,12),日次入力!$C$4:$C$1500,"Metaウェビナー")) | M32: =IF(L32="","",IFERROR(L32/F32,"")) | N32: =IF(COUNTIFS(日次入力!$A$4:$A$1500,">="&DATE(2026,10,6),日次入力!$A$4:$A$1500,"<="&DATE(2026,10,12),日次入力!$C$4:$C$1500,"Metaウェビナー")=0,"",SUMIFS(日次入力!$I$4:$I$1500,日次入力!$A$4:$A$1500,">="&DATE(2026,10,6),日次入力!$A$4:$A$1500,"<="&DATE(2026,10,12),日次入力!$C$4:$C$1500,"Metaウェビナー")) | O32: =IF(N32="","",IFERROR(N32/L32,"")) | P32: =IF(N32=0,"",IFERROR(C32/N32,"")) | Q32: =IF(N32=0,"",IFERROR(IF(C32/N32<=用語集!$B$22,"◎ 許容内","✗ 超過"),"—")) -> — | R32: =IFERROR(用語集!$B$22/P32,"")
A33: W28 | B33: 10/13–10/19 | C33: =IF(COUNTIFS(日次入力!$A$4:$A$1500,">="&DATE(2026,10,13),日次入力!$A$4:$A$1500,"<="&DATE(2026,10,19),日次入力!$C$4:$C$1500,"Metaウェビナー")=0,"",SUMIFS(日次入力!$D$4:$D$1500,日次入力!$A$4:$A$1500,">="&DATE(2026,10,13),日次入力!$A$4:$A$1500,"<="&DATE(2026,10,19),日次入力!$C$4:$C$1500,"Metaウェビナー")) | D33: =IF(COUNTIFS(日次入力!$A$4:$A$1500,">="&DATE(2026,10,13),日次入力!$A$4:$A$1500,"<="&DATE(2026,10,19),日次入力!$C$4:$C$1500,"Metaウェビナー")=0,"",SUMIFS(日次入力!$E$4:$E$1500,日次入力!$A$4:$A$1500,">="&DATE(2026,10,13),日次入力!$A$4:$A$1500,"<="&DATE(2026,10,19),日次入力!$C$4:$C$1500,"Metaウェビナー")) | E33: =IF(COUNTIFS(日次入力!$A$4:$A$1500,">="&DATE(2026,10,13),日次入力!$A$4:$A$1500,"<="&DATE(2026,10,19),日次入力!$C$4:$C$1500,"Metaウェビナー")=0,"",SUMIFS(日次入力!$F$4:$F$1500,日次入力!$A$4:$A$1500,">="&DATE(2026,10,13),日次入力!$A$4:$A$1500,"<="&DATE(2026,10,19),日次入力!$C$4:$C$1500,"Metaウェビナー")) | F33: =IF(COUNTIFS(日次入力!$A$4:$A$1500,">="&DATE(2026,10,13),日次入力!$A$4:$A$1500,"<="&DATE(2026,10,19),日次入力!$C$4:$C$1500,"Metaウェビナー")=0,"",SUMIFS(日次入力!$G$4:$G$1500,日次入力!$A$4:$A$1500,">="&DATE(2026,10,13),日次入力!$A$4:$A$1500,"<="&DATE(2026,10,19),日次入力!$C$4:$C$1500,"Metaウェビナー")) | G33: =IFERROR(E33/D33,"") | H33: =IFERROR(C33/E33,"") | I33: =IFERROR(C33/D33*1000,"") | J33: =IFERROR(F33/E33,"") | K33: =IFERROR(C33/F33,"") | L33: =IF(COUNTIFS(日次入力!$A$4:$A$1500,">="&DATE(2026,10,13),日次入力!$A$4:$A$1500,"<="&DATE(2026,10,19),日次入力!$C$4:$C$1500,"Metaウェビナー")=0,"",SUMIFS(日次入力!$H$4:$H$1500,日次入力!$A$4:$A$1500,">="&DATE(2026,10,13),日次入力!$A$4:$A$1500,"<="&DATE(2026,10,19),日次入力!$C$4:$C$1500,"Metaウェビナー")) | M33: =IF(L33="","",IFERROR(L33/F33,"")) | N33: =IF(COUNTIFS(日次入力!$A$4:$A$1500,">="&DATE(2026,10,13),日次入力!$A$4:$A$1500,"<="&DATE(2026,10,19),日次入力!$C$4:$C$1500,"Metaウェビナー")=0,"",SUMIFS(日次入力!$I$4:$I$1500,日次入力!$A$4:$A$1500,">="&DATE(2026,10,13),日次入力!$A$4:$A$1500,"<="&DATE(2026,10,19),日次入力!$C$4:$C$1500,"Metaウェビナー")) | O33: =IF(N33="","",IFERROR(N33/L33,"")) | P33: =IF(N33=0,"",IFERROR(C33/N33,"")) | Q33: =IF(N33=0,"",IFERROR(IF(C33/N33<=用語集!$B$22,"◎ 許容内","✗ 超過"),"—")) -> — | R33: =IFERROR(用語集!$B$22/P33,"")
A34: W29 | B34: 10/20–10/26 | C34: =IF(COUNTIFS(日次入力!$A$4:$A$1500,">="&DATE(2026,10,20),日次入力!$A$4:$A$1500,"<="&DATE(2026,10,26),日次入力!$C$4:$C$1500,"Metaウェビナー")=0,"",SUMIFS(日次入力!$D$4:$D$1500,日次入力!$A$4:$A$1500,">="&DATE(2026,10,20),日次入力!$A$4:$A$1500,"<="&DATE(2026,10,26),日次入力!$C$4:$C$1500,"Metaウェビナー")) | D34: =IF(COUNTIFS(日次入力!$A$4:$A$1500,">="&DATE(2026,10,20),日次入力!$A$4:$A$1500,"<="&DATE(2026,10,26),日次入力!$C$4:$C$1500,"Metaウェビナー")=0,"",SUMIFS(日次入力!$E$4:$E$1500,日次入力!$A$4:$A$1500,">="&DATE(2026,10,20),日次入力!$A$4:$A$1500,"<="&DATE(2026,10,26),日次入力!$C$4:$C$1500,"Metaウェビナー")) | E34: =IF(COUNTIFS(日次入力!$A$4:$A$1500,">="&DATE(2026,10,20),日次入力!$A$4:$A$1500,"<="&DATE(2026,10,26),日次入力!$C$4:$C$1500,"Metaウェビナー")=0,"",SUMIFS(日次入力!$F$4:$F$1500,日次入力!$A$4:$A$1500,">="&DATE(2026,10,20),日次入力!$A$4:$A$1500,"<="&DATE(2026,10,26),日次入力!$C$4:$C$1500,"Metaウェビナー")) | F34: =IF(COUNTIFS(日次入力!$A$4:$A$1500,">="&DATE(2026,10,20),日次入力!$A$4:$A$1500,"<="&DATE(2026,10,26),日次入力!$C$4:$C$1500,"Metaウェビナー")=0,"",SUMIFS(日次入力!$G$4:$G$1500,日次入力!$A$4:$A$1500,">="&DATE(2026,10,20),日次入力!$A$4:$A$1500,"<="&DATE(2026,10,26),日次入力!$C$4:$C$1500,"Metaウェビナー")) | G34: =IFERROR(E34/D34,"") | H34: =IFERROR(C34/E34,"") | I34: =IFERROR(C34/D34*1000,"") | J34: =IFERROR(F34/E34,"") | K34: =IFERROR(C34/F34,"") | L34: =IF(COUNTIFS(日次入力!$A$4:$A$1500,">="&DATE(2026,10,20),日次入力!$A$4:$A$1500,"<="&DATE(2026,10,26),日次入力!$C$4:$C$1500,"Metaウェビナー")=0,"",SUMIFS(日次入力!$H$4:$H$1500,日次入力!$A$4:$A$1500,">="&DATE(2026,10,20),日次入力!$A$4:$A$1500,"<="&DATE(2026,10,26),日次入力!$C$4:$C$1500,"Metaウェビナー")) | M34: =IF(L34="","",IFERROR(L34/F34,"")) | N34: =IF(COUNTIFS(日次入力!$A$4:$A$1500,">="&DATE(2026,10,20),日次入力!$A$4:$A$1500,"<="&DATE(2026,10,26),日次入力!$C$4:$C$1500,"Metaウェビナー")=0,"",SUMIFS(日次入力!$I$4:$I$1500,日次入力!$A$4:$A$1500,">="&DATE(2026,10,20),日次入力!$A$4:$A$1500,"<="&DATE(2026,10,26),日次入力!$C$4:$C$1500,"Metaウェビナー")) | O34: =IF(N34="","",IFERROR(N34/L34,"")) | P34: =IF(N34=0,"",IFERROR(C34/N34,"")) | Q34: =IF(N34=0,"",IFERROR(IF(C34/N34<=用語集!$B$22,"◎ 許容内","✗ 超過"),"—")) -> — | R34: =IFERROR(用語集!$B$22/P34,"")
A35: W30 | B35: 10/27–11/2 | C35: =IF(COUNTIFS(日次入力!$A$4:$A$1500,">="&DATE(2026,10,27),日次入力!$A$4:$A$1500,"<="&DATE(2026,11,2),日次入力!$C$4:$C$1500,"Metaウェビナー")=0,"",SUMIFS(日次入力!$D$4:$D$1500,日次入力!$A$4:$A$1500,">="&DATE(2026,10,27),日次入力!$A$4:$A$1500,"<="&DATE(2026,11,2),日次入力!$C$4:$C$1500,"Metaウェビナー")) | D35: =IF(COUNTIFS(日次入力!$A$4:$A$1500,">="&DATE(2026,10,27),日次入力!$A$4:$A$1500,"<="&DATE(2026,11,2),日次入力!$C$4:$C$1500,"Metaウェビナー")=0,"",SUMIFS(日次入力!$E$4:$E$1500,日次入力!$A$4:$A$1500,">="&DATE(2026,10,27),日次入力!$A$4:$A$1500,"<="&DATE(2026,11,2),日次入力!$C$4:$C$1500,"Metaウェビナー")) | E35: =IF(COUNTIFS(日次入力!$A$4:$A$1500,">="&DATE(2026,10,27),日次入力!$A$4:$A$1500,"<="&DATE(2026,11,2),日次入力!$C$4:$C$1500,"Metaウェビナー")=0,"",SUMIFS(日次入力!$F$4:$F$1500,日次入力!$A$4:$A$1500,">="&DATE(2026,10,27),日次入力!$A$4:$A$1500,"<="&DATE(2026,11,2),日次入力!$C$4:$C$1500,"Metaウェビナー")) | F35: =IF(COUNTIFS(日次入力!$A$4:$A$1500,">="&DATE(2026,10,27),日次入力!$A$4:$A$1500,"<="&DATE(2026,11,2),日次入力!$C$4:$C$1500,"Metaウェビナー")=0,"",SUMIFS(日次入力!$G$4:$G$1500,日次入力!$A$4:$A$1500,">="&DATE(2026,10,27),日次入力!$A$4:$A$1500,"<="&DATE(2026,11,2),日次入力!$C$4:$C$1500,"Metaウェビナー")) | G35: =IFERROR(E35/D35,"") | H35: =IFERROR(C35/E35,"") | I35: =IFERROR(C35/D35*1000,"") | J35: =IFERROR(F35/E35,"") | K35: =IFERROR(C35/F35,"") | L35: =IF(COUNTIFS(日次入力!$A$4:$A$1500,">="&DATE(2026,10,27),日次入力!$A$4:$A$1500,"<="&DATE(2026,11,2),日次入力!$C$4:$C$1500,"Metaウェビナー")=0,"",SUMIFS(日次入力!$H$4:$H$1500,日次入力!$A$4:$A$1500,">="&DATE(2026,10,27),日次入力!$A$4:$A$1500,"<="&DATE(2026,11,2),日次入力!$C$4:$C$1500,"Metaウェビナー")) | M35: =IF(L35="","",IFERROR(L35/F35,"")) | N35: =IF(COUNTIFS(日次入力!$A$4:$A$1500,">="&DATE(2026,10,27),日次入力!$A$4:$A$1500,"<="&DATE(2026,11,2),日次入力!$C$4:$C$1500,"Metaウェビナー")=0,"",SUMIFS(日次入力!$I$4:$I$1500,日次入力!$A$4:$A$1500,">="&DATE(2026,10,27),日次入力!$A$4:$A$1500,"<="&DATE(2026,11,2),日次入力!$C$4:$C$1500,"Metaウェビナー")) | O35: =IF(N35="","",IFERROR(N35/L35,"")) | P35: =IF(N35=0,"",IFERROR(C35/N35,"")) | Q35: =IF(N35=0,"",IFERROR(IF(C35/N35<=用語集!$B$22,"◎ 許容内","✗ 超過"),"—")) -> — | R35: =IFERROR(用語集!$B$22/P35,"")
A36: W31 | B36: 11/3–11/9 | C36: =IF(COUNTIFS(日次入力!$A$4:$A$1500,">="&DATE(2026,11,3),日次入力!$A$4:$A$1500,"<="&DATE(2026,11,9),日次入力!$C$4:$C$1500,"Metaウェビナー")=0,"",SUMIFS(日次入力!$D$4:$D$1500,日次入力!$A$4:$A$1500,">="&DATE(2026,11,3),日次入力!$A$4:$A$1500,"<="&DATE(2026,11,9),日次入力!$C$4:$C$1500,"Metaウェビナー")) | D36: =IF(COUNTIFS(日次入力!$A$4:$A$1500,">="&DATE(2026,11,3),日次入力!$A$4:$A$1500,"<="&DATE(2026,11,9),日次入力!$C$4:$C$1500,"Metaウェビナー")=0,"",SUMIFS(日次入力!$E$4:$E$1500,日次入力!$A$4:$A$1500,">="&DATE(2026,11,3),日次入力!$A$4:$A$1500,"<="&DATE(2026,11,9),日次入力!$C$4:$C$1500,"Metaウェビナー")) | E36: =IF(COUNTIFS(日次入力!$A$4:$A$1500,">="&DATE(2026,11,3),日次入力!$A$4:$A$1500,"<="&DATE(2026,11,9),日次入力!$C$4:$C$1500,"Metaウェビナー")=0,"",SUMIFS(日次入力!$F$4:$F$1500,日次入力!$A$4:$A$1500,">="&DATE(2026,11,3),日次入力!$A$4:$A$1500,"<="&DATE(2026,11,9),日次入力!$C$4:$C$1500,"Metaウェビナー")) | F36: =IF(COUNTIFS(日次入力!$A$4:$A$1500,">="&DATE(2026,11,3),日次入力!$A$4:$A$1500,"<="&DATE(2026,11,9),日次入力!$C$4:$C$1500,"Metaウェビナー")=0,"",SUMIFS(日次入力!$G$4:$G$1500,日次入力!$A$4:$A$1500,">="&DATE(2026,11,3),日次入力!$A$4:$A$1500,"<="&DATE(2026,11,9),日次入力!$C$4:$C$1500,"Metaウェビナー")) | G36: =IFERROR(E36/D36,"") | H36: =IFERROR(C36/E36,"") | I36: =IFERROR(C36/D36*1000,"") | J36: =IFERROR(F36/E36,"") | K36: =IFERROR(C36/F36,"") | L36: =IF(COUNTIFS(日次入力!$A$4:$A$1500,">="&DATE(2026,11,3),日次入力!$A$4:$A$1500,"<="&DATE(2026,11,9),日次入力!$C$4:$C$1500,"Metaウェビナー")=0,"",SUMIFS(日次入力!$H$4:$H$1500,日次入力!$A$4:$A$1500,">="&DATE(2026,11,3),日次入力!$A$4:$A$1500,"<="&DATE(2026,11,9),日次入力!$C$4:$C$1500,"Metaウェビナー")) | M36: =IF(L36="","",IFERROR(L36/F36,"")) | N36: =IF(COUNTIFS(日次入力!$A$4:$A$1500,">="&DATE(2026,11,3),日次入力!$A$4:$A$1500,"<="&DATE(2026,11,9),日次入力!$C$4:$C$1500,"Metaウェビナー")=0,"",SUMIFS(日次入力!$I$4:$I$1500,日次入力!$A$4:$A$1500,">="&DATE(2026,11,3),日次入力!$A$4:$A$1500,"<="&DATE(2026,11,9),日次入力!$C$4:$C$1500,"Metaウェビナー")) | O36: =IF(N36="","",IFERROR(N36/L36,"")) | P36: =IF(N36=0,"",IFERROR(C36/N36,"")) | Q36: =IF(N36=0,"",IFERROR(IF(C36/N36<=用語集!$B$22,"◎ 許容内","✗ 超過"),"—")) -> — | R36: =IFERROR(用語集!$B$22/P36,"")
A37: W32 | B37: 11/10–11/16 | C37: =IF(COUNTIFS(日次入力!$A$4:$A$1500,">="&DATE(2026,11,10),日次入力!$A$4:$A$1500,"<="&DATE(2026,11,16),日次入力!$C$4:$C$1500,"Metaウェビナー")=0,"",SUMIFS(日次入力!$D$4:$D$1500,日次入力!$A$4:$A$1500,">="&DATE(2026,11,10),日次入力!$A$4:$A$1500,"<="&DATE(2026,11,16),日次入力!$C$4:$C$1500,"Metaウェビナー")) | D37: =IF(COUNTIFS(日次入力!$A$4:$A$1500,">="&DATE(2026,11,10),日次入力!$A$4:$A$1500,"<="&DATE(2026,11,16),日次入力!$C$4:$C$1500,"Metaウェビナー")=0,"",SUMIFS(日次入力!$E$4:$E$1500,日次入力!$A$4:$A$1500,">="&DATE(2026,11,10),日次入力!$A$4:$A$1500,"<="&DATE(2026,11,16),日次入力!$C$4:$C$1500,"Metaウェビナー")) | E37: =IF(COUNTIFS(日次入力!$A$4:$A$1500,">="&DATE(2026,11,10),日次入力!$A$4:$A$1500,"<="&DATE(2026,11,16),日次入力!$C$4:$C$1500,"Metaウェビナー")=0,"",SUMIFS(日次入力!$F$4:$F$1500,日次入力!$A$4:$A$1500,">="&DATE(2026,11,10),日次入力!$A$4:$A$1500,"<="&DATE(2026,11,16),日次入力!$C$4:$C$1500,"Metaウェビナー")) | F37: =IF(COUNTIFS(日次入力!$A$4:$A$1500,">="&DATE(2026,11,10),日次入力!$A$4:$A$1500,"<="&DATE(2026,11,16),日次入力!$C$4:$C$1500,"Metaウェビナー")=0,"",SUMIFS(日次入力!$G$4:$G$1500,日次入力!$A$4:$A$1500,">="&DATE(2026,11,10),日次入力!$A$4:$A$1500,"<="&DATE(2026,11,16),日次入力!$C$4:$C$1500,"Metaウェビナー")) | G37: =IFERROR(E37/D37,"") | H37: =IFERROR(C37/E37,"") | I37: =IFERROR(C37/D37*1000,"") | J37: =IFERROR(F37/E37,"") | K37: =IFERROR(C37/F37,"") | L37: =IF(COUNTIFS(日次入力!$A$4:$A$1500,">="&DATE(2026,11,10),日次入力!$A$4:$A$1500,"<="&DATE(2026,11,16),日次入力!$C$4:$C$1500,"Metaウェビナー")=0,"",SUMIFS(日次入力!$H$4:$H$1500,日次入力!$A$4:$A$1500,">="&DATE(2026,11,10),日次入力!$A$4:$A$1500,"<="&DATE(2026,11,16),日次入力!$C$4:$C$1500,"Metaウェビナー")) | M37: =IF(L37="","",IFERROR(L37/F37,"")) | N37: =IF(COUNTIFS(日次入力!$A$4:$A$1500,">="&DATE(2026,11,10),日次入力!$A$4:$A$1500,"<="&DATE(2026,11,16),日次入力!$C$4:$C$1500,"Metaウェビナー")=0,"",SUMIFS(日次入力!$I$4:$I$1500,日次入力!$A$4:$A$1500,">="&DATE(2026,11,10),日次入力!$A$4:$A$1500,"<="&DATE(2026,11,16),日次入力!$C$4:$C$1500,"Metaウェビナー")) | O37: =IF(N37="","",IFERROR(N37/L37,"")) | P37: =IF(N37=0,"",IFERROR(C37/N37,"")) | Q37: =IF(N37=0,"",IFERROR(IF(C37/N37<=用語集!$B$22,"◎ 許容内","✗ 超過"),"—")) -> — | R37: =IFERROR(用語集!$B$22/P37,"")
A38: W33 | B38: 11/17–11/23 | C38: =IF(COUNTIFS(日次入力!$A$4:$A$1500,">="&DATE(2026,11,17),日次入力!$A$4:$A$1500,"<="&DATE(2026,11,23),日次入力!$C$4:$C$1500,"Metaウェビナー")=0,"",SUMIFS(日次入力!$D$4:$D$1500,日次入力!$A$4:$A$1500,">="&DATE(2026,11,17),日次入力!$A$4:$A$1500,"<="&DATE(2026,11,23),日次入力!$C$4:$C$1500,"Metaウェビナー")) | D38: =IF(COUNTIFS(日次入力!$A$4:$A$1500,">="&DATE(2026,11,17),日次入力!$A$4:$A$1500,"<="&DATE(2026,11,23),日次入力!$C$4:$C$1500,"Metaウェビナー")=0,"",SUMIFS(日次入力!$E$4:$E$1500,日次入力!$A$4:$A$1500,">="&DATE(2026,11,17),日次入力!$A$4:$A$1500,"<="&DATE(2026,11,23),日次入力!$C$4:$C$1500,"Metaウェビナー")) | E38: =IF(COUNTIFS(日次入力!$A$4:$A$1500,">="&DATE(2026,11,17),日次入力!$A$4:$A$1500,"<="&DATE(2026,11,23),日次入力!$C$4:$C$1500,"Metaウェビナー")=0,"",SUMIFS(日次入力!$F$4:$F$1500,日次入力!$A$4:$A$1500,">="&DATE(2026,11,17),日次入力!$A$4:$A$1500,"<="&DATE(2026,11,23),日次入力!$C$4:$C$1500,"Metaウェビナー")) | F38: =IF(COUNTIFS(日次入力!$A$4:$A$1500,">="&DATE(2026,11,17),日次入力!$A$4:$A$1500,"<="&DATE(2026,11,23),日次入力!$C$4:$C$1500,"Metaウェビナー")=0,"",SUMIFS(日次入力!$G$4:$G$1500,日次入力!$A$4:$A$1500,">="&DATE(2026,11,17),日次入力!$A$4:$A$1500,"<="&DATE(2026,11,23),日次入力!$C$4:$C$1500,"Metaウェビナー")) | G38: =IFERROR(E38/D38,"") | H38: =IFERROR(C38/E38,"") | I38: =IFERROR(C38/D38*1000,"") | J38: =IFERROR(F38/E38,"") | K38: =IFERROR(C38/F38,"") | L38: =IF(COUNTIFS(日次入力!$A$4:$A$1500,">="&DATE(2026,11,17),日次入力!$A$4:$A$1500,"<="&DATE(2026,11,23),日次入力!$C$4:$C$1500,"Metaウェビナー")=0,"",SUMIFS(日次入力!$H$4:$H$1500,日次入力!$A$4:$A$1500,">="&DATE(2026,11,17),日次入力!$A$4:$A$1500,"<="&DATE(2026,11,23),日次入力!$C$4:$C$1500,"Metaウェビナー")) | M38: =IF(L38="","",IFERROR(L38/F38,"")) | N38: =IF(COUNTIFS(日次入力!$A$4:$A$1500,">="&DATE(2026,11,17),日次入力!$A$4:$A$1500,"<="&DATE(2026,11,23),日次入力!$C$4:$C$1500,"Metaウェビナー")=0,"",SUMIFS(日次入力!$I$4:$I$1500,日次入力!$A$4:$A$1500,">="&DATE(2026,11,17),日次入力!$A$4:$A$1500,"<="&DATE(2026,11,23),日次入力!$C$4:$C$1500,"Metaウェビナー")) | O38: =IF(N38="","",IFERROR(N38/L38,"")) | P38: =IF(N38=0,"",IFERROR(C38/N38,"")) | Q38: =IF(N38=0,"",IFERROR(IF(C38/N38<=用語集!$B$22,"◎ 許容内","✗ 超過"),"—")) -> — | R38: =IFERROR(用語集!$B$22/P38,"")
A39: W34 | B39: 11/24–11/30 | C39: =IF(COUNTIFS(日次入力!$A$4:$A$1500,">="&DATE(2026,11,24),日次入力!$A$4:$A$1500,"<="&DATE(2026,11,30),日次入力!$C$4:$C$1500,"Metaウェビナー")=0,"",SUMIFS(日次入力!$D$4:$D$1500,日次入力!$A$4:$A$1500,">="&DATE(2026,11,24),日次入力!$A$4:$A$1500,"<="&DATE(2026,11,30),日次入力!$C$4:$C$1500,"Metaウェビナー")) | D39: =IF(COUNTIFS(日次入力!$A$4:$A$1500,">="&DATE(2026,11,24),日次入力!$A$4:$A$1500,"<="&DATE(2026,11,30),日次入力!$C$4:$C$1500,"Metaウェビナー")=0,"",SUMIFS(日次入力!$E$4:$E$1500,日次入力!$A$4:$A$1500,">="&DATE(2026,11,24),日次入力!$A$4:$A$1500,"<="&DATE(2026,11,30),日次入力!$C$4:$C$1500,"Metaウェビナー")) | E39: =IF(COUNTIFS(日次入力!$A$4:$A$1500,">="&DATE(2026,11,24),日次入力!$A$4:$A$1500,"<="&DATE(2026,11,30),日次入力!$C$4:$C$1500,"Metaウェビナー")=0,"",SUMIFS(日次入力!$F$4:$F$1500,日次入力!$A$4:$A$1500,">="&DATE(2026,11,24),日次入力!$A$4:$A$1500,"<="&DATE(2026,11,30),日次入力!$C$4:$C$1500,"Metaウェビナー")) | F39: =IF(COUNTIFS(日次入力!$A$4:$A$1500,">="&DATE(2026,11,24),日次入力!$A$4:$A$1500,"<="&DATE(2026,11,30),日次入力!$C$4:$C$1500,"Metaウェビナー")=0,"",SUMIFS(日次入力!$G$4:$G$1500,日次入力!$A$4:$A$1500,">="&DATE(2026,11,24),日次入力!$A$4:$A$1500,"<="&DATE(2026,11,30),日次入力!$C$4:$C$1500,"Metaウェビナー")) | G39: =IFERROR(E39/D39,"") | H39: =IFERROR(C39/E39,"") | I39: =IFERROR(C39/D39*1000,"") | J39: =IFERROR(F39/E39,"") | K39: =IFERROR(C39/F39,"") | L39: =IF(COUNTIFS(日次入力!$A$4:$A$1500,">="&DATE(2026,11,24),日次入力!$A$4:$A$1500,"<="&DATE(2026,11,30),日次入力!$C$4:$C$1500,"Metaウェビナー")=0,"",SUMIFS(日次入力!$H$4:$H$1500,日次入力!$A$4:$A$1500,">="&DATE(2026,11,24),日次入力!$A$4:$A$1500,"<="&DATE(2026,11,30),日次入力!$C$4:$C$1500,"Metaウェビナー")) | M39: =IF(L39="","",IFERROR(L39/F39,"")) | N39: =IF(COUNTIFS(日次入力!$A$4:$A$1500,">="&DATE(2026,11,24),日次入力!$A$4:$A$1500,"<="&DATE(2026,11,30),日次入力!$C$4:$C$1500,"Metaウェビナー")=0,"",SUMIFS(日次入力!$I$4:$I$1500,日次入力!$A$4:$A$1500,">="&DATE(2026,11,24),日次入力!$A$4:$A$1500,"<="&DATE(2026,11,30),日次入力!$C$4:$C$1500,"Metaウェビナー")) | O39: =IF(N39="","",IFERROR(N39/L39,"")) | P39: =IF(N39=0,"",IFERROR(C39/N39,"")) | Q39: =IF(N39=0,"",IFERROR(IF(C39/N39<=用語集!$B$22,"◎ 許容内","✗ 超過"),"—")) -> — | R39: =IFERROR(用語集!$B$22/P39,"")
A40: W35 | B40: 12/1–12/7 | C40: =IF(COUNTIFS(日次入力!$A$4:$A$1500,">="&DATE(2026,12,1),日次入力!$A$4:$A$1500,"<="&DATE(2026,12,7),日次入力!$C$4:$C$1500,"Metaウェビナー")=0,"",SUMIFS(日次入力!$D$4:$D$1500,日次入力!$A$4:$A$1500,">="&DATE(2026,12,1),日次入力!$A$4:$A$1500,"<="&DATE(2026,12,7),日次入力!$C$4:$C$1500,"Metaウェビナー")) | D40: =IF(COUNTIFS(日次入力!$A$4:$A$1500,">="&DATE(2026,12,1),日次入力!$A$4:$A$1500,"<="&DATE(2026,12,7),日次入力!$C$4:$C$1500,"Metaウェビナー")=0,"",SUMIFS(日次入力!$E$4:$E$1500,日次入力!$A$4:$A$1500,">="&DATE(2026,12,1),日次入力!$A$4:$A$1500,"<="&DATE(2026,12,7),日次入力!$C$4:$C$1500,"Metaウェビナー")) | E40: =IF(COUNTIFS(日次入力!$A$4:$A$1500,">="&DATE(2026,12,1),日次入力!$A$4:$A$1500,"<="&DATE(2026,12,7),日次入力!$C$4:$C$1500,"Metaウェビナー")=0,"",SUMIFS(日次入力!$F$4:$F$1500,日次入力!$A$4:$A$1500,">="&DATE(2026,12,1),日次入力!$A$4:$A$1500,"<="&DATE(2026,12,7),日次入力!$C$4:$C$1500,"Metaウェビナー")) | F40: =IF(COUNTIFS(日次入力!$A$4:$A$1500,">="&DATE(2026,12,1),日次入力!$A$4:$A$1500,"<="&DATE(2026,12,7),日次入力!$C$4:$C$1500,"Metaウェビナー")=0,"",SUMIFS(日次入力!$G$4:$G$1500,日次入力!$A$4:$A$1500,">="&DATE(2026,12,1),日次入力!$A$4:$A$1500,"<="&DATE(2026,12,7),日次入力!$C$4:$C$1500,"Metaウェビナー")) | G40: =IFERROR(E40/D40,"") | H40: =IFERROR(C40/E40,"") | I40: =IFERROR(C40/D40*1000,"") | J40: =IFERROR(F40/E40,"") | K40: =IFERROR(C40/F40,"") | L40: =IF(COUNTIFS(日次入力!$A$4:$A$1500,">="&DATE(2026,12,1),日次入力!$A$4:$A$1500,"<="&DATE(2026,12,7),日次入力!$C$4:$C$1500,"Metaウェビナー")=0,"",SUMIFS(日次入力!$H$4:$H$1500,日次入力!$A$4:$A$1500,">="&DATE(2026,12,1),日次入力!$A$4:$A$1500,"<="&DATE(2026,12,7),日次入力!$C$4:$C$1500,"Metaウェビナー")) | M40: =IF(L40="","",IFERROR(L40/F40,"")) | N40: =IF(COUNTIFS(日次入力!$A$4:$A$1500,">="&DATE(2026,12,1),日次入力!$A$4:$A$1500,"<="&DATE(2026,12,7),日次入力!$C$4:$C$1500,"Metaウェビナー")=0,"",SUMIFS(日次入力!$I$4:$I$1500,日次入力!$A$4:$A$1500,">="&DATE(2026,12,1),日次入力!$A$4:$A$1500,"<="&DATE(2026,12,7),日次入力!$C$4:$C$1500,"Metaウェビナー")) | O40: =IF(N40="","",IFERROR(N40/L40,"")) | P40: =IF(N40=0,"",IFERROR(C40/N40,"")) | Q40: =IF(N40=0,"",IFERROR(IF(C40/N40<=用語集!$B$22,"◎ 許容内","✗ 超過"),"—")) -> — | R40: =IFERROR(用語集!$B$22/P40,"")
A41: W36 | B41: 12/8–12/14 | C41: =IF(COUNTIFS(日次入力!$A$4:$A$1500,">="&DATE(2026,12,8),日次入力!$A$4:$A$1500,"<="&DATE(2026,12,14),日次入力!$C$4:$C$1500,"Metaウェビナー")=0,"",SUMIFS(日次入力!$D$4:$D$1500,日次入力!$A$4:$A$1500,">="&DATE(2026,12,8),日次入力!$A$4:$A$1500,"<="&DATE(2026,12,14),日次入力!$C$4:$C$1500,"Metaウェビナー")) | D41: =IF(COUNTIFS(日次入力!$A$4:$A$1500,">="&DATE(2026,12,8),日次入力!$A$4:$A$1500,"<="&DATE(2026,12,14),日次入力!$C$4:$C$1500,"Metaウェビナー")=0,"",SUMIFS(日次入力!$E$4:$E$1500,日次入力!$A$4:$A$1500,">="&DATE(2026,12,8),日次入力!$A$4:$A$1500,"<="&DATE(2026,12,14),日次入力!$C$4:$C$1500,"Metaウェビナー")) | E41: =IF(COUNTIFS(日次入力!$A$4:$A$1500,">="&DATE(2026,12,8),日次入力!$A$4:$A$1500,"<="&DATE(2026,12,14),日次入力!$C$4:$C$1500,"Metaウェビナー")=0,"",SUMIFS(日次入力!$F$4:$F$1500,日次入力!$A$4:$A$1500,">="&DATE(2026,12,8),日次入力!$A$4:$A$1500,"<="&DATE(2026,12,14),日次入力!$C$4:$C$1500,"Metaウェビナー")) | F41: =IF(COUNTIFS(日次入力!$A$4:$A$1500,">="&DATE(2026,12,8),日次入力!$A$4:$A$1500,"<="&DATE(2026,12,14),日次入力!$C$4:$C$1500,"Metaウェビナー")=0,"",SUMIFS(日次入力!$G$4:$G$1500,日次入力!$A$4:$A$1500,">="&DATE(2026,12,8),日次入力!$A$4:$A$1500,"<="&DATE(2026,12,14),日次入力!$C$4:$C$1500,"Metaウェビナー")) | G41: =IFERROR(E41/D41,"") | H41: =IFERROR(C41/E41,"") | I41: =IFERROR(C41/D41*1000,"") | J41: =IFERROR(F41/E41,"") | K41: =IFERROR(C41/F41,"") | L41: =IF(COUNTIFS(日次入力!$A$4:$A$1500,">="&DATE(2026,12,8),日次入力!$A$4:$A$1500,"<="&DATE(2026,12,14),日次入力!$C$4:$C$1500,"Metaウェビナー")=0,"",SUMIFS(日次入力!$H$4:$H$1500,日次入力!$A$4:$A$1500,">="&DATE(2026,12,8),日次入力!$A$4:$A$1500,"<="&DATE(2026,12,14),日次入力!$C$4:$C$1500,"Metaウェビナー")) | M41: =IF(L41="","",IFERROR(L41/F41,"")) | N41: =IF(COUNTIFS(日次入力!$A$4:$A$1500,">="&DATE(2026,12,8),日次入力!$A$4:$A$1500,"<="&DATE(2026,12,14),日次入力!$C$4:$C$1500,"Metaウェビナー")=0,"",SUMIFS(日次入力!$I$4:$I$1500,日次入力!$A$4:$A$1500,">="&DATE(2026,12,8),日次入力!$A$4:$A$1500,"<="&DATE(2026,12,14),日次入力!$C$4:$C$1500,"Metaウェビナー")) | O41: =IF(N41="","",IFERROR(N41/L41,"")) | P41: =IF(N41=0,"",IFERROR(C41/N41,"")) | Q41: =IF(N41=0,"",IFERROR(IF(C41/N41<=用語集!$B$22,"◎ 許容内","✗ 超過"),"—")) -> — | R41: =IFERROR(用語集!$B$22/P41,"")
A42: W37 | B42: 12/15–12/21 | C42: =IF(COUNTIFS(日次入力!$A$4:$A$1500,">="&DATE(2026,12,15),日次入力!$A$4:$A$1500,"<="&DATE(2026,12,21),日次入力!$C$4:$C$1500,"Metaウェビナー")=0,"",SUMIFS(日次入力!$D$4:$D$1500,日次入力!$A$4:$A$1500,">="&DATE(2026,12,15),日次入力!$A$4:$A$1500,"<="&DATE(2026,12,21),日次入力!$C$4:$C$1500,"Metaウェビナー")) | D42: =IF(COUNTIFS(日次入力!$A$4:$A$1500,">="&DATE(2026,12,15),日次入力!$A$4:$A$1500,"<="&DATE(2026,12,21),日次入力!$C$4:$C$1500,"Metaウェビナー")=0,"",SUMIFS(日次入力!$E$4:$E$1500,日次入力!$A$4:$A$1500,">="&DATE(2026,12,15),日次入力!$A$4:$A$1500,"<="&DATE(2026,12,21),日次入力!$C$4:$C$1500,"Metaウェビナー")) | E42: =IF(COUNTIFS(日次入力!$A$4:$A$1500,">="&DATE(2026,12,15),日次入力!$A$4:$A$1500,"<="&DATE(2026,12,21),日次入力!$C$4:$C$1500,"Metaウェビナー")=0,"",SUMIFS(日次入力!$F$4:$F$1500,日次入力!$A$4:$A$1500,">="&DATE(2026,12,15),日次入力!$A$4:$A$1500,"<="&DATE(2026,12,21),日次入力!$C$4:$C$1500,"Metaウェビナー")) | F42: =IF(COUNTIFS(日次入力!$A$4:$A$1500,">="&DATE(2026,12,15),日次入力!$A$4:$A$1500,"<="&DATE(2026,12,21),日次入力!$C$4:$C$1500,"Metaウェビナー")=0,"",SUMIFS(日次入力!$G$4:$G$1500,日次入力!$A$4:$A$1500,">="&DATE(2026,12,15),日次入力!$A$4:$A$1500,"<="&DATE(2026,12,21),日次入力!$C$4:$C$1500,"Metaウェビナー")) | G42: =IFERROR(E42/D42,"") | H42: =IFERROR(C42/E42,"") | I42: =IFERROR(C42/D42*1000,"") | J42: =IFERROR(F42/E42,"") | K42: =IFERROR(C42/F42,"") | L42: =IF(COUNTIFS(日次入力!$A$4:$A$1500,">="&DATE(2026,12,15),日次入力!$A$4:$A$1500,"<="&DATE(2026,12,21),日次入力!$C$4:$C$1500,"Metaウェビナー")=0,"",SUMIFS(日次入力!$H$4:$H$1500,日次入力!$A$4:$A$1500,">="&DATE(2026,12,15),日次入力!$A$4:$A$1500,"<="&DATE(2026,12,21),日次入力!$C$4:$C$1500,"Metaウェビナー")) | M42: =IF(L42="","",IFERROR(L42/F42,"")) | N42: =IF(COUNTIFS(日次入力!$A$4:$A$1500,">="&DATE(2026,12,15),日次入力!$A$4:$A$1500,"<="&DATE(2026,12,21),日次入力!$C$4:$C$1500,"Metaウェビナー")=0,"",SUMIFS(日次入力!$I$4:$I$1500,日次入力!$A$4:$A$1500,">="&DATE(2026,12,15),日次入力!$A$4:$A$1500,"<="&DATE(2026,12,21),日次入力!$C$4:$C$1500,"Metaウェビナー")) | O42: =IF(N42="","",IFERROR(N42/L42,"")) | P42: =IF(N42=0,"",IFERROR(C42/N42,"")) | Q42: =IF(N42=0,"",IFERROR(IF(C42/N42<=用語集!$B$22,"◎ 許容内","✗ 超過"),"—")) -> — | R42: =IFERROR(用語集!$B$22/P42,"")
A43: W38 | B43: 12/22–12/28 | C43: =IF(COUNTIFS(日次入力!$A$4:$A$1500,">="&DATE(2026,12,22),日次入力!$A$4:$A$1500,"<="&DATE(2026,12,28),日次入力!$C$4:$C$1500,"Metaウェビナー")=0,"",SUMIFS(日次入力!$D$4:$D$1500,日次入力!$A$4:$A$1500,">="&DATE(2026,12,22),日次入力!$A$4:$A$1500,"<="&DATE(2026,12,28),日次入力!$C$4:$C$1500,"Metaウェビナー")) | D43: =IF(COUNTIFS(日次入力!$A$4:$A$1500,">="&DATE(2026,12,22),日次入力!$A$4:$A$1500,"<="&DATE(2026,12,28),日次入力!$C$4:$C$1500,"Metaウェビナー")=0,"",SUMIFS(日次入力!$E$4:$E$1500,日次入力!$A$4:$A$1500,">="&DATE(2026,12,22),日次入力!$A$4:$A$1500,"<="&DATE(2026,12,28),日次入力!$C$4:$C$1500,"Metaウェビナー")) | E43: =IF(COUNTIFS(日次入力!$A$4:$A$1500,">="&DATE(2026,12,22),日次入力!$A$4:$A$1500,"<="&DATE(2026,12,28),日次入力!$C$4:$C$1500,"Metaウェビナー")=0,"",SUMIFS(日次入力!$F$4:$F$1500,日次入力!$A$4:$A$1500,">="&DATE(2026,12,22),日次入力!$A$4:$A$1500,"<="&DATE(2026,12,28),日次入力!$C$4:$C$1500,"Metaウェビナー")) | F43: =IF(COUNTIFS(日次入力!$A$4:$A$1500,">="&DATE(2026,12,22),日次入力!$A$4:$A$1500,"<="&DATE(2026,12,28),日次入力!$C$4:$C$1500,"Metaウェビナー")=0,"",SUMIFS(日次入力!$G$4:$G$1500,日次入力!$A$4:$A$1500,">="&DATE(2026,12,22),日次入力!$A$4:$A$1500,"<="&DATE(2026,12,28),日次入力!$C$4:$C$1500,"Metaウェビナー")) | G43: =IFERROR(E43/D43,"") | H43: =IFERROR(C43/E43,"") | I43: =IFERROR(C43/D43*1000,"") | J43: =IFERROR(F43/E43,"") | K43: =IFERROR(C43/F43,"") | L43: =IF(COUNTIFS(日次入力!$A$4:$A$1500,">="&DATE(2026,12,22),日次入力!$A$4:$A$1500,"<="&DATE(2026,12,28),日次入力!$C$4:$C$1500,"Metaウェビナー")=0,"",SUMIFS(日次入力!$H$4:$H$1500,日次入力!$A$4:$A$1500,">="&DATE(2026,12,22),日次入力!$A$4:$A$1500,"<="&DATE(2026,12,28),日次入力!$C$4:$C$1500,"Metaウェビナー")) | M43: =IF(L43="","",IFERROR(L43/F43,"")) | N43: =IF(COUNTIFS(日次入力!$A$4:$A$1500,">="&DATE(2026,12,22),日次入力!$A$4:$A$1500,"<="&DATE(2026,12,28),日次入力!$C$4:$C$1500,"Metaウェビナー")=0,"",SUMIFS(日次入力!$I$4:$I$1500,日次入力!$A$4:$A$1500,">="&DATE(2026,12,22),日次入力!$A$4:$A$1500,"<="&DATE(2026,12,28),日次入力!$C$4:$C$1500,"Metaウェビナー")) | O43: =IF(N43="","",IFERROR(N43/L43,"")) | P43: =IF(N43=0,"",IFERROR(C43/N43,"")) | Q43: =IF(N43=0,"",IFERROR(IF(C43/N43<=用語集!$B$22,"◎ 許容内","✗ 超過"),"—")) -> — | R43: =IFERROR(用語集!$B$22/P43,"")
A44: W39 | B44: 12/29–1/4 | C44: =IF(COUNTIFS(日次入力!$A$4:$A$1500,">="&DATE(2026,12,29),日次入力!$A$4:$A$1500,"<="&DATE(2027,1,4),日次入力!$C$4:$C$1500,"Metaウェビナー")=0,"",SUMIFS(日次入力!$D$4:$D$1500,日次入力!$A$4:$A$1500,">="&DATE(2026,12,29),日次入力!$A$4:$A$1500,"<="&DATE(2027,1,4),日次入力!$C$4:$C$1500,"Metaウェビナー")) | D44: =IF(COUNTIFS(日次入力!$A$4:$A$1500,">="&DATE(2026,12,29),日次入力!$A$4:$A$1500,"<="&DATE(2027,1,4),日次入力!$C$4:$C$1500,"Metaウェビナー")=0,"",SUMIFS(日次入力!$E$4:$E$1500,日次入力!$A$4:$A$1500,">="&DATE(2026,12,29),日次入力!$A$4:$A$1500,"<="&DATE(2027,1,4),日次入力!$C$4:$C$1500,"Metaウェビナー")) | E44: =IF(COUNTIFS(日次入力!$A$4:$A$1500,">="&DATE(2026,12,29),日次入力!$A$4:$A$1500,"<="&DATE(2027,1,4),日次入力!$C$4:$C$1500,"Metaウェビナー")=0,"",SUMIFS(日次入力!$F$4:$F$1500,日次入力!$A$4:$A$1500,">="&DATE(2026,12,29),日次入力!$A$4:$A$1500,"<="&DATE(2027,1,4),日次入力!$C$4:$C$1500,"Metaウェビナー")) | F44: =IF(COUNTIFS(日次入力!$A$4:$A$1500,">="&DATE(2026,12,29),日次入力!$A$4:$A$1500,"<="&DATE(2027,1,4),日次入力!$C$4:$C$1500,"Metaウェビナー")=0,"",SUMIFS(日次入力!$G$4:$G$1500,日次入力!$A$4:$A$1500,">="&DATE(2026,12,29),日次入力!$A$4:$A$1500,"<="&DATE(2027,1,4),日次入力!$C$4:$C$1500,"Metaウェビナー")) | G44: =IFERROR(E44/D44,"") | H44: =IFERROR(C44/E44,"") | I44: =IFERROR(C44/D44*1000,"") | J44: =IFERROR(F44/E44,"") | K44: =IFERROR(C44/F44,"") | L44: =IF(COUNTIFS(日次入力!$A$4:$A$1500,">="&DATE(2026,12,29),日次入力!$A$4:$A$1500,"<="&DATE(2027,1,4),日次入力!$C$4:$C$1500,"Metaウェビナー")=0,"",SUMIFS(日次入力!$H$4:$H$1500,日次入力!$A$4:$A$1500,">="&DATE(2026,12,29),日次入力!$A$4:$A$1500,"<="&DATE(2027,1,4),日次入力!$C$4:$C$1500,"Metaウェビナー")) | M44: =IF(L44="","",IFERROR(L44/F44,"")) | N44: =IF(COUNTIFS(日次入力!$A$4:$A$1500,">="&DATE(2026,12,29),日次入力!$A$4:$A$1500,"<="&DATE(2027,1,4),日次入力!$C$4:$C$1500,"Metaウェビナー")=0,"",SUMIFS(日次入力!$I$4:$I$1500,日次入力!$A$4:$A$1500,">="&DATE(2026,12,29),日次入力!$A$4:$A$1500,"<="&DATE(2027,1,4),日次入力!$C$4:$C$1500,"Metaウェビナー")) | O44: =IF(N44="","",IFERROR(N44/L44,"")) | P44: =IF(N44=0,"",IFERROR(C44/N44,"")) | Q44: =IF(N44=0,"",IFERROR(IF(C44/N44<=用語集!$B$22,"◎ 許容内","✗ 超過"),"—")) -> — | R44: =IFERROR(用語集!$B$22/P44,"")
A45: W40 | B45: 1/5–1/11 | C45: =IF(COUNTIFS(日次入力!$A$4:$A$1500,">="&DATE(2027,1,5),日次入力!$A$4:$A$1500,"<="&DATE(2027,1,11),日次入力!$C$4:$C$1500,"Metaウェビナー")=0,"",SUMIFS(日次入力!$D$4:$D$1500,日次入力!$A$4:$A$1500,">="&DATE(2027,1,5),日次入力!$A$4:$A$1500,"<="&DATE(2027,1,11),日次入力!$C$4:$C$1500,"Metaウェビナー")) | D45: =IF(COUNTIFS(日次入力!$A$4:$A$1500,">="&DATE(2027,1,5),日次入力!$A$4:$A$1500,"<="&DATE(2027,1,11),日次入力!$C$4:$C$1500,"Metaウェビナー")=0,"",SUMIFS(日次入力!$E$4:$E$1500,日次入力!$A$4:$A$1500,">="&DATE(2027,1,5),日次入力!$A$4:$A$1500,"<="&DATE(2027,1,11),日次入力!$C$4:$C$1500,"Metaウェビナー")) | E45: =IF(COUNTIFS(日次入力!$A$4:$A$1500,">="&DATE(2027,1,5),日次入力!$A$4:$A$1500,"<="&DATE(2027,1,11),日次入力!$C$4:$C$1500,"Metaウェビナー")=0,"",SUMIFS(日次入力!$F$4:$F$1500,日次入力!$A$4:$A$1500,">="&DATE(2027,1,5),日次入力!$A$4:$A$1500,"<="&DATE(2027,1,11),日次入力!$C$4:$C$1500,"Metaウェビナー")) | F45: =IF(COUNTIFS(日次入力!$A$4:$A$1500,">="&DATE(2027,1,5),日次入力!$A$4:$A$1500,"<="&DATE(2027,1,11),日次入力!$C$4:$C$1500,"Metaウェビナー")=0,"",SUMIFS(日次入力!$G$4:$G$1500,日次入力!$A$4:$A$1500,">="&DATE(2027,1,5),日次入力!$A$4:$A$1500,"<="&DATE(2027,1,11),日次入力!$C$4:$C$1500,"Metaウェビナー")) | G45: =IFERROR(E45/D45,"") | H45: =IFERROR(C45/E45,"") | I45: =IFERROR(C45/D45*1000,"") | J45: =IFERROR(F45/E45,"") | K45: =IFERROR(C45/F45,"") | L45: =IF(COUNTIFS(日次入力!$A$4:$A$1500,">="&DATE(2027,1,5),日次入力!$A$4:$A$1500,"<="&DATE(2027,1,11),日次入力!$C$4:$C$1500,"Metaウェビナー")=0,"",SUMIFS(日次入力!$H$4:$H$1500,日次入力!$A$4:$A$1500,">="&DATE(2027,1,5),日次入力!$A$4:$A$1500,"<="&DATE(2027,1,11),日次入力!$C$4:$C$1500,"Metaウェビナー")) | M45: =IF(L45="","",IFERROR(L45/F45,"")) | N45: =IF(COUNTIFS(日次入力!$A$4:$A$1500,">="&DATE(2027,1,5),日次入力!$A$4:$A$1500,"<="&DATE(2027,1,11),日次入力!$C$4:$C$1500,"Metaウェビナー")=0,"",SUMIFS(日次入力!$I$4:$I$1500,日次入力!$A$4:$A$1500,">="&DATE(2027,1,5),日次入力!$A$4:$A$1500,"<="&DATE(2027,1,11),日次入力!$C$4:$C$1500,"Metaウェビナー")) | O45: =IF(N45="","",IFERROR(N45/L45,"")) | P45: =IF(N45=0,"",IFERROR(C45/N45,"")) | Q45: =IF(N45=0,"",IFERROR(IF(C45/N45<=用語集!$B$22,"◎ 許容内","✗ 超過"),"—")) -> — | R45: =IFERROR(用語集!$B$22/P45,"")
A46: W41 | B46: 1/12–1/18 | C46: =IF(COUNTIFS(日次入力!$A$4:$A$1500,">="&DATE(2027,1,12),日次入力!$A$4:$A$1500,"<="&DATE(2027,1,18),日次入力!$C$4:$C$1500,"Metaウェビナー")=0,"",SUMIFS(日次入力!$D$4:$D$1500,日次入力!$A$4:$A$1500,">="&DATE(2027,1,12),日次入力!$A$4:$A$1500,"<="&DATE(2027,1,18),日次入力!$C$4:$C$1500,"Metaウェビナー")) | D46: =IF(COUNTIFS(日次入力!$A$4:$A$1500,">="&DATE(2027,1,12),日次入力!$A$4:$A$1500,"<="&DATE(2027,1,18),日次入力!$C$4:$C$1500,"Metaウェビナー")=0,"",SUMIFS(日次入力!$E$4:$E$1500,日次入力!$A$4:$A$1500,">="&DATE(2027,1,12),日次入力!$A$4:$A$1500,"<="&DATE(2027,1,18),日次入力!$C$4:$C$1500,"Metaウェビナー")) | E46: =IF(COUNTIFS(日次入力!$A$4:$A$1500,">="&DATE(2027,1,12),日次入力!$A$4:$A$1500,"<="&DATE(2027,1,18),日次入力!$C$4:$C$1500,"Metaウェビナー")=0,"",SUMIFS(日次入力!$F$4:$F$1500,日次入力!$A$4:$A$1500,">="&DATE(2027,1,12),日次入力!$A$4:$A$1500,"<="&DATE(2027,1,18),日次入力!$C$4:$C$1500,"Metaウェビナー")) | F46: =IF(COUNTIFS(日次入力!$A$4:$A$1500,">="&DATE(2027,1,12),日次入力!$A$4:$A$1500,"<="&DATE(2027,1,18),日次入力!$C$4:$C$1500,"Metaウェビナー")=0,"",SUMIFS(日次入力!$G$4:$G$1500,日次入力!$A$4:$A$1500,">="&DATE(2027,1,12),日次入力!$A$4:$A$1500,"<="&DATE(2027,1,18),日次入力!$C$4:$C$1500,"Metaウェビナー")) | G46: =IFERROR(E46/D46,"") | H46: =IFERROR(C46/E46,"") | I46: =IFERROR(C46/D46*1000,"") | J46: =IFERROR(F46/E46,"") | K46: =IFERROR(C46/F46,"") | L46: =IF(COUNTIFS(日次入力!$A$4:$A$1500,">="&DATE(2027,1,12),日次入力!$A$4:$A$1500,"<="&DATE(2027,1,18),日次入力!$C$4:$C$1500,"Metaウェビナー")=0,"",SUMIFS(日次入力!$H$4:$H$1500,日次入力!$A$4:$A$1500,">="&DATE(2027,1,12),日次入力!$A$4:$A$1500,"<="&DATE(2027,1,18),日次入力!$C$4:$C$1500,"Metaウェビナー")) | M46: =IF(L46="","",IFERROR(L46/F46,"")) | N46: =IF(COUNTIFS(日次入力!$A$4:$A$1500,">="&DATE(2027,1,12),日次入力!$A$4:$A$1500,"<="&DATE(2027,1,18),日次入力!$C$4:$C$1500,"Metaウェビナー")=0,"",SUMIFS(日次入力!$I$4:$I$1500,日次入力!$A$4:$A$1500,">="&DATE(2027,1,12),日次入力!$A$4:$A$1500,"<="&DATE(2027,1,18),日次入力!$C$4:$C$1500,"Metaウェビナー")) | O46: =IF(N46="","",IFERROR(N46/L46,"")) | P46: =IF(N46=0,"",IFERROR(C46/N46,"")) | Q46: =IF(N46=0,"",IFERROR(IF(C46/N46<=用語集!$B$22,"◎ 許容内","✗ 超過"),"—")) -> — | R46: =IFERROR(用語集!$B$22/P46,"")
A47: W42 | B47: 1/19–1/25 | C47: =IF(COUNTIFS(日次入力!$A$4:$A$1500,">="&DATE(2027,1,19),日次入力!$A$4:$A$1500,"<="&DATE(2027,1,25),日次入力!$C$4:$C$1500,"Metaウェビナー")=0,"",SUMIFS(日次入力!$D$4:$D$1500,日次入力!$A$4:$A$1500,">="&DATE(2027,1,19),日次入力!$A$4:$A$1500,"<="&DATE(2027,1,25),日次入力!$C$4:$C$1500,"Metaウェビナー")) | D47: =IF(COUNTIFS(日次入力!$A$4:$A$1500,">="&DATE(2027,1,19),日次入力!$A$4:$A$1500,"<="&DATE(2027,1,25),日次入力!$C$4:$C$1500,"Metaウェビナー")=0,"",SUMIFS(日次入力!$E$4:$E$1500,日次入力!$A$4:$A$1500,">="&DATE(2027,1,19),日次入力!$A$4:$A$1500,"<="&DATE(2027,1,25),日次入力!$C$4:$C$1500,"Metaウェビナー")) | E47: =IF(COUNTIFS(日次入力!$A$4:$A$1500,">="&DATE(2027,1,19),日次入力!$A$4:$A$1500,"<="&DATE(2027,1,25),日次入力!$C$4:$C$1500,"Metaウェビナー")=0,"",SUMIFS(日次入力!$F$4:$F$1500,日次入力!$A$4:$A$1500,">="&DATE(2027,1,19),日次入力!$A$4:$A$1500,"<="&DATE(2027,1,25),日次入力!$C$4:$C$1500,"Metaウェビナー")) | F47: =IF(COUNTIFS(日次入力!$A$4:$A$1500,">="&DATE(2027,1,19),日次入力!$A$4:$A$1500,"<="&DATE(2027,1,25),日次入力!$C$4:$C$1500,"Metaウェビナー")=0,"",SUMIFS(日次入力!$G$4:$G$1500,日次入力!$A$4:$A$1500,">="&DATE(2027,1,19),日次入力!$A$4:$A$1500,"<="&DATE(2027,1,25),日次入力!$C$4:$C$1500,"Metaウェビナー")) | G47: =IFERROR(E47/D47,"") | H47: =IFERROR(C47/E47,"") | I47: =IFERROR(C47/D47*1000,"") | J47: =IFERROR(F47/E47,"") | K47: =IFERROR(C47/F47,"") | L47: =IF(COUNTIFS(日次入力!$A$4:$A$1500,">="&DATE(2027,1,19),日次入力!$A$4:$A$1500,"<="&DATE(2027,1,25),日次入力!$C$4:$C$1500,"Metaウェビナー")=0,"",SUMIFS(日次入力!$H$4:$H$1500,日次入力!$A$4:$A$1500,">="&DATE(2027,1,19),日次入力!$A$4:$A$1500,"<="&DATE(2027,1,25),日次入力!$C$4:$C$1500,"Metaウェビナー")) | M47: =IF(L47="","",IFERROR(L47/F47,"")) | N47: =IF(COUNTIFS(日次入力!$A$4:$A$1500,">="&DATE(2027,1,19),日次入力!$A$4:$A$1500,"<="&DATE(2027,1,25),日次入力!$C$4:$C$1500,"Metaウェビナー")=0,"",SUMIFS(日次入力!$I$4:$I$1500,日次入力!$A$4:$A$1500,">="&DATE(2027,1,19),日次入力!$A$4:$A$1500,"<="&DATE(2027,1,25),日次入力!$C$4:$C$1500,"Metaウェビナー")) | O47: =IF(N47="","",IFERROR(N47/L47,"")) | P47: =IF(N47=0,"",IFERROR(C47/N47,"")) | Q47: =IF(N47=0,"",IFERROR(IF(C47/N47<=用語集!$B$22,"◎ 許容内","✗ 超過"),"—")) -> — | R47: =IFERROR(用語集!$B$22/P47,"")
A48: W43 | B48: 1/26–2/1 | C48: =IF(COUNTIFS(日次入力!$A$4:$A$1500,">="&DATE(2027,1,26),日次入力!$A$4:$A$1500,"<="&DATE(2027,2,1),日次入力!$C$4:$C$1500,"Metaウェビナー")=0,"",SUMIFS(日次入力!$D$4:$D$1500,日次入力!$A$4:$A$1500,">="&DATE(2027,1,26),日次入力!$A$4:$A$1500,"<="&DATE(2027,2,1),日次入力!$C$4:$C$1500,"Metaウェビナー")) | D48: =IF(COUNTIFS(日次入力!$A$4:$A$1500,">="&DATE(2027,1,26),日次入力!$A$4:$A$1500,"<="&DATE(2027,2,1),日次入力!$C$4:$C$1500,"Metaウェビナー")=0,"",SUMIFS(日次入力!$E$4:$E$1500,日次入力!$A$4:$A$1500,">="&DATE(2027,1,26),日次入力!$A$4:$A$1500,"<="&DATE(2027,2,1),日次入力!$C$4:$C$1500,"Metaウェビナー")) | E48: =IF(COUNTIFS(日次入力!$A$4:$A$1500,">="&DATE(2027,1,26),日次入力!$A$4:$A$1500,"<="&DATE(2027,2,1),日次入力!$C$4:$C$1500,"Metaウェビナー")=0,"",SUMIFS(日次入力!$F$4:$F$1500,日次入力!$A$4:$A$1500,">="&DATE(2027,1,26),日次入力!$A$4:$A$1500,"<="&DATE(2027,2,1),日次入力!$C$4:$C$1500,"Metaウェビナー")) | F48: =IF(COUNTIFS(日次入力!$A$4:$A$1500,">="&DATE(2027,1,26),日次入力!$A$4:$A$1500,"<="&DATE(2027,2,1),日次入力!$C$4:$C$1500,"Metaウェビナー")=0,"",SUMIFS(日次入力!$G$4:$G$1500,日次入力!$A$4:$A$1500,">="&DATE(2027,1,26),日次入力!$A$4:$A$1500,"<="&DATE(2027,2,1),日次入力!$C$4:$C$1500,"Metaウェビナー")) | G48: =IFERROR(E48/D48,"") | H48: =IFERROR(C48/E48,"") | I48: =IFERROR(C48/D48*1000,"") | J48: =IFERROR(F48/E48,"") | K48: =IFERROR(C48/F48,"") | L48: =IF(COUNTIFS(日次入力!$A$4:$A$1500,">="&DATE(2027,1,26),日次入力!$A$4:$A$1500,"<="&DATE(2027,2,1),日次入力!$C$4:$C$1500,"Metaウェビナー")=0,"",SUMIFS(日次入力!$H$4:$H$1500,日次入力!$A$4:$A$1500,">="&DATE(2027,1,26),日次入力!$A$4:$A$1500,"<="&DATE(2027,2,1),日次入力!$C$4:$C$1500,"Metaウェビナー")) | M48: =IF(L48="","",IFERROR(L48/F48,"")) | N48: =IF(COUNTIFS(日次入力!$A$4:$A$1500,">="&DATE(2027,1,26),日次入力!$A$4:$A$1500,"<="&DATE(2027,2,1),日次入力!$C$4:$C$1500,"Metaウェビナー")=0,"",SUMIFS(日次入力!$I$4:$I$1500,日次入力!$A$4:$A$1500,">="&DATE(2027,1,26),日次入力!$A$4:$A$1500,"<="&DATE(2027,2,1),日次入力!$C$4:$C$1500,"Metaウェビナー")) | O48: =IF(N48="","",IFERROR(N48/L48,"")) | P48: =IF(N48=0,"",IFERROR(C48/N48,"")) | Q48: =IF(N48=0,"",IFERROR(IF(C48/N48<=用語集!$B$22,"◎ 許容内","✗ 超過"),"—")) -> — | R48: =IFERROR(用語集!$B$22/P48,"")
A49: W44 | B49: 2/2–2/8 | C49: =IF(COUNTIFS(日次入力!$A$4:$A$1500,">="&DATE(2027,2,2),日次入力!$A$4:$A$1500,"<="&DATE(2027,2,8),日次入力!$C$4:$C$1500,"Metaウェビナー")=0,"",SUMIFS(日次入力!$D$4:$D$1500,日次入力!$A$4:$A$1500,">="&DATE(2027,2,2),日次入力!$A$4:$A$1500,"<="&DATE(2027,2,8),日次入力!$C$4:$C$1500,"Metaウェビナー")) | D49: =IF(COUNTIFS(日次入力!$A$4:$A$1500,">="&DATE(2027,2,2),日次入力!$A$4:$A$1500,"<="&DATE(2027,2,8),日次入力!$C$4:$C$1500,"Metaウェビナー")=0,"",SUMIFS(日次入力!$E$4:$E$1500,日次入力!$A$4:$A$1500,">="&DATE(2027,2,2),日次入力!$A$4:$A$1500,"<="&DATE(2027,2,8),日次入力!$C$4:$C$1500,"Metaウェビナー")) | E49: =IF(COUNTIFS(日次入力!$A$4:$A$1500,">="&DATE(2027,2,2),日次入力!$A$4:$A$1500,"<="&DATE(2027,2,8),日次入力!$C$4:$C$1500,"Metaウェビナー")=0,"",SUMIFS(日次入力!$F$4:$F$1500,日次入力!$A$4:$A$1500,">="&DATE(2027,2,2),日次入力!$A$4:$A$1500,"<="&DATE(2027,2,8),日次入力!$C$4:$C$1500,"Metaウェビナー")) | F49: =IF(COUNTIFS(日次入力!$A$4:$A$1500,">="&DATE(2027,2,2),日次入力!$A$4:$A$1500,"<="&DATE(2027,2,8),日次入力!$C$4:$C$1500,"Metaウェビナー")=0,"",SUMIFS(日次入力!$G$4:$G$1500,日次入力!$A$4:$A$1500,">="&DATE(2027,2,2),日次入力!$A$4:$A$1500,"<="&DATE(2027,2,8),日次入力!$C$4:$C$1500,"Metaウェビナー")) | G49: =IFERROR(E49/D49,"") | H49: =IFERROR(C49/E49,"") | I49: =IFERROR(C49/D49*1000,"") | J49: =IFERROR(F49/E49,"") | K49: =IFERROR(C49/F49,"") | L49: =IF(COUNTIFS(日次入力!$A$4:$A$1500,">="&DATE(2027,2,2),日次入力!$A$4:$A$1500,"<="&DATE(2027,2,8),日次入力!$C$4:$C$1500,"Metaウェビナー")=0,"",SUMIFS(日次入力!$H$4:$H$1500,日次入力!$A$4:$A$1500,">="&DATE(2027,2,2),日次入力!$A$4:$A$1500,"<="&DATE(2027,2,8),日次入力!$C$4:$C$1500,"Metaウェビナー")) | M49: =IF(L49="","",IFERROR(L49/F49,"")) | N49: =IF(COUNTIFS(日次入力!$A$4:$A$1500,">="&DATE(2027,2,2),日次入力!$A$4:$A$1500,"<="&DATE(2027,2,8),日次入力!$C$4:$C$1500,"Metaウェビナー")=0,"",SUMIFS(日次入力!$I$4:$I$1500,日次入力!$A$4:$A$1500,">="&DATE(2027,2,2),日次入力!$A$4:$A$1500,"<="&DATE(2027,2,8),日次入力!$C$4:$C$1500,"Metaウェビナー")) | O49: =IF(N49="","",IFERROR(N49/L49,"")) | P49: =IF(N49=0,"",IFERROR(C49/N49,"")) | Q49: =IF(N49=0,"",IFERROR(IF(C49/N49<=用語集!$B$22,"◎ 許容内","✗ 超過"),"—")) -> — | R49: =IFERROR(用語集!$B$22/P49,"")
A50: W45 | B50: 2/9–2/15 | C50: =IF(COUNTIFS(日次入力!$A$4:$A$1500,">="&DATE(2027,2,9),日次入力!$A$4:$A$1500,"<="&DATE(2027,2,15),日次入力!$C$4:$C$1500,"Metaウェビナー")=0,"",SUMIFS(日次入力!$D$4:$D$1500,日次入力!$A$4:$A$1500,">="&DATE(2027,2,9),日次入力!$A$4:$A$1500,"<="&DATE(2027,2,15),日次入力!$C$4:$C$1500,"Metaウェビナー")) | D50: =IF(COUNTIFS(日次入力!$A$4:$A$1500,">="&DATE(2027,2,9),日次入力!$A$4:$A$1500,"<="&DATE(2027,2,15),日次入力!$C$4:$C$1500,"Metaウェビナー")=0,"",SUMIFS(日次入力!$E$4:$E$1500,日次入力!$A$4:$A$1500,">="&DATE(2027,2,9),日次入力!$A$4:$A$1500,"<="&DATE(2027,2,15),日次入力!$C$4:$C$1500,"Metaウェビナー")) | E50: =IF(COUNTIFS(日次入力!$A$4:$A$1500,">="&DATE(2027,2,9),日次入力!$A$4:$A$1500,"<="&DATE(2027,2,15),日次入力!$C$4:$C$1500,"Metaウェビナー")=0,"",SUMIFS(日次入力!$F$4:$F$1500,日次入力!$A$4:$A$1500,">="&DATE(2027,2,9),日次入力!$A$4:$A$1500,"<="&DATE(2027,2,15),日次入力!$C$4:$C$1500,"Metaウェビナー")) | F50: =IF(COUNTIFS(日次入力!$A$4:$A$1500,">="&DATE(2027,2,9),日次入力!$A$4:$A$1500,"<="&DATE(2027,2,15),日次入力!$C$4:$C$1500,"Metaウェビナー")=0,"",SUMIFS(日次入力!$G$4:$G$1500,日次入力!$A$4:$A$1500,">="&DATE(2027,2,9),日次入力!$A$4:$A$1500,"<="&DATE(2027,2,15),日次入力!$C$4:$C$1500,"Metaウェビナー")) | G50: =IFERROR(E50/D50,"") | H50: =IFERROR(C50/E50,"") | I50: =IFERROR(C50/D50*1000,"") | J50: =IFERROR(F50/E50,"") | K50: =IFERROR(C50/F50,"") | L50: =IF(COUNTIFS(日次入力!$A$4:$A$1500,">="&DATE(2027,2,9),日次入力!$A$4:$A$1500,"<="&DATE(2027,2,15),日次入力!$C$4:$C$1500,"Metaウェビナー")=0,"",SUMIFS(日次入力!$H$4:$H$1500,日次入力!$A$4:$A$1500,">="&DATE(2027,2,9),日次入力!$A$4:$A$1500,"<="&DATE(2027,2,15),日次入力!$C$4:$C$1500,"Metaウェビナー")) | M50: =IF(L50="","",IFERROR(L50/F50,"")) | N50: =IF(COUNTIFS(日次入力!$A$4:$A$1500,">="&DATE(2027,2,9),日次入力!$A$4:$A$1500,"<="&DATE(2027,2,15),日次入力!$C$4:$C$1500,"Metaウェビナー")=0,"",SUMIFS(日次入力!$I$4:$I$1500,日次入力!$A$4:$A$1500,">="&DATE(2027,2,9),日次入力!$A$4:$A$1500,"<="&DATE(2027,2,15),日次入力!$C$4:$C$1500,"Metaウェビナー")) | O50: =IF(N50="","",IFERROR(N50/L50,"")) | P50: =IF(N50=0,"",IFERROR(C50/N50,"")) | Q50: =IF(N50=0,"",IFERROR(IF(C50/N50<=用語集!$B$22,"◎ 許容内","✗ 超過"),"—")) -> — | R50: =IFERROR(用語集!$B$22/P50,"")
A51: W46 | B51: 2/16–2/22 | C51: =IF(COUNTIFS(日次入力!$A$4:$A$1500,">="&DATE(2027,2,16),日次入力!$A$4:$A$1500,"<="&DATE(2027,2,22),日次入力!$C$4:$C$1500,"Metaウェビナー")=0,"",SUMIFS(日次入力!$D$4:$D$1500,日次入力!$A$4:$A$1500,">="&DATE(2027,2,16),日次入力!$A$4:$A$1500,"<="&DATE(2027,2,22),日次入力!$C$4:$C$1500,"Metaウェビナー")) | D51: =IF(COUNTIFS(日次入力!$A$4:$A$1500,">="&DATE(2027,2,16),日次入力!$A$4:$A$1500,"<="&DATE(2027,2,22),日次入力!$C$4:$C$1500,"Metaウェビナー")=0,"",SUMIFS(日次入力!$E$4:$E$1500,日次入力!$A$4:$A$1500,">="&DATE(2027,2,16),日次入力!$A$4:$A$1500,"<="&DATE(2027,2,22),日次入力!$C$4:$C$1500,"Metaウェビナー")) | E51: =IF(COUNTIFS(日次入力!$A$4:$A$1500,">="&DATE(2027,2,16),日次入力!$A$4:$A$1500,"<="&DATE(2027,2,22),日次入力!$C$4:$C$1500,"Metaウェビナー")=0,"",SUMIFS(日次入力!$F$4:$F$1500,日次入力!$A$4:$A$1500,">="&DATE(2027,2,16),日次入力!$A$4:$A$1500,"<="&DATE(2027,2,22),日次入力!$C$4:$C$1500,"Metaウェビナー")) | F51: =IF(COUNTIFS(日次入力!$A$4:$A$1500,">="&DATE(2027,2,16),日次入力!$A$4:$A$1500,"<="&DATE(2027,2,22),日次入力!$C$4:$C$1500,"Metaウェビナー")=0,"",SUMIFS(日次入力!$G$4:$G$1500,日次入力!$A$4:$A$1500,">="&DATE(2027,2,16),日次入力!$A$4:$A$1500,"<="&DATE(2027,2,22),日次入力!$C$4:$C$1500,"Metaウェビナー")) | G51: =IFERROR(E51/D51,"") | H51: =IFERROR(C51/E51,"") | I51: =IFERROR(C51/D51*1000,"") | J51: =IFERROR(F51/E51,"") | K51: =IFERROR(C51/F51,"") | L51: =IF(COUNTIFS(日次入力!$A$4:$A$1500,">="&DATE(2027,2,16),日次入力!$A$4:$A$1500,"<="&DATE(2027,2,22),日次入力!$C$4:$C$1500,"Metaウェビナー")=0,"",SUMIFS(日次入力!$H$4:$H$1500,日次入力!$A$4:$A$1500,">="&DATE(2027,2,16),日次入力!$A$4:$A$1500,"<="&DATE(2027,2,22),日次入力!$C$4:$C$1500,"Metaウェビナー")) | M51: =IF(L51="","",IFERROR(L51/F51,"")) | N51: =IF(COUNTIFS(日次入力!$A$4:$A$1500,">="&DATE(2027,2,16),日次入力!$A$4:$A$1500,"<="&DATE(2027,2,22),日次入力!$C$4:$C$1500,"Metaウェビナー")=0,"",SUMIFS(日次入力!$I$4:$I$1500,日次入力!$A$4:$A$1500,">="&DATE(2027,2,16),日次入力!$A$4:$A$1500,"<="&DATE(2027,2,22),日次入力!$C$4:$C$1500,"Metaウェビナー")) | O51: =IF(N51="","",IFERROR(N51/L51,"")) | P51: =IF(N51=0,"",IFERROR(C51/N51,"")) | Q51: =IF(N51=0,"",IFERROR(IF(C51/N51<=用語集!$B$22,"◎ 許容内","✗ 超過"),"—")) -> — | R51: =IFERROR(用語集!$B$22/P51,"")
A52: W47 | B52: 2/23–3/1 | C52: =IF(COUNTIFS(日次入力!$A$4:$A$1500,">="&DATE(2027,2,23),日次入力!$A$4:$A$1500,"<="&DATE(2027,3,1),日次入力!$C$4:$C$1500,"Metaウェビナー")=0,"",SUMIFS(日次入力!$D$4:$D$1500,日次入力!$A$4:$A$1500,">="&DATE(2027,2,23),日次入力!$A$4:$A$1500,"<="&DATE(2027,3,1),日次入力!$C$4:$C$1500,"Metaウェビナー")) | D52: =IF(COUNTIFS(日次入力!$A$4:$A$1500,">="&DATE(2027,2,23),日次入力!$A$4:$A$1500,"<="&DATE(2027,3,1),日次入力!$C$4:$C$1500,"Metaウェビナー")=0,"",SUMIFS(日次入力!$E$4:$E$1500,日次入力!$A$4:$A$1500,">="&DATE(2027,2,23),日次入力!$A$4:$A$1500,"<="&DATE(2027,3,1),日次入力!$C$4:$C$1500,"Metaウェビナー")) | E52: =IF(COUNTIFS(日次入力!$A$4:$A$1500,">="&DATE(2027,2,23),日次入力!$A$4:$A$1500,"<="&DATE(2027,3,1),日次入力!$C$4:$C$1500,"Metaウェビナー")=0,"",SUMIFS(日次入力!$F$4:$F$1500,日次入力!$A$4:$A$1500,">="&DATE(2027,2,23),日次入力!$A$4:$A$1500,"<="&DATE(2027,3,1),日次入力!$C$4:$C$1500,"Metaウェビナー")) | F52: =IF(COUNTIFS(日次入力!$A$4:$A$1500,">="&DATE(2027,2,23),日次入力!$A$4:$A$1500,"<="&DATE(2027,3,1),日次入力!$C$4:$C$1500,"Metaウェビナー")=0,"",SUMIFS(日次入力!$G$4:$G$1500,日次入力!$A$4:$A$1500,">="&DATE(2027,2,23),日次入力!$A$4:$A$1500,"<="&DATE(2027,3,1),日次入力!$C$4:$C$1500,"Metaウェビナー")) | G52: =IFERROR(E52/D52,"") | H52: =IFERROR(C52/E52,"") | I52: =IFERROR(C52/D52*1000,"") | J52: =IFERROR(F52/E52,"") | K52: =IFERROR(C52/F52,"") | L52: =IF(COUNTIFS(日次入力!$A$4:$A$1500,">="&DATE(2027,2,23),日次入力!$A$4:$A$1500,"<="&DATE(2027,3,1),日次入力!$C$4:$C$1500,"Metaウェビナー")=0,"",SUMIFS(日次入力!$H$4:$H$1500,日次入力!$A$4:$A$1500,">="&DATE(2027,2,23),日次入力!$A$4:$A$1500,"<="&DATE(2027,3,1),日次入力!$C$4:$C$1500,"Metaウェビナー")) | M52: =IF(L52="","",IFERROR(L52/F52,"")) | N52: =IF(COUNTIFS(日次入力!$A$4:$A$1500,">="&DATE(2027,2,23),日次入力!$A$4:$A$1500,"<="&DATE(2027,3,1),日次入力!$C$4:$C$1500,"Metaウェビナー")=0,"",SUMIFS(日次入力!$I$4:$I$1500,日次入力!$A$4:$A$1500,">="&DATE(2027,2,23),日次入力!$A$4:$A$1500,"<="&DATE(2027,3,1),日次入力!$C$4:$C$1500,"Metaウェビナー")) | O52: =IF(N52="","",IFERROR(N52/L52,"")) | P52: =IF(N52=0,"",IFERROR(C52/N52,"")) | Q52: =IF(N52=0,"",IFERROR(IF(C52/N52<=用語集!$B$22,"◎ 許容内","✗ 超過"),"—")) -> — | R52: =IFERROR(用語集!$B$22/P52,"")
A53: W48 | B53: 3/2–3/8 | C53: =IF(COUNTIFS(日次入力!$A$4:$A$1500,">="&DATE(2027,3,2),日次入力!$A$4:$A$1500,"<="&DATE(2027,3,8),日次入力!$C$4:$C$1500,"Metaウェビナー")=0,"",SUMIFS(日次入力!$D$4:$D$1500,日次入力!$A$4:$A$1500,">="&DATE(2027,3,2),日次入力!$A$4:$A$1500,"<="&DATE(2027,3,8),日次入力!$C$4:$C$1500,"Metaウェビナー")) | D53: =IF(COUNTIFS(日次入力!$A$4:$A$1500,">="&DATE(2027,3,2),日次入力!$A$4:$A$1500,"<="&DATE(2027,3,8),日次入力!$C$4:$C$1500,"Metaウェビナー")=0,"",SUMIFS(日次入力!$E$4:$E$1500,日次入力!$A$4:$A$1500,">="&DATE(2027,3,2),日次入力!$A$4:$A$1500,"<="&DATE(2027,3,8),日次入力!$C$4:$C$1500,"Metaウェビナー")) | E53: =IF(COUNTIFS(日次入力!$A$4:$A$1500,">="&DATE(2027,3,2),日次入力!$A$4:$A$1500,"<="&DATE(2027,3,8),日次入力!$C$4:$C$1500,"Metaウェビナー")=0,"",SUMIFS(日次入力!$F$4:$F$1500,日次入力!$A$4:$A$1500,">="&DATE(2027,3,2),日次入力!$A$4:$A$1500,"<="&DATE(2027,3,8),日次入力!$C$4:$C$1500,"Metaウェビナー")) | F53: =IF(COUNTIFS(日次入力!$A$4:$A$1500,">="&DATE(2027,3,2),日次入力!$A$4:$A$1500,"<="&DATE(2027,3,8),日次入力!$C$4:$C$1500,"Metaウェビナー")=0,"",SUMIFS(日次入力!$G$4:$G$1500,日次入力!$A$4:$A$1500,">="&DATE(2027,3,2),日次入力!$A$4:$A$1500,"<="&DATE(2027,3,8),日次入力!$C$4:$C$1500,"Metaウェビナー")) | G53: =IFERROR(E53/D53,"") | H53: =IFERROR(C53/E53,"") | I53: =IFERROR(C53/D53*1000,"") | J53: =IFERROR(F53/E53,"") | K53: =IFERROR(C53/F53,"") | L53: =IF(COUNTIFS(日次入力!$A$4:$A$1500,">="&DATE(2027,3,2),日次入力!$A$4:$A$1500,"<="&DATE(2027,3,8),日次入力!$C$4:$C$1500,"Metaウェビナー")=0,"",SUMIFS(日次入力!$H$4:$H$1500,日次入力!$A$4:$A$1500,">="&DATE(2027,3,2),日次入力!$A$4:$A$1500,"<="&DATE(2027,3,8),日次入力!$C$4:$C$1500,"Metaウェビナー")) | M53: =IF(L53="","",IFERROR(L53/F53,"")) | N53: =IF(COUNTIFS(日次入力!$A$4:$A$1500,">="&DATE(2027,3,2),日次入力!$A$4:$A$1500,"<="&DATE(2027,3,8),日次入力!$C$4:$C$1500,"Metaウェビナー")=0,"",SUMIFS(日次入力!$I$4:$I$1500,日次入力!$A$4:$A$1500,">="&DATE(2027,3,2),日次入力!$A$4:$A$1500,"<="&DATE(2027,3,8),日次入力!$C$4:$C$1500,"Metaウェビナー")) | O53: =IF(N53="","",IFERROR(N53/L53,"")) | P53: =IF(N53=0,"",IFERROR(C53/N53,"")) | Q53: =IF(N53=0,"",IFERROR(IF(C53/N53<=用語集!$B$22,"◎ 許容内","✗ 超過"),"—")) -> — | R53: =IFERROR(用語集!$B$22/P53,"")
A54: W49 | B54: 3/9–3/15 | C54: =IF(COUNTIFS(日次入力!$A$4:$A$1500,">="&DATE(2027,3,9),日次入力!$A$4:$A$1500,"<="&DATE(2027,3,15),日次入力!$C$4:$C$1500,"Metaウェビナー")=0,"",SUMIFS(日次入力!$D$4:$D$1500,日次入力!$A$4:$A$1500,">="&DATE(2027,3,9),日次入力!$A$4:$A$1500,"<="&DATE(2027,3,15),日次入力!$C$4:$C$1500,"Metaウェビナー")) | D54: =IF(COUNTIFS(日次入力!$A$4:$A$1500,">="&DATE(2027,3,9),日次入力!$A$4:$A$1500,"<="&DATE(2027,3,15),日次入力!$C$4:$C$1500,"Metaウェビナー")=0,"",SUMIFS(日次入力!$E$4:$E$1500,日次入力!$A$4:$A$1500,">="&DATE(2027,3,9),日次入力!$A$4:$A$1500,"<="&DATE(2027,3,15),日次入力!$C$4:$C$1500,"Metaウェビナー")) | E54: =IF(COUNTIFS(日次入力!$A$4:$A$1500,">="&DATE(2027,3,9),日次入力!$A$4:$A$1500,"<="&DATE(2027,3,15),日次入力!$C$4:$C$1500,"Metaウェビナー")=0,"",SUMIFS(日次入力!$F$4:$F$1500,日次入力!$A$4:$A$1500,">="&DATE(2027,3,9),日次入力!$A$4:$A$1500,"<="&DATE(2027,3,15),日次入力!$C$4:$C$1500,"Metaウェビナー")) | F54: =IF(COUNTIFS(日次入力!$A$4:$A$1500,">="&DATE(2027,3,9),日次入力!$A$4:$A$1500,"<="&DATE(2027,3,15),日次入力!$C$4:$C$1500,"Metaウェビナー")=0,"",SUMIFS(日次入力!$G$4:$G$1500,日次入力!$A$4:$A$1500,">="&DATE(2027,3,9),日次入力!$A$4:$A$1500,"<="&DATE(2027,3,15),日次入力!$C$4:$C$1500,"Metaウェビナー")) | G54: =IFERROR(E54/D54,"") | H54: =IFERROR(C54/E54,"") | I54: =IFERROR(C54/D54*1000,"") | J54: =IFERROR(F54/E54,"") | K54: =IFERROR(C54/F54,"") | L54: =IF(COUNTIFS(日次入力!$A$4:$A$1500,">="&DATE(2027,3,9),日次入力!$A$4:$A$1500,"<="&DATE(2027,3,15),日次入力!$C$4:$C$1500,"Metaウェビナー")=0,"",SUMIFS(日次入力!$H$4:$H$1500,日次入力!$A$4:$A$1500,">="&DATE(2027,3,9),日次入力!$A$4:$A$1500,"<="&DATE(2027,3,15),日次入力!$C$4:$C$1500,"Metaウェビナー")) | M54: =IF(L54="","",IFERROR(L54/F54,"")) | N54: =IF(COUNTIFS(日次入力!$A$4:$A$1500,">="&DATE(2027,3,9),日次入力!$A$4:$A$1500,"<="&DATE(2027,3,15),日次入力!$C$4:$C$1500,"Metaウェビナー")=0,"",SUMIFS(日次入力!$I$4:$I$1500,日次入力!$A$4:$A$1500,">="&DATE(2027,3,9),日次入力!$A$4:$A$1500,"<="&DATE(2027,3,15),日次入力!$C$4:$C$1500,"Metaウェビナー")) | O54: =IF(N54="","",IFERROR(N54/L54,"")) | P54: =IF(N54=0,"",IFERROR(C54/N54,"")) | Q54: =IF(N54=0,"",IFERROR(IF(C54/N54<=用語集!$B$22,"◎ 許容内","✗ 超過"),"—")) -> — | R54: =IFERROR(用語集!$B$22/P54,"")
A55: W50 | B55: 3/16–3/22 | C55: =IF(COUNTIFS(日次入力!$A$4:$A$1500,">="&DATE(2027,3,16),日次入力!$A$4:$A$1500,"<="&DATE(2027,3,22),日次入力!$C$4:$C$1500,"Metaウェビナー")=0,"",SUMIFS(日次入力!$D$4:$D$1500,日次入力!$A$4:$A$1500,">="&DATE(2027,3,16),日次入力!$A$4:$A$1500,"<="&DATE(2027,3,22),日次入力!$C$4:$C$1500,"Metaウェビナー")) | D55: =IF(COUNTIFS(日次入力!$A$4:$A$1500,">="&DATE(2027,3,16),日次入力!$A$4:$A$1500,"<="&DATE(2027,3,22),日次入力!$C$4:$C$1500,"Metaウェビナー")=0,"",SUMIFS(日次入力!$E$4:$E$1500,日次入力!$A$4:$A$1500,">="&DATE(2027,3,16),日次入力!$A$4:$A$1500,"<="&DATE(2027,3,22),日次入力!$C$4:$C$1500,"Metaウェビナー")) | E55: =IF(COUNTIFS(日次入力!$A$4:$A$1500,">="&DATE(2027,3,16),日次入力!$A$4:$A$1500,"<="&DATE(2027,3,22),日次入力!$C$4:$C$1500,"Metaウェビナー")=0,"",SUMIFS(日次入力!$F$4:$F$1500,日次入力!$A$4:$A$1500,">="&DATE(2027,3,16),日次入力!$A$4:$A$1500,"<="&DATE(2027,3,22),日次入力!$C$4:$C$1500,"Metaウェビナー")) | F55: =IF(COUNTIFS(日次入力!$A$4:$A$1500,">="&DATE(2027,3,16),日次入力!$A$4:$A$1500,"<="&DATE(2027,3,22),日次入力!$C$4:$C$1500,"Metaウェビナー")=0,"",SUMIFS(日次入力!$G$4:$G$1500,日次入力!$A$4:$A$1500,">="&DATE(2027,3,16),日次入力!$A$4:$A$1500,"<="&DATE(2027,3,22),日次入力!$C$4:$C$1500,"Metaウェビナー")) | G55: =IFERROR(E55/D55,"") | H55: =IFERROR(C55/E55,"") | I55: =IFERROR(C55/D55*1000,"") | J55: =IFERROR(F55/E55,"") | K55: =IFERROR(C55/F55,"") | L55: =IF(COUNTIFS(日次入力!$A$4:$A$1500,">="&DATE(2027,3,16),日次入力!$A$4:$A$1500,"<="&DATE(2027,3,22),日次入力!$C$4:$C$1500,"Metaウェビナー")=0,"",SUMIFS(日次入力!$H$4:$H$1500,日次入力!$A$4:$A$1500,">="&DATE(2027,3,16),日次入力!$A$4:$A$1500,"<="&DATE(2027,3,22),日次入力!$C$4:$C$1500,"Metaウェビナー")) | M55: =IF(L55="","",IFERROR(L55/F55,"")) | N55: =IF(COUNTIFS(日次入力!$A$4:$A$1500,">="&DATE(2027,3,16),日次入力!$A$4:$A$1500,"<="&DATE(2027,3,22),日次入力!$C$4:$C$1500,"Metaウェビナー")=0,"",SUMIFS(日次入力!$I$4:$I$1500,日次入力!$A$4:$A$1500,">="&DATE(2027,3,16),日次入力!$A$4:$A$1500,"<="&DATE(2027,3,22),日次入力!$C$4:$C$1500,"Metaウェビナー")) | O55: =IF(N55="","",IFERROR(N55/L55,"")) | P55: =IF(N55=0,"",IFERROR(C55/N55,"")) | Q55: =IF(N55=0,"",IFERROR(IF(C55/N55<=用語集!$B$22,"◎ 許容内","✗ 超過"),"—")) -> — | R55: =IFERROR(用語集!$B$22/P55,"")
A56: W51 | B56: 3/23–3/29 | C56: =IF(COUNTIFS(日次入力!$A$4:$A$1500,">="&DATE(2027,3,23),日次入力!$A$4:$A$1500,"<="&DATE(2027,3,29),日次入力!$C$4:$C$1500,"Metaウェビナー")=0,"",SUMIFS(日次入力!$D$4:$D$1500,日次入力!$A$4:$A$1500,">="&DATE(2027,3,23),日次入力!$A$4:$A$1500,"<="&DATE(2027,3,29),日次入力!$C$4:$C$1500,"Metaウェビナー")) | D56: =IF(COUNTIFS(日次入力!$A$4:$A$1500,">="&DATE(2027,3,23),日次入力!$A$4:$A$1500,"<="&DATE(2027,3,29),日次入力!$C$4:$C$1500,"Metaウェビナー")=0,"",SUMIFS(日次入力!$E$4:$E$1500,日次入力!$A$4:$A$1500,">="&DATE(2027,3,23),日次入力!$A$4:$A$1500,"<="&DATE(2027,3,29),日次入力!$C$4:$C$1500,"Metaウェビナー")) | E56: =IF(COUNTIFS(日次入力!$A$4:$A$1500,">="&DATE(2027,3,23),日次入力!$A$4:$A$1500,"<="&DATE(2027,3,29),日次入力!$C$4:$C$1500,"Metaウェビナー")=0,"",SUMIFS(日次入力!$F$4:$F$1500,日次入力!$A$4:$A$1500,">="&DATE(2027,3,23),日次入力!$A$4:$A$1500,"<="&DATE(2027,3,29),日次入力!$C$4:$C$1500,"Metaウェビナー")) | F56: =IF(COUNTIFS(日次入力!$A$4:$A$1500,">="&DATE(2027,3,23),日次入力!$A$4:$A$1500,"<="&DATE(2027,3,29),日次入力!$C$4:$C$1500,"Metaウェビナー")=0,"",SUMIFS(日次入力!$G$4:$G$1500,日次入力!$A$4:$A$1500,">="&DATE(2027,3,23),日次入力!$A$4:$A$1500,"<="&DATE(2027,3,29),日次入力!$C$4:$C$1500,"Metaウェビナー")) | G56: =IFERROR(E56/D56,"") | H56: =IFERROR(C56/E56,"") | I56: =IFERROR(C56/D56*1000,"") | J56: =IFERROR(F56/E56,"") | K56: =IFERROR(C56/F56,"") | L56: =IF(COUNTIFS(日次入力!$A$4:$A$1500,">="&DATE(2027,3,23),日次入力!$A$4:$A$1500,"<="&DATE(2027,3,29),日次入力!$C$4:$C$1500,"Metaウェビナー")=0,"",SUMIFS(日次入力!$H$4:$H$1500,日次入力!$A$4:$A$1500,">="&DATE(2027,3,23),日次入力!$A$4:$A$1500,"<="&DATE(2027,3,29),日次入力!$C$4:$C$1500,"Metaウェビナー")) | M56: =IF(L56="","",IFERROR(L56/F56,"")) | N56: =IF(COUNTIFS(日次入力!$A$4:$A$1500,">="&DATE(2027,3,23),日次入力!$A$4:$A$1500,"<="&DATE(2027,3,29),日次入力!$C$4:$C$1500,"Metaウェビナー")=0,"",SUMIFS(日次入力!$I$4:$I$1500,日次入力!$A$4:$A$1500,">="&DATE(2027,3,23),日次入力!$A$4:$A$1500,"<="&DATE(2027,3,29),日次入力!$C$4:$C$1500,"Metaウェビナー")) | O56: =IF(N56="","",IFERROR(N56/L56,"")) | P56: =IF(N56=0,"",IFERROR(C56/N56,"")) | Q56: =IF(N56=0,"",IFERROR(IF(C56/N56<=用語集!$B$22,"◎ 許容内","✗ 超過"),"—")) -> — | R56: =IFERROR(用語集!$B$22/P56,"")
A57: W52 | B57: 3/30–4/5 | C57: =IF(COUNTIFS(日次入力!$A$4:$A$1500,">="&DATE(2027,3,30),日次入力!$A$4:$A$1500,"<="&DATE(2027,4,5),日次入力!$C$4:$C$1500,"Metaウェビナー")=0,"",SUMIFS(日次入力!$D$4:$D$1500,日次入力!$A$4:$A$1500,">="&DATE(2027,3,30),日次入力!$A$4:$A$1500,"<="&DATE(2027,4,5),日次入力!$C$4:$C$1500,"Metaウェビナー")) | D57: =IF(COUNTIFS(日次入力!$A$4:$A$1500,">="&DATE(2027,3,30),日次入力!$A$4:$A$1500,"<="&DATE(2027,4,5),日次入力!$C$4:$C$1500,"Metaウェビナー")=0,"",SUMIFS(日次入力!$E$4:$E$1500,日次入力!$A$4:$A$1500,">="&DATE(2027,3,30),日次入力!$A$4:$A$1500,"<="&DATE(2027,4,5),日次入力!$C$4:$C$1500,"Metaウェビナー")) | E57: =IF(COUNTIFS(日次入力!$A$4:$A$1500,">="&DATE(2027,3,30),日次入力!$A$4:$A$1500,"<="&DATE(2027,4,5),日次入力!$C$4:$C$1500,"Metaウェビナー")=0,"",SUMIFS(日次入力!$F$4:$F$1500,日次入力!$A$4:$A$1500,">="&DATE(2027,3,30),日次入力!$A$4:$A$1500,"<="&DATE(2027,4,5),日次入力!$C$4:$C$1500,"Metaウェビナー")) | F57: =IF(COUNTIFS(日次入力!$A$4:$A$1500,">="&DATE(2027,3,30),日次入力!$A$4:$A$1500,"<="&DATE(2027,4,5),日次入力!$C$4:$C$1500,"Metaウェビナー")=0,"",SUMIFS(日次入力!$G$4:$G$1500,日次入力!$A$4:$A$1500,">="&DATE(2027,3,30),日次入力!$A$4:$A$1500,"<="&DATE(2027,4,5),日次入力!$C$4:$C$1500,"Metaウェビナー")) | G57: =IFERROR(E57/D57,"") | H57: =IFERROR(C57/E57,"") | I57: =IFERROR(C57/D57*1000,"") | J57: =IFERROR(F57/E57,"") | K57: =IFERROR(C57/F57,"") | L57: =IF(COUNTIFS(日次入力!$A$4:$A$1500,">="&DATE(2027,3,30),日次入力!$A$4:$A$1500,"<="&DATE(2027,4,5),日次入力!$C$4:$C$1500,"Metaウェビナー")=0,"",SUMIFS(日次入力!$H$4:$H$1500,日次入力!$A$4:$A$1500,">="&DATE(2027,3,30),日次入力!$A$4:$A$1500,"<="&DATE(2027,4,5),日次入力!$C$4:$C$1500,"Metaウェビナー")) | M57: =IF(L57="","",IFERROR(L57/F57,"")) | N57: =IF(COUNTIFS(日次入力!$A$4:$A$1500,">="&DATE(2027,3,30),日次入力!$A$4:$A$1500,"<="&DATE(2027,4,5),日次入力!$C$4:$C$1500,"Metaウェビナー")=0,"",SUMIFS(日次入力!$I$4:$I$1500,日次入力!$A$4:$A$1500,">="&DATE(2027,3,30),日次入力!$A$4:$A$1500,"<="&DATE(2027,4,5),日次入力!$C$4:$C$1500,"Metaウェビナー")) | O57: =IF(N57="","",IFERROR(N57/L57,"")) | P57: =IF(N57=0,"",IFERROR(C57/N57,"")) | Q57: =IF(N57=0,"",IFERROR(IF(C57/N57<=用語集!$B$22,"◎ 許容内","✗ 超過"),"—")) -> — | R57: =IFERROR(用語集!$B$22/P57,"")
A58: 合計 | C58: =SUM(C6:C57) -> 545218 | D58: =SUM(D6:D57) -> 197232 | E58: =SUM(E6:E57) -> 3412 | F58: =SUM(F6:F57) -> 272 | G58: =IFERROR(E58/D58,"") -> 0.017299424 | H58: =IFERROR(C58/E58,"") -> 159.79426 | I58: =IFERROR(C58/D58*1000,"") -> 2764.3486 | J58: =IFERROR(F58/D58,"") -> 0.0013790866 | K58: =IFERROR(C58/F58,"") -> 2004.4779 | L58: =SUM(L6:L57) -> 3 | M58: =IF(L58=0,"",IFERROR(L58/F58,"")) -> 0.011029412 | N58: =SUM(N6:N57) -> 0 | O58: =IF(L58=0,"",IFERROR(N58/L58,"")) -> 0 | P58: =IF(N58=0,"",IFERROR(C58/N58,"")) | Q58: =IF(N58=0,"",IFERROR(IF(C58/N58<=用語集!$B$22,"◎ 許容内","✗ 超過"),"—")) | R58: =IFERROR(用語集!$B$22/P58,"")
A60: Meta ／ 常設・介護校LP （目標CPL ¥3,000）
A61: 週 | B61: 期間 | C61: 消費金額 | D61: IMP | E61: クリック | F61: CV | G61: CTR | H61: CPC | I61: CPM | J61: CVR | K61: CPL | L61: 商談 | M61: 歩留まり | N61: 成約 | O61: 成約率 | P61: 1成約広告費 | Q61: 対許容CPA | R61: 余裕倍率
A62: W1 | B62: 4/7–4/13 | C62: 104849 | D62: 115662 | E62: 9658 | F62: 18 | G62: =IFERROR(E62/D62,"") -> 0.083501928 | H62: =IFERROR(C62/E62,"") -> 10.856181 | I62: =IFERROR(C62/D62*1000,"") -> 906.51208 | J62: =IFERROR(F62/E62,"") -> 0.0018637399 | K62: =IFERROR(C62/F62,"") -> 5824.9444 | L62: 1 | M62: =IF(L62="","",IFERROR(L62/F62,"")) -> 0.055555556 | O62: =IF(N62="","",IFERROR(N62/L62,"")) | P62: =IF(N62=0,"",IFERROR(C62/N62,"")) | Q62: =IF(N62=0,"",IFERROR(IF(C62/N62<=用語集!$B$22,"◎ 許容内","✗ 超過"),"—")) | R62: =IFERROR(用語集!$B$22/P62,"")
A63: W2 | B63: 4/14–4/20 | C63: 45827 | D63: 19906 | E63: 561 | F63: 51 | G63: =IFERROR(E63/D63,"") -> 0.028182458 | H63: =IFERROR(C63/E63,"") -> 81.688057 | I63: =IFERROR(C63/D63*1000,"") -> 2302.1702 | J63: =IFERROR(F63/E63,"") -> 0.090909091 | K63: =IFERROR(C63/F63,"") -> 898.56863 | L63: 2 | M63: =IF(L63="","",IFERROR(L63/F63,"")) -> 0.039215686 | O63: =IF(N63="","",IFERROR(N63/L63,"")) | P63: =IF(N63=0,"",IFERROR(C63/N63,"")) | Q63: =IF(N63=0,"",IFERROR(IF(C63/N63<=用語集!$B$22,"◎ 許容内","✗ 超過"),"—")) | R63: =IFERROR(用語集!$B$22/P63,"")
A64: W3 | B64: 4/21–4/27 | C64: 58556 | D64: 18969 | E64: 644 | F64: 22 | G64: =IFERROR(E64/D64,"") -> 0.033950129 | H64: =IFERROR(C64/E64,"") -> 90.925466 | I64: =IFERROR(C64/D64*1000,"") -> 3086.9313 | J64: =IFERROR(F64/E64,"") -> 0.034161491 | K64: =IFERROR(C64/F64,"") -> 2661.6364 | L64: 2 | M64: =IF(L64="","",IFERROR(L64/F64,"")) -> 0.090909091 | O64: =IF(N64="","",IFERROR(N64/L64,"")) | P64: =IF(N64=0,"",IFERROR(C64/N64,"")) | Q64: =IF(N64=0,"",IFERROR(IF(C64/N64<=用語集!$B$22,"◎ 許容内","✗ 超過"),"—")) | R64: =IFERROR(用語集!$B$22/P64,"")
A65: W4 | B65: 4/28–5/4 | C65: 79731 | D65: 24236 | E65: 621 | F65: 34 | G65: =IFERROR(E65/D65,"") -> 0.02562304 | H65: =IFERROR(C65/E65,"") -> 128.3913 | I65: =IFERROR(C65/D65*1000,"") -> 3289.7755 | J65: =IFERROR(F65/E65,"") -> 0.054750403 | K65: =IFERROR(C65/F65,"") -> 2345.0294 | L65: 1 | M65: =IF(L65="","",IFERROR(L65/F65,"")) -> 0.029411765 | O65: =IF(N65="","",IFERROR(N65/L65,"")) | P65: =IF(N65=0,"",IFERROR(C65/N65,"")) | Q65: =IF(N65=0,"",IFERROR(IF(C65/N65<=用語集!$B$22,"◎ 許容内","✗ 超過"),"—")) | R65: =IFERROR(用語集!$B$22/P65,"")
A66: W5 | B66: 5/5–5/11 | C66: 105749 | D66: 26723 | E66: 867 | F66: 35 | G66: =IFERROR(E66/D66,"") -> 0.032443962 | H66: =IFERROR(C66/E66,"") -> 121.97116 | I66: =IFERROR(C66/D66*1000,"") -> 3957.2279 | J66: =IFERROR(F66/E66,"") -> 0.040369089 | K66: =IFERROR(C66/F66,"") -> 3021.4 | L66: 2 | M66: =IF(L66="","",IFERROR(L66/F66,"")) -> 0.057142857 | O66: =IF(N66="","",IFERROR(N66/L66,"")) | P66: =IF(N66=0,"",IFERROR(C66/N66,"")) | Q66: =IF(N66=0,"",IFERROR(IF(C66/N66<=用語集!$B$22,"◎ 許容内","✗ 超過"),"—")) | R66: =IFERROR(用語集!$B$22/P66,"")
A67: W6 | B67: 5/12–5/18 | C67: 105217 | D67: 23468 | E67: 800 | F67: 31 | G67: =IFERROR(E67/D67,"") -> 0.034088972 | H67: =IFERROR(C67/E67,"") -> 131.52125 | I67: =IFERROR(C67/D67*1000,"") -> 4483.4242 | J67: =IFERROR(F67/E67,"") -> 0.03875 | K67: =IFERROR(C67/F67,"") -> 3394.0968 | L67: 3 | M67: =IF(L67="","",IFERROR(L67/F67,"")) -> 0.096774194 | O67: =IF(N67="","",IFERROR(N67/L67,"")) | P67: =IF(N67=0,"",IFERROR(C67/N67,"")) | Q67: =IF(N67=0,"",IFERROR(IF(C67/N67<=用語集!$B$22,"◎ 許容内","✗ 超過"),"—")) | R67: =IFERROR(用語集!$B$22/P67,"")
A68: W7 | B68: 5/19–5/25 | C68: 105644 | D68: 22405 | E68: 806 | F68: 41 | G68: =IFERROR(E68/D68,"") -> 0.035974113 | H68: =IFERROR(C68/E68,"") -> 131.07196 | I68: =IFERROR(C68/D68*1000,"") -> 4715.1975 | J68: =IFERROR(F68/E68,"") -> 0.050868486 | K68: =IFERROR(C68/F68,"") -> 2576.6829 | L68: 2 | M68: =IF(L68="","",IFERROR(L68/F68,"")) -> 0.048780488 | N68: 1 | O68: =IF(N68="","",IFERROR(N68/L68,"")) -> 0.5 | P68: =IF(N68=0,"",IFERROR(C68/N68,"")) -> 105644 | Q68: =IF(N68=0,"",IFERROR(IF(C68/N68<=用語集!$B$22,"◎ 許容内","✗ 超過"),"—")) -> ◎ 許容内 | R68: =IFERROR(用語集!$B$22/P68,"") -> 2.9059861
A69: W8 | B69: 5/26–6/1 | C69: 103424 | D69: 20757 | E69: 628 | F69: 25 | G69: =IFERROR(E69/D69,"") -> 0.030254854 | H69: =IFERROR(C69/E69,"") -> 164.6879 | I69: =IFERROR(C69/D69*1000,"") -> 4982.6083 | J69: =IFERROR(F69/E69,"") -> 0.039808917 | K69: =IFERROR(C69/F69,"") -> 4136.96 | L69: 1 | M69: =IF(L69="","",IFERROR(L69/F69,"")) -> 0.04 | O69: =IF(N69="","",IFERROR(N69/L69,"")) | P69: =IF(N69=0,"",IFERROR(C69/N69,"")) | Q69: =IF(N69=0,"",IFERROR(IF(C69/N69<=用語集!$B$22,"◎ 許容内","✗ 超過"),"—")) | R69: =IFERROR(用語集!$B$22/P69,"")
A70: W9 | B70: 6/2–6/8 | C70: 137186 | D70: 26913 | E70: 828 | F70: 28 | G70: =IFERROR(E70/D70,"") -> 0.030765801 | H70: =IFERROR(C70/E70,"") -> 165.68357 | I70: =IFERROR(C70/D70*1000,"") -> 5097.3879 | J70: =IFERROR(F70/E70,"") -> 0.033816425 | K70: =IFERROR(C70/F70,"") -> 4899.5 | M70: =IF(L70="","",IFERROR(L70/F70,"")) | O70: =IF(N70="","",IFERROR(N70/L70,"")) | P70: =IF(N70=0,"",IFERROR(C70/N70,"")) | Q70: =IF(N70=0,"",IFERROR(IF(C70/N70<=用語集!$B$22,"◎ 許容内","✗ 超過"),"—")) | R70: =IFERROR(用語集!$B$22/P70,"")
A71: W10 | B71: 6/9–6/15 | C71: =IF(COUNTIFS(日次入力!$A$4:$A$1500,">="&DATE(2026,6,9),日次入力!$A$4:$A$1500,"<="&DATE(2026,6,15),日次入力!$C$4:$C$1500,"Meta介護校")=0,"",SUMIFS(日次入力!$D$4:$D$1500,日次入力!$A$4:$A$1500,">="&DATE(2026,6,9),日次入力!$A$4:$A$1500,"<="&DATE(2026,6,15),日次入力!$C$4:$C$1500,"Meta介護校")) -> 98142 | D71: =IF(COUNTIFS(日次入力!$A$4:$A$1500,">="&DATE(2026,6,9),日次入力!$A$4:$A$1500,"<="&DATE(2026,6,15),日次入力!$C$4:$C$1500,"Meta介護校")=0,"",SUMIFS(日次入力!$E$4:$E$1500,日次入力!$A$4:$A$1500,">="&DATE(2026,6,9),日次入力!$A$4:$A$1500,"<="&DATE(2026,6,15),日次入力!$C$4:$C$1500,"Meta介護校")) -> 16863 | E71: =IF(COUNTIFS(日次入力!$A$4:$A$1500,">="&DATE(2026,6,9),日次入力!$A$4:$A$1500,"<="&DATE(2026,6,15),日次入力!$C$4:$C$1500,"Meta介護校")=0,"",SUMIFS(日次入力!$F$4:$F$1500,日次入力!$A$4:$A$1500,">="&DATE(2026,6,9),日次入力!$A$4:$A$1500,"<="&DATE(2026,6,15),日次入力!$C$4:$C$1500,"Meta介護校")) -> 465 | F71: =IF(COUNTIFS(日次入力!$A$4:$A$1500,">="&DATE(2026,6,9),日次入力!$A$4:$A$1500,"<="&DATE(2026,6,15),日次入力!$C$4:$C$1500,"Meta介護校")=0,"",SUMIFS(日次入力!$G$4:$G$1500,日次入力!$A$4:$A$1500,">="&DATE(2026,6,9),日次入力!$A$4:$A$1500,"<="&DATE(2026,6,15),日次入力!$C$4:$C$1500,"Meta介護校")) -> 19 | G71: =IFERROR(E71/D71,"") -> 0.027575165 | H71: =IFERROR(C71/E71,"") -> 211.05806 | I71: =IFERROR(C71/D71*1000,"") -> 5819.9609 | J71: =IFERROR(F71/E71,"") -> 0.040860215 | K71: =IFERROR(C71/F71,"") -> 5165.3684 | L71: =IF(COUNTIFS(日次入力!$A$4:$A$1500,">="&DATE(2026,6,9),日次入力!$A$4:$A$1500,"<="&DATE(2026,6,15),日次入力!$C$4:$C$1500,"Meta介護校")=0,"",SUMIFS(日次入力!$H$4:$H$1500,日次入力!$A$4:$A$1500,">="&DATE(2026,6,9),日次入力!$A$4:$A$1500,"<="&DATE(2026,6,15),日次入力!$C$4:$C$1500,"Meta介護校")) -> 0 | M71: =IF(L71="","",IFERROR(L71/F71,"")) -> 0 | N71: =IF(COUNTIFS(日次入力!$A$4:$A$1500,">="&DATE(2026,6,9),日次入力!$A$4:$A$1500,"<="&DATE(2026,6,15),日次入力!$C$4:$C$1500,"Meta介護校")=0,"",SUMIFS(日次入力!$I$4:$I$1500,日次入力!$A$4:$A$1500,">="&DATE(2026,6,9),日次入力!$A$4:$A$1500,"<="&DATE(2026,6,15),日次入力!$C$4:$C$1500,"Meta介護校")) -> 0 | O71: =IF(N71="","",IFERROR(N71/L71,"")) | P71: =IF(N71=0,"",IFERROR(C71/N71,"")) | Q71: =IF(N71=0,"",IFERROR(IF(C71/N71<=用語集!$B$22,"◎ 許容内","✗ 超過"),"—")) | R71: =IFERROR(用語集!$B$22/P71,"")
A72: W11 | B72: 6/16–6/22 | C72: =IF(COUNTIFS(日次入力!$A$4:$A$1500,">="&DATE(2026,6,16),日次入力!$A$4:$A$1500,"<="&DATE(2026,6,22),日次入力!$C$4:$C$1500,"Meta介護校")=0,"",SUMIFS(日次入力!$D$4:$D$1500,日次入力!$A$4:$A$1500,">="&DATE(2026,6,16),日次入力!$A$4:$A$1500,"<="&DATE(2026,6,22),日次入力!$C$4:$C$1500,"Meta介護校")) -> 102707 | D72: =IF(COUNTIFS(日次入力!$A$4:$A$1500,">="&DATE(2026,6,16),日次入力!$A$4:$A$1500,"<="&DATE(2026,6,22),日次入力!$C$4:$C$1500,"Meta介護校")=0,"",SUMIFS(日次入力!$E$4:$E$1500,日次入力!$A$4:$A$1500,">="&DATE(2026,6,16),日次入力!$A$4:$A$1500,"<="&DATE(2026,6,22),日次入力!$C$4:$C$1500,"Meta介護校")) -> 32282 | E72: =IF(COUNTIFS(日次入力!$A$4:$A$1500,">="&DATE(2026,6,16),日次入力!$A$4:$A$1500,"<="&DATE(2026,6,22),日次入力!$C$4:$C$1500,"Meta介護校")=0,"",SUMIFS(日次入力!$F$4:$F$1500,日次入力!$A$4:$A$1500,">="&DATE(2026,6,16),日次入力!$A$4:$A$1500,"<="&DATE(2026,6,22),日次入力!$C$4:$C$1500,"Meta介護校")) -> 773 | F72: =IF(COUNTIFS(日次入力!$A$4:$A$1500,">="&DATE(2026,6,16),日次入力!$A$4:$A$1500,"<="&DATE(2026,6,22),日次入力!$C$4:$C$1500,"Meta介護校")=0,"",SUMIFS(日次入力!$G$4:$G$1500,日次入力!$A$4:$A$1500,">="&DATE(2026,6,16),日次入力!$A$4:$A$1500,"<="&DATE(2026,6,22),日次入力!$C$4:$C$1500,"Meta介護校")) -> 26 | G72: =IFERROR(E72/D72,"") -> 0.023945233 | H72: =IFERROR(C72/E72,"") -> 132.86805 | I72: =IFERROR(C72/D72*1000,"") -> 3181.5563 | J72: =IFERROR(F72/E72,"") -> 0.033635188 | K72: =IFERROR(C72/F72,"") -> 3950.2692 | L72: =IF(COUNTIFS(日次入力!$A$4:$A$1500,">="&DATE(2026,6,16),日次入力!$A$4:$A$1500,"<="&DATE(2026,6,22),日次入力!$C$4:$C$1500,"Meta介護校")=0,"",SUMIFS(日次入力!$H$4:$H$1500,日次入力!$A$4:$A$1500,">="&DATE(2026,6,16),日次入力!$A$4:$A$1500,"<="&DATE(2026,6,22),日次入力!$C$4:$C$1500,"Meta介護校")) -> 2 | M72: =IF(L72="","",IFERROR(L72/F72,"")) -> 0.076923077 | N72: =IF(COUNTIFS(日次入力!$A$4:$A$1500,">="&DATE(2026,6,16),日次入力!$A$4:$A$1500,"<="&DATE(2026,6,22),日次入力!$C$4:$C$1500,"Meta介護校")=0,"",SUMIFS(日次入力!$I$4:$I$1500,日次入力!$A$4:$A$1500,">="&DATE(2026,6,16),日次入力!$A$4:$A$1500,"<="&DATE(2026,6,22),日次入力!$C$4:$C$1500,"Meta介護校")) -> 0 | O72: =IF(N72="","",IFERROR(N72/L72,"")) -> 0 | P72: =IF(N72=0,"",IFERROR(C72/N72,"")) | Q72: =IF(N72=0,"",IFERROR(IF(C72/N72<=用語集!$B$22,"◎ 許容内","✗ 超過"),"—")) | R72: =IFERROR(用語集!$B$22/P72,"")
A73: W12 | B73: 6/23–6/29 | C73: =IF(COUNTIFS(日次入力!$A$4:$A$1500,">="&DATE(2026,6,23),日次入力!$A$4:$A$1500,"<="&DATE(2026,6,29),日次入力!$C$4:$C$1500,"Meta介護校")=0,"",SUMIFS(日次入力!$D$4:$D$1500,日次入力!$A$4:$A$1500,">="&DATE(2026,6,23),日次入力!$A$4:$A$1500,"<="&DATE(2026,6,29),日次入力!$C$4:$C$1500,"Meta介護校")) | D73: =IF(COUNTIFS(日次入力!$A$4:$A$1500,">="&DATE(2026,6,23),日次入力!$A$4:$A$1500,"<="&DATE(2026,6,29),日次入力!$C$4:$C$1500,"Meta介護校")=0,"",SUMIFS(日次入力!$E$4:$E$1500,日次入力!$A$4:$A$1500,">="&DATE(2026,6,23),日次入力!$A$4:$A$1500,"<="&DATE(2026,6,29),日次入力!$C$4:$C$1500,"Meta介護校")) | E73: =IF(COUNTIFS(日次入力!$A$4:$A$1500,">="&DATE(2026,6,23),日次入力!$A$4:$A$1500,"<="&DATE(2026,6,29),日次入力!$C$4:$C$1500,"Meta介護校")=0,"",SUMIFS(日次入力!$F$4:$F$1500,日次入力!$A$4:$A$1500,">="&DATE(2026,6,23),日次入力!$A$4:$A$1500,"<="&DATE(2026,6,29),日次入力!$C$4:$C$1500,"Meta介護校")) | F73: =IF(COUNTIFS(日次入力!$A$4:$A$1500,">="&DATE(2026,6,23),日次入力!$A$4:$A$1500,"<="&DATE(2026,6,29),日次入力!$C$4:$C$1500,"Meta介護校")=0,"",SUMIFS(日次入力!$G$4:$G$1500,日次入力!$A$4:$A$1500,">="&DATE(2026,6,23),日次入力!$A$4:$A$1500,"<="&DATE(2026,6,29),日次入力!$C$4:$C$1500,"Meta介護校")) | G73: =IFERROR(E73/D73,"") | H73: =IFERROR(C73/E73,"") | I73: =IFERROR(C73/D73*1000,"") | J73: =IFERROR(F73/E73,"") | K73: =IFERROR(C73/F73,"") | L73: =IF(COUNTIFS(日次入力!$A$4:$A$1500,">="&DATE(2026,6,23),日次入力!$A$4:$A$1500,"<="&DATE(2026,6,29),日次入力!$C$4:$C$1500,"Meta介護校")=0,"",SUMIFS(日次入力!$H$4:$H$1500,日次入力!$A$4:$A$1500,">="&DATE(2026,6,23),日次入力!$A$4:$A$1500,"<="&DATE(2026,6,29),日次入力!$C$4:$C$1500,"Meta介護校")) | M73: =IF(L73="","",IFERROR(L73/F73,"")) | N73: =IF(COUNTIFS(日次入力!$A$4:$A$1500,">="&DATE(2026,6,23),日次入力!$A$4:$A$1500,"<="&DATE(2026,6,29),日次入力!$C$4:$C$1500,"Meta介護校")=0,"",SUMIFS(日次入力!$I$4:$I$1500,日次入力!$A$4:$A$1500,">="&DATE(2026,6,23),日次入力!$A$4:$A$1500,"<="&DATE(2026,6,29),日次入力!$C$4:$C$1500,"Meta介護校")) | O73: =IF(N73="","",IFERROR(N73/L73,"")) | P73: =IF(N73=0,"",IFERROR(C73/N73,"")) | Q73: =IF(N73=0,"",IFERROR(IF(C73/N73<=用語集!$B$22,"◎ 許容内","✗ 超過"),"—")) -> — | R73: =IFERROR(用語集!$B$22/P73,"")
A74: W13 | B74: 6/30–7/6 | C74: =IF(COUNTIFS(日次入力!$A$4:$A$1500,">="&DATE(2026,6,30),日次入力!$A$4:$A$1500,"<="&DATE(2026,7,6),日次入力!$C$4:$C$1500,"Meta介護校")=0,"",SUMIFS(日次入力!$D$4:$D$1500,日次入力!$A$4:$A$1500,">="&DATE(2026,6,30),日次入力!$A$4:$A$1500,"<="&DATE(2026,7,6),日次入力!$C$4:$C$1500,"Meta介護校")) | D74: =IF(COUNTIFS(日次入力!$A$4:$A$1500,">="&DATE(2026,6,30),日次入力!$A$4:$A$1500,"<="&DATE(2026,7,6),日次入力!$C$4:$C$1500,"Meta介護校")=0,"",SUMIFS(日次入力!$E$4:$E$1500,日次入力!$A$4:$A$1500,">="&DATE(2026,6,30),日次入力!$A$4:$A$1500,"<="&DATE(2026,7,6),日次入力!$C$4:$C$1500,"Meta介護校")) | E74: =IF(COUNTIFS(日次入力!$A$4:$A$1500,">="&DATE(2026,6,30),日次入力!$A$4:$A$1500,"<="&DATE(2026,7,6),日次入力!$C$4:$C$1500,"Meta介護校")=0,"",SUMIFS(日次入力!$F$4:$F$1500,日次入力!$A$4:$A$1500,">="&DATE(2026,6,30),日次入力!$A$4:$A$1500,"<="&DATE(2026,7,6),日次入力!$C$4:$C$1500,"Meta介護校")) | F74: =IF(COUNTIFS(日次入力!$A$4:$A$1500,">="&DATE(2026,6,30),日次入力!$A$4:$A$1500,"<="&DATE(2026,7,6),日次入力!$C$4:$C$1500,"Meta介護校")=0,"",SUMIFS(日次入力!$G$4:$G$1500,日次入力!$A$4:$A$1500,">="&DATE(2026,6,30),日次入力!$A$4:$A$1500,"<="&DATE(2026,7,6),日次入力!$C$4:$C$1500,"Meta介護校")) | G74: =IFERROR(E74/D74,"") | H74: =IFERROR(C74/E74,"") | I74: =IFERROR(C74/D74*1000,"") | J74: =IFERROR(F74/E74,"") | K74: =IFERROR(C74/F74,"") | L74: =IF(COUNTIFS(日次入力!$A$4:$A$1500,">="&DATE(2026,6,30),日次入力!$A$4:$A$1500,"<="&DATE(2026,7,6),日次入力!$C$4:$C$1500,"Meta介護校")=0,"",SUMIFS(日次入力!$H$4:$H$1500,日次入力!$A$4:$A$1500,">="&DATE(2026,6,30),日次入力!$A$4:$A$1500,"<="&DATE(2026,7,6),日次入力!$C$4:$C$1500,"Meta介護校")) | M74: =IF(L74="","",IFERROR(L74/F74,"")) | N74: =IF(COUNTIFS(日次入力!$A$4:$A$1500,">="&DATE(2026,6,30),日次入力!$A$4:$A$1500,"<="&DATE(2026,7,6),日次入力!$C$4:$C$1500,"Meta介護校")=0,"",SUMIFS(日次入力!$I$4:$I$1500,日次入力!$A$4:$A$1500,">="&DATE(2026,6,30),日次入力!$A$4:$A$1500,"<="&DATE(2026,7,6),日次入力!$C$4:$C$1500,"Meta介護校")) | O74: =IF(N74="","",IFERROR(N74/L74,"")) | P74: =IF(N74=0,"",IFERROR(C74/N74,"")) | Q74: =IF(N74=0,"",IFERROR(IF(C74/N74<=用語集!$B$22,"◎ 許容内","✗ 超過"),"—")) -> — | R74: =IFERROR(用語集!$B$22/P74,"")
A75: W14 | B75: 7/7–7/13 | C75: =IF(COUNTIFS(日次入力!$A$4:$A$1500,">="&DATE(2026,7,7),日次入力!$A$4:$A$1500,"<="&DATE(2026,7,13),日次入力!$C$4:$C$1500,"Meta介護校")=0,"",SUMIFS(日次入力!$D$4:$D$1500,日次入力!$A$4:$A$1500,">="&DATE(2026,7,7),日次入力!$A$4:$A$1500,"<="&DATE(2026,7,13),日次入力!$C$4:$C$1500,"Meta介護校")) | D75: =IF(COUNTIFS(日次入力!$A$4:$A$1500,">="&DATE(2026,7,7),日次入力!$A$4:$A$1500,"<="&DATE(2026,7,13),日次入力!$C$4:$C$1500,"Meta介護校")=0,"",SUMIFS(日次入力!$E$4:$E$1500,日次入力!$A$4:$A$1500,">="&DATE(2026,7,7),日次入力!$A$4:$A$1500,"<="&DATE(2026,7,13),日次入力!$C$4:$C$1500,"Meta介護校")) | E75: =IF(COUNTIFS(日次入力!$A$4:$A$1500,">="&DATE(2026,7,7),日次入力!$A$4:$A$1500,"<="&DATE(2026,7,13),日次入力!$C$4:$C$1500,"Meta介護校")=0,"",SUMIFS(日次入力!$F$4:$F$1500,日次入力!$A$4:$A$1500,">="&DATE(2026,7,7),日次入力!$A$4:$A$1500,"<="&DATE(2026,7,13),日次入力!$C$4:$C$1500,"Meta介護校")) | F75: =IF(COUNTIFS(日次入力!$A$4:$A$1500,">="&DATE(2026,7,7),日次入力!$A$4:$A$1500,"<="&DATE(2026,7,13),日次入力!$C$4:$C$1500,"Meta介護校")=0,"",SUMIFS(日次入力!$G$4:$G$1500,日次入力!$A$4:$A$1500,">="&DATE(2026,7,7),日次入力!$A$4:$A$1500,"<="&DATE(2026,7,13),日次入力!$C$4:$C$1500,"Meta介護校")) | G75: =IFERROR(E75/D75,"") | H75: =IFERROR(C75/E75,"") | I75: =IFERROR(C75/D75*1000,"") | J75: =IFERROR(F75/E75,"") | K75: =IFERROR(C75/F75,"") | L75: =IF(COUNTIFS(日次入力!$A$4:$A$1500,">="&DATE(2026,7,7),日次入力!$A$4:$A$1500,"<="&DATE(2026,7,13),日次入力!$C$4:$C$1500,"Meta介護校")=0,"",SUMIFS(日次入力!$H$4:$H$1500,日次入力!$A$4:$A$1500,">="&DATE(2026,7,7),日次入力!$A$4:$A$1500,"<="&DATE(2026,7,13),日次入力!$C$4:$C$1500,"Meta介護校")) | M75: =IF(L75="","",IFERROR(L75/F75,"")) | N75: =IF(COUNTIFS(日次入力!$A$4:$A$1500,">="&DATE(2026,7,7),日次入力!$A$4:$A$1500,"<="&DATE(2026,7,13),日次入力!$C$4:$C$1500,"Meta介護校")=0,"",SUMIFS(日次入力!$I$4:$I$1500,日次入力!$A$4:$A$1500,">="&DATE(2026,7,7),日次入力!$A$4:$A$1500,"<="&DATE(2026,7,13),日次入力!$C$4:$C$1500,"Meta介護校")) | O75: =IF(N75="","",IFERROR(N75/L75,"")) | P75: =IF(N75=0,"",IFERROR(C75/N75,"")) | Q75: =IF(N75=0,"",IFERROR(IF(C75/N75<=用語集!$B$22,"◎ 許容内","✗ 超過"),"—")) -> — | R75: =IFERROR(用語集!$B$22/P75,"")
A76: W15 | B76: 7/14–7/20 | C76: =IF(COUNTIFS(日次入力!$A$4:$A$1500,">="&DATE(2026,7,14),日次入力!$A$4:$A$1500,"<="&DATE(2026,7,20),日次入力!$C$4:$C$1500,"Meta介護校")=0,"",SUMIFS(日次入力!$D$4:$D$1500,日次入力!$A$4:$A$1500,">="&DATE(2026,7,14),日次入力!$A$4:$A$1500,"<="&DATE(2026,7,20),日次入力!$C$4:$C$1500,"Meta介護校")) | D76: =IF(COUNTIFS(日次入力!$A$4:$A$1500,">="&DATE(2026,7,14),日次入力!$A$4:$A$1500,"<="&DATE(2026,7,20),日次入力!$C$4:$C$1500,"Meta介護校")=0,"",SUMIFS(日次入力!$E$4:$E$1500,日次入力!$A$4:$A$1500,">="&DATE(2026,7,14),日次入力!$A$4:$A$1500,"<="&DATE(2026,7,20),日次入力!$C$4:$C$1500,"Meta介護校")) | E76: =IF(COUNTIFS(日次入力!$A$4:$A$1500,">="&DATE(2026,7,14),日次入力!$A$4:$A$1500,"<="&DATE(2026,7,20),日次入力!$C$4:$C$1500,"Meta介護校")=0,"",SUMIFS(日次入力!$F$4:$F$1500,日次入力!$A$4:$A$1500,">="&DATE(2026,7,14),日次入力!$A$4:$A$1500,"<="&DATE(2026,7,20),日次入力!$C$4:$C$1500,"Meta介護校")) | F76: =IF(COUNTIFS(日次入力!$A$4:$A$1500,">="&DATE(2026,7,14),日次入力!$A$4:$A$1500,"<="&DATE(2026,7,20),日次入力!$C$4:$C$1500,"Meta介護校")=0,"",SUMIFS(日次入力!$G$4:$G$1500,日次入力!$A$4:$A$1500,">="&DATE(2026,7,14),日次入力!$A$4:$A$1500,"<="&DATE(2026,7,20),日次入力!$C$4:$C$1500,"Meta介護校")) | G76: =IFERROR(E76/D76,"") | H76: =IFERROR(C76/E76,"") | I76: =IFERROR(C76/D76*1000,"") | J76: =IFERROR(F76/E76,"") | K76: =IFERROR(C76/F76,"") | L76: =IF(COUNTIFS(日次入力!$A$4:$A$1500,">="&DATE(2026,7,14),日次入力!$A$4:$A$1500,"<="&DATE(2026,7,20),日次入力!$C$4:$C$1500,"Meta介護校")=0,"",SUMIFS(日次入力!$H$4:$H$1500,日次入力!$A$4:$A$1500,">="&DATE(2026,7,14),日次入力!$A$4:$A$1500,"<="&DATE(2026,7,20),日次入力!$C$4:$C$1500,"Meta介護校")) | M76: =IF(L76="","",IFERROR(L76/F76,"")) | N76: =IF(COUNTIFS(日次入力!$A$4:$A$1500,">="&DATE(2026,7,14),日次入力!$A$4:$A$1500,"<="&DATE(2026,7,20),日次入力!$C$4:$C$1500,"Meta介護校")=0,"",SUMIFS(日次入力!$I$4:$I$1500,日次入力!$A$4:$A$1500,">="&DATE(2026,7,14),日次入力!$A$4:$A$1500,"<="&DATE(2026,7,20),日次入力!$C$4:$C$1500,"Meta介護校")) | O76: =IF(N76="","",IFERROR(N76/L76,"")) | P76: =IF(N76=0,"",IFERROR(C76/N76,"")) | Q76: =IF(N76=0,"",IFERROR(IF(C76/N76<=用語集!$B$22,"◎ 許容内","✗ 超過"),"—")) -> — | R76: =IFERROR(用語集!$B$22/P76,"")
A77: W16 | B77: 7/21–7/27 | C77: =IF(COUNTIFS(日次入力!$A$4:$A$1500,">="&DATE(2026,7,21),日次入力!$A$4:$A$1500,"<="&DATE(2026,7,27),日次入力!$C$4:$C$1500,"Meta介護校")=0,"",SUMIFS(日次入力!$D$4:$D$1500,日次入力!$A$4:$A$1500,">="&DATE(2026,7,21),日次入力!$A$4:$A$1500,"<="&DATE(2026,7,27),日次入力!$C$4:$C$1500,"Meta介護校")) | D77: =IF(COUNTIFS(日次入力!$A$4:$A$1500,">="&DATE(2026,7,21),日次入力!$A$4:$A$1500,"<="&DATE(2026,7,27),日次入力!$C$4:$C$1500,"Meta介護校")=0,"",SUMIFS(日次入力!$E$4:$E$1500,日次入力!$A$4:$A$1500,">="&DATE(2026,7,21),日次入力!$A$4:$A$1500,"<="&DATE(2026,7,27),日次入力!$C$4:$C$1500,"Meta介護校")) | E77: =IF(COUNTIFS(日次入力!$A$4:$A$1500,">="&DATE(2026,7,21),日次入力!$A$4:$A$1500,"<="&DATE(2026,7,27),日次入力!$C$4:$C$1500,"Meta介護校")=0,"",SUMIFS(日次入力!$F$4:$F$1500,日次入力!$A$4:$A$1500,">="&DATE(2026,7,21),日次入力!$A$4:$A$1500,"<="&DATE(2026,7,27),日次入力!$C$4:$C$1500,"Meta介護校")) | F77: =IF(COUNTIFS(日次入力!$A$4:$A$1500,">="&DATE(2026,7,21),日次入力!$A$4:$A$1500,"<="&DATE(2026,7,27),日次入力!$C$4:$C$1500,"Meta介護校")=0,"",SUMIFS(日次入力!$G$4:$G$1500,日次入力!$A$4:$A$1500,">="&DATE(2026,7,21),日次入力!$A$4:$A$1500,"<="&DATE(2026,7,27),日次入力!$C$4:$C$1500,"Meta介護校")) | G77: =IFERROR(E77/D77,"") | H77: =IFERROR(C77/E77,"") | I77: =IFERROR(C77/D77*1000,"") | J77: =IFERROR(F77/E77,"") | K77: =IFERROR(C77/F77,"") | L77: =IF(COUNTIFS(日次入力!$A$4:$A$1500,">="&DATE(2026,7,21),日次入力!$A$4:$A$1500,"<="&DATE(2026,7,27),日次入力!$C$4:$C$1500,"Meta介護校")=0,"",SUMIFS(日次入力!$H$4:$H$1500,日次入力!$A$4:$A$1500,">="&DATE(2026,7,21),日次入力!$A$4:$A$1500,"<="&DATE(2026,7,27),日次入力!$C$4:$C$1500,"Meta介護校")) | M77: =IF(L77="","",IFERROR(L77/F77,"")) | N77: =IF(COUNTIFS(日次入力!$A$4:$A$1500,">="&DATE(2026,7,21),日次入力!$A$4:$A$1500,"<="&DATE(2026,7,27),日次入力!$C$4:$C$1500,"Meta介護校")=0,"",SUMIFS(日次入力!$I$4:$I$1500,日次入力!$A$4:$A$1500,">="&DATE(2026,7,21),日次入力!$A$4:$A$1500,"<="&DATE(2026,7,27),日次入力!$C$4:$C$1500,"Meta介護校")) | O77: =IF(N77="","",IFERROR(N77/L77,"")) | P77: =IF(N77=0,"",IFERROR(C77/N77,"")) | Q77: =IF(N77=0,"",IFERROR(IF(C77/N77<=用語集!$B$22,"◎ 許容内","✗ 超過"),"—")) -> — | R77: =IFERROR(用語集!$B$22/P77,"")
A78: W17 | B78: 7/28–8/3 | C78: =IF(COUNTIFS(日次入力!$A$4:$A$1500,">="&DATE(2026,7,28),日次入力!$A$4:$A$1500,"<="&DATE(2026,8,3),日次入力!$C$4:$C$1500,"Meta介護校")=0,"",SUMIFS(日次入力!$D$4:$D$1500,日次入力!$A$4:$A$1500,">="&DATE(2026,7,28),日次入力!$A$4:$A$1500,"<="&DATE(2026,8,3),日次入力!$C$4:$C$1500,"Meta介護校")) | D78: =IF(COUNTIFS(日次入力!$A$4:$A$1500,">="&DATE(2026,7,28),日次入力!$A$4:$A$1500,"<="&DATE(2026,8,3),日次入力!$C$4:$C$1500,"Meta介護校")=0,"",SUMIFS(日次入力!$E$4:$E$1500,日次入力!$A$4:$A$1500,">="&DATE(2026,7,28),日次入力!$A$4:$A$1500,"<="&DATE(2026,8,3),日次入力!$C$4:$C$1500,"Meta介護校")) | E78: =IF(COUNTIFS(日次入力!$A$4:$A$1500,">="&DATE(2026,7,28),日次入力!$A$4:$A$1500,"<="&DATE(2026,8,3),日次入力!$C$4:$C$1500,"Meta介護校")=0,"",SUMIFS(日次入力!$F$4:$F$1500,日次入力!$A$4:$A$1500,">="&DATE(2026,7,28),日次入力!$A$4:$A$1500,"<="&DATE(2026,8,3),日次入力!$C$4:$C$1500,"Meta介護校")) | F78: =IF(COUNTIFS(日次入力!$A$4:$A$1500,">="&DATE(2026,7,28),日次入力!$A$4:$A$1500,"<="&DATE(2026,8,3),日次入力!$C$4:$C$1500,"Meta介護校")=0,"",SUMIFS(日次入力!$G$4:$G$1500,日次入力!$A$4:$A$1500,">="&DATE(2026,7,28),日次入力!$A$4:$A$1500,"<="&DATE(2026,8,3),日次入力!$C$4:$C$1500,"Meta介護校")) | G78: =IFERROR(E78/D78,"") | H78: =IFERROR(C78/E78,"") | I78: =IFERROR(C78/D78*1000,"") | J78: =IFERROR(F78/E78,"") | K78: =IFERROR(C78/F78,"") | L78: =IF(COUNTIFS(日次入力!$A$4:$A$1500,">="&DATE(2026,7,28),日次入力!$A$4:$A$1500,"<="&DATE(2026,8,3),日次入力!$C$4:$C$1500,"Meta介護校")=0,"",SUMIFS(日次入力!$H$4:$H$1500,日次入力!$A$4:$A$1500,">="&DATE(2026,7,28),日次入力!$A$4:$A$1500,"<="&DATE(2026,8,3),日次入力!$C$4:$C$1500,"Meta介護校")) | M78: =IF(L78="","",IFERROR(L78/F78,"")) | N78: =IF(COUNTIFS(日次入力!$A$4:$A$1500,">="&DATE(2026,7,28),日次入力!$A$4:$A$1500,"<="&DATE(2026,8,3),日次入力!$C$4:$C$1500,"Meta介護校")=0,"",SUMIFS(日次入力!$I$4:$I$1500,日次入力!$A$4:$A$1500,">="&DATE(2026,7,28),日次入力!$A$4:$A$1500,"<="&DATE(2026,8,3),日次入力!$C$4:$C$1500,"Meta介護校")) | O78: =IF(N78="","",IFERROR(N78/L78,"")) | P78: =IF(N78=0,"",IFERROR(C78/N78,"")) | Q78: =IF(N78=0,"",IFERROR(IF(C78/N78<=用語集!$B$22,"◎ 許容内","✗ 超過"),"—")) -> — | R78: =IFERROR(用語集!$B$22/P78,"")
A79: W18 | B79: 8/4–8/10 | C79: =IF(COUNTIFS(日次入力!$A$4:$A$1500,">="&DATE(2026,8,4),日次入力!$A$4:$A$1500,"<="&DATE(2026,8,10),日次入力!$C$4:$C$1500,"Meta介護校")=0,"",SUMIFS(日次入力!$D$4:$D$1500,日次入力!$A$4:$A$1500,">="&DATE(2026,8,4),日次入力!$A$4:$A$1500,"<="&DATE(2026,8,10),日次入力!$C$4:$C$1500,"Meta介護校")) | D79: =IF(COUNTIFS(日次入力!$A$4:$A$1500,">="&DATE(2026,8,4),日次入力!$A$4:$A$1500,"<="&DATE(2026,8,10),日次入力!$C$4:$C$1500,"Meta介護校")=0,"",SUMIFS(日次入力!$E$4:$E$1500,日次入力!$A$4:$A$1500,">="&DATE(2026,8,4),日次入力!$A$4:$A$1500,"<="&DATE(2026,8,10),日次入力!$C$4:$C$1500,"Meta介護校")) | E79: =IF(COUNTIFS(日次入力!$A$4:$A$1500,">="&DATE(2026,8,4),日次入力!$A$4:$A$1500,"<="&DATE(2026,8,10),日次入力!$C$4:$C$1500,"Meta介護校")=0,"",SUMIFS(日次入力!$F$4:$F$1500,日次入力!$A$4:$A$1500,">="&DATE(2026,8,4),日次入力!$A$4:$A$1500,"<="&DATE(2026,8,10),日次入力!$C$4:$C$1500,"Meta介護校")) | F79: =IF(COUNTIFS(日次入力!$A$4:$A$1500,">="&DATE(2026,8,4),日次入力!$A$4:$A$1500,"<="&DATE(2026,8,10),日次入力!$C$4:$C$1500,"Meta介護校")=0,"",SUMIFS(日次入力!$G$4:$G$1500,日次入力!$A$4:$A$1500,">="&DATE(2026,8,4),日次入力!$A$4:$A$1500,"<="&DATE(2026,8,10),日次入力!$C$4:$C$1500,"Meta介護校")) | G79: =IFERROR(E79/D79,"") | H79: =IFERROR(C79/E79,"") | I79: =IFERROR(C79/D79*1000,"") | J79: =IFERROR(F79/E79,"") | K79: =IFERROR(C79/F79,"") | L79: =IF(COUNTIFS(日次入力!$A$4:$A$1500,">="&DATE(2026,8,4),日次入力!$A$4:$A$1500,"<="&DATE(2026,8,10),日次入力!$C$4:$C$1500,"Meta介護校")=0,"",SUMIFS(日次入力!$H$4:$H$1500,日次入力!$A$4:$A$1500,">="&DATE(2026,8,4),日次入力!$A$4:$A$1500,"<="&DATE(2026,8,10),日次入力!$C$4:$C$1500,"Meta介護校")) | M79: =IF(L79="","",IFERROR(L79/F79,"")) | N79: =IF(COUNTIFS(日次入力!$A$4:$A$1500,">="&DATE(2026,8,4),日次入力!$A$4:$A$1500,"<="&DATE(2026,8,10),日次入力!$C$4:$C$1500,"Meta介護校")=0,"",SUMIFS(日次入力!$I$4:$I$1500,日次入力!$A$4:$A$1500,">="&DATE(2026,8,4),日次入力!$A$4:$A$1500,"<="&DATE(2026,8,10),日次入力!$C$4:$C$1500,"Meta介護校")) | O79: =IF(N79="","",IFERROR(N79/L79,"")) | P79: =IF(N79=0,"",IFERROR(C79/N79,"")) | Q79: =IF(N79=0,"",IFERROR(IF(C79/N79<=用語集!$B$22,"◎ 許容内","✗ 超過"),"—")) -> — | R79: =IFERROR(用語集!$B$22/P79,"")
A80: W19 | B80: 8/11–8/17 | C80: =IF(COUNTIFS(日次入力!$A$4:$A$1500,">="&DATE(2026,8,11),日次入力!$A$4:$A$1500,"<="&DATE(2026,8,17),日次入力!$C$4:$C$1500,"Meta介護校")=0,"",SUMIFS(日次入力!$D$4:$D$1500,日次入力!$A$4:$A$1500,">="&DATE(2026,8,11),日次入力!$A$4:$A$1500,"<="&DATE(2026,8,17),日次入力!$C$4:$C$1500,"Meta介護校")) | D80: =IF(COUNTIFS(日次入力!$A$4:$A$1500,">="&DATE(2026,8,11),日次入力!$A$4:$A$1500,"<="&DATE(2026,8,17),日次入力!$C$4:$C$1500,"Meta介護校")=0,"",SUMIFS(日次入力!$E$4:$E$1500,日次入力!$A$4:$A$1500,">="&DATE(2026,8,11),日次入力!$A$4:$A$1500,"<="&DATE(2026,8,17),日次入力!$C$4:$C$1500,"Meta介護校")) | E80: =IF(COUNTIFS(日次入力!$A$4:$A$1500,">="&DATE(2026,8,11),日次入力!$A$4:$A$1500,"<="&DATE(2026,8,17),日次入力!$C$4:$C$1500,"Meta介護校")=0,"",SUMIFS(日次入力!$F$4:$F$1500,日次入力!$A$4:$A$1500,">="&DATE(2026,8,11),日次入力!$A$4:$A$1500,"<="&DATE(2026,8,17),日次入力!$C$4:$C$1500,"Meta介護校")) | F80: =IF(COUNTIFS(日次入力!$A$4:$A$1500,">="&DATE(2026,8,11),日次入力!$A$4:$A$1500,"<="&DATE(2026,8,17),日次入力!$C$4:$C$1500,"Meta介護校")=0,"",SUMIFS(日次入力!$G$4:$G$1500,日次入力!$A$4:$A$1500,">="&DATE(2026,8,11),日次入力!$A$4:$A$1500,"<="&DATE(2026,8,17),日次入力!$C$4:$C$1500,"Meta介護校")) | G80: =IFERROR(E80/D80,"") | H80: =IFERROR(C80/E80,"") | I80: =IFERROR(C80/D80*1000,"") | J80: =IFERROR(F80/E80,"") | K80: =IFERROR(C80/F80,"") | L80: =IF(COUNTIFS(日次入力!$A$4:$A$1500,">="&DATE(2026,8,11),日次入力!$A$4:$A$1500,"<="&DATE(2026,8,17),日次入力!$C$4:$C$1500,"Meta介護校")=0,"",SUMIFS(日次入力!$H$4:$H$1500,日次入力!$A$4:$A$1500,">="&DATE(2026,8,11),日次入力!$A$4:$A$1500,"<="&DATE(2026,8,17),日次入力!$C$4:$C$1500,"Meta介護校")) | M80: =IF(L80="","",IFERROR(L80/F80,"")) | N80: =IF(COUNTIFS(日次入力!$A$4:$A$1500,">="&DATE(2026,8,11),日次入力!$A$4:$A$1500,"<="&DATE(2026,8,17),日次入力!$C$4:$C$1500,"Meta介護校")=0,"",SUMIFS(日次入力!$I$4:$I$1500,日次入力!$A$4:$A$1500,">="&DATE(2026,8,11),日次入力!$A$4:$A$1500,"<="&DATE(2026,8,17),日次入力!$C$4:$C$1500,"Meta介護校")) | O80: =IF(N80="","",IFERROR(N80/L80,"")) | P80: =IF(N80=0,"",IFERROR(C80/N80,"")) | Q80: =IF(N80=0,"",IFERROR(IF(C80/N80<=用語集!$B$22,"◎ 許容内","✗ 超過"),"—")) -> — | R80: =IFERROR(用語集!$B$22/P80,"")
A81: W20 | B81: 8/18–8/24 | C81: =IF(COUNTIFS(日次入力!$A$4:$A$1500,">="&DATE(2026,8,18),日次入力!$A$4:$A$1500,"<="&DATE(2026,8,24),日次入力!$C$4:$C$1500,"Meta介護校")=0,"",SUMIFS(日次入力!$D$4:$D$1500,日次入力!$A$4:$A$1500,">="&DATE(2026,8,18),日次入力!$A$4:$A$1500,"<="&DATE(2026,8,24),日次入力!$C$4:$C$1500,"Meta介護校")) | D81: =IF(COUNTIFS(日次入力!$A$4:$A$1500,">="&DATE(2026,8,18),日次入力!$A$4:$A$1500,"<="&DATE(2026,8,24),日次入力!$C$4:$C$1500,"Meta介護校")=0,"",SUMIFS(日次入力!$E$4:$E$1500,日次入力!$A$4:$A$1500,">="&DATE(2026,8,18),日次入力!$A$4:$A$1500,"<="&DATE(2026,8,24),日次入力!$C$4:$C$1500,"Meta介護校")) | E81: =IF(COUNTIFS(日次入力!$A$4:$A$1500,">="&DATE(2026,8,18),日次入力!$A$4:$A$1500,"<="&DATE(2026,8,24),日次入力!$C$4:$C$1500,"Meta介護校")=0,"",SUMIFS(日次入力!$F$4:$F$1500,日次入力!$A$4:$A$1500,">="&DATE(2026,8,18),日次入力!$A$4:$A$1500,"<="&DATE(2026,8,24),日次入力!$C$4:$C$1500,"Meta介護校")) | F81: =IF(COUNTIFS(日次入力!$A$4:$A$1500,">="&DATE(2026,8,18),日次入力!$A$4:$A$1500,"<="&DATE(2026,8,24),日次入力!$C$4:$C$1500,"Meta介護校")=0,"",SUMIFS(日次入力!$G$4:$G$1500,日次入力!$A$4:$A$1500,">="&DATE(2026,8,18),日次入力!$A$4:$A$1500,"<="&DATE(2026,8,24),日次入力!$C$4:$C$1500,"Meta介護校")) | G81: =IFERROR(E81/D81,"") | H81: =IFERROR(C81/E81,"") | I81: =IFERROR(C81/D81*1000,"") | J81: =IFERROR(F81/E81,"") | K81: =IFERROR(C81/F81,"") | L81: =IF(COUNTIFS(日次入力!$A$4:$A$1500,">="&DATE(2026,8,18),日次入力!$A$4:$A$1500,"<="&DATE(2026,8,24),日次入力!$C$4:$C$1500,"Meta介護校")=0,"",SUMIFS(日次入力!$H$4:$H$1500,日次入力!$A$4:$A$1500,">="&DATE(2026,8,18),日次入力!$A$4:$A$1500,"<="&DATE(2026,8,24),日次入力!$C$4:$C$1500,"Meta介護校")) | M81: =IF(L81="","",IFERROR(L81/F81,"")) | N81: =IF(COUNTIFS(日次入力!$A$4:$A$1500,">="&DATE(2026,8,18),日次入力!$A$4:$A$1500,"<="&DATE(2026,8,24),日次入力!$C$4:$C$1500,"Meta介護校")=0,"",SUMIFS(日次入力!$I$4:$I$1500,日次入力!$A$4:$A$1500,">="&DATE(2026,8,18),日次入力!$A$4:$A$1500,"<="&DATE(2026,8,24),日次入力!$C$4:$C$1500,"Meta介護校")) | O81: =IF(N81="","",IFERROR(N81/L81,"")) | P81: =IF(N81=0,"",IFERROR(C81/N81,"")) | Q81: =IF(N81=0,"",IFERROR(IF(C81/N81<=用語集!$B$22,"◎ 許容内","✗ 超過"),"—")) -> — | R81: =IFERROR(用語集!$B$22/P81,"")
A82: W21 | B82: 8/25–8/31 | C82: =IF(COUNTIFS(日次入力!$A$4:$A$1500,">="&DATE(2026,8,25),日次入力!$A$4:$A$1500,"<="&DATE(2026,8,31),日次入力!$C$4:$C$1500,"Meta介護校")=0,"",SUMIFS(日次入力!$D$4:$D$1500,日次入力!$A$4:$A$1500,">="&DATE(2026,8,25),日次入力!$A$4:$A$1500,"<="&DATE(2026,8,31),日次入力!$C$4:$C$1500,"Meta介護校")) | D82: =IF(COUNTIFS(日次入力!$A$4:$A$1500,">="&DATE(2026,8,25),日次入力!$A$4:$A$1500,"<="&DATE(2026,8,31),日次入力!$C$4:$C$1500,"Meta介護校")=0,"",SUMIFS(日次入力!$E$4:$E$1500,日次入力!$A$4:$A$1500,">="&DATE(2026,8,25),日次入力!$A$4:$A$1500,"<="&DATE(2026,8,31),日次入力!$C$4:$C$1500,"Meta介護校")) | E82: =IF(COUNTIFS(日次入力!$A$4:$A$1500,">="&DATE(2026,8,25),日次入力!$A$4:$A$1500,"<="&DATE(2026,8,31),日次入力!$C$4:$C$1500,"Meta介護校")=0,"",SUMIFS(日次入力!$F$4:$F$1500,日次入力!$A$4:$A$1500,">="&DATE(2026,8,25),日次入力!$A$4:$A$1500,"<="&DATE(2026,8,31),日次入力!$C$4:$C$1500,"Meta介護校")) | F82: =IF(COUNTIFS(日次入力!$A$4:$A$1500,">="&DATE(2026,8,25),日次入力!$A$4:$A$1500,"<="&DATE(2026,8,31),日次入力!$C$4:$C$1500,"Meta介護校")=0,"",SUMIFS(日次入力!$G$4:$G$1500,日次入力!$A$4:$A$1500,">="&DATE(2026,8,25),日次入力!$A$4:$A$1500,"<="&DATE(2026,8,31),日次入力!$C$4:$C$1500,"Meta介護校")) | G82: =IFERROR(E82/D82,"") | H82: =IFERROR(C82/E82,"") | I82: =IFERROR(C82/D82*1000,"") | J82: =IFERROR(F82/E82,"") | K82: =IFERROR(C82/F82,"") | L82: =IF(COUNTIFS(日次入力!$A$4:$A$1500,">="&DATE(2026,8,25),日次入力!$A$4:$A$1500,"<="&DATE(2026,8,31),日次入力!$C$4:$C$1500,"Meta介護校")=0,"",SUMIFS(日次入力!$H$4:$H$1500,日次入力!$A$4:$A$1500,">="&DATE(2026,8,25),日次入力!$A$4:$A$1500,"<="&DATE(2026,8,31),日次入力!$C$4:$C$1500,"Meta介護校")) | M82: =IF(L82="","",IFERROR(L82/F82,"")) | N82: =IF(COUNTIFS(日次入力!$A$4:$A$1500,">="&DATE(2026,8,25),日次入力!$A$4:$A$1500,"<="&DATE(2026,8,31),日次入力!$C$4:$C$1500,"Meta介護校")=0,"",SUMIFS(日次入力!$I$4:$I$1500,日次入力!$A$4:$A$1500,">="&DATE(2026,8,25),日次入力!$A$4:$A$1500,"<="&DATE(2026,8,31),日次入力!$C$4:$C$1500,"Meta介護校")) | O82: =IF(N82="","",IFERROR(N82/L82,"")) | P82: =IF(N82=0,"",IFERROR(C82/N82,"")) | Q82: =IF(N82=0,"",IFERROR(IF(C82/N82<=用語集!$B$22,"◎ 許容内","✗ 超過"),"—")) -> — | R82: =IFERROR(用語集!$B$22/P82,"")
A83: W22 | B83: 9/1–9/7 | C83: =IF(COUNTIFS(日次入力!$A$4:$A$1500,">="&DATE(2026,9,1),日次入力!$A$4:$A$1500,"<="&DATE(2026,9,7),日次入力!$C$4:$C$1500,"Meta介護校")=0,"",SUMIFS(日次入力!$D$4:$D$1500,日次入力!$A$4:$A$1500,">="&DATE(2026,9,1),日次入力!$A$4:$A$1500,"<="&DATE(2026,9,7),日次入力!$C$4:$C$1500,"Meta介護校")) | D83: =IF(COUNTIFS(日次入力!$A$4:$A$1500,">="&DATE(2026,9,1),日次入力!$A$4:$A$1500,"<="&DATE(2026,9,7),日次入力!$C$4:$C$1500,"Meta介護校")=0,"",SUMIFS(日次入力!$E$4:$E$1500,日次入力!$A$4:$A$1500,">="&DATE(2026,9,1),日次入力!$A$4:$A$1500,"<="&DATE(2026,9,7),日次入力!$C$4:$C$1500,"Meta介護校")) | E83: =IF(COUNTIFS(日次入力!$A$4:$A$1500,">="&DATE(2026,9,1),日次入力!$A$4:$A$1500,"<="&DATE(2026,9,7),日次入力!$C$4:$C$1500,"Meta介護校")=0,"",SUMIFS(日次入力!$F$4:$F$1500,日次入力!$A$4:$A$1500,">="&DATE(2026,9,1),日次入力!$A$4:$A$1500,"<="&DATE(2026,9,7),日次入力!$C$4:$C$1500,"Meta介護校")) | F83: =IF(COUNTIFS(日次入力!$A$4:$A$1500,">="&DATE(2026,9,1),日次入力!$A$4:$A$1500,"<="&DATE(2026,9,7),日次入力!$C$4:$C$1500,"Meta介護校")=0,"",SUMIFS(日次入力!$G$4:$G$1500,日次入力!$A$4:$A$1500,">="&DATE(2026,9,1),日次入力!$A$4:$A$1500,"<="&DATE(2026,9,7),日次入力!$C$4:$C$1500,"Meta介護校")) | G83: =IFERROR(E83/D83,"") | H83: =IFERROR(C83/E83,"") | I83: =IFERROR(C83/D83*1000,"") | J83: =IFERROR(F83/E83,"") | K83: =IFERROR(C83/F83,"") | L83: =IF(COUNTIFS(日次入力!$A$4:$A$1500,">="&DATE(2026,9,1),日次入力!$A$4:$A$1500,"<="&DATE(2026,9,7),日次入力!$C$4:$C$1500,"Meta介護校")=0,"",SUMIFS(日次入力!$H$4:$H$1500,日次入力!$A$4:$A$1500,">="&DATE(2026,9,1),日次入力!$A$4:$A$1500,"<="&DATE(2026,9,7),日次入力!$C$4:$C$1500,"Meta介護校")) | M83: =IF(L83="","",IFERROR(L83/F83,"")) | N83: =IF(COUNTIFS(日次入力!$A$4:$A$1500,">="&DATE(2026,9,1),日次入力!$A$4:$A$1500,"<="&DATE(2026,9,7),日次入力!$C$4:$C$1500,"Meta介護校")=0,"",SUMIFS(日次入力!$I$4:$I$1500,日次入力!$A$4:$A$1500,">="&DATE(2026,9,1),日次入力!$A$4:$A$1500,"<="&DATE(2026,9,7),日次入力!$C$4:$C$1500,"Meta介護校")) | O83: =IF(N83="","",IFERROR(N83/L83,"")) | P83: =IF(N83=0,"",IFERROR(C83/N83,"")) | Q83: =IF(N83=0,"",IFERROR(IF(C83/N83<=用語集!$B$22,"◎ 許容内","✗ 超過"),"—")) -> — | R83: =IFERROR(用語集!$B$22/P83,"")
A84: W23 | B84: 9/8–9/14 | C84: =IF(COUNTIFS(日次入力!$A$4:$A$1500,">="&DATE(2026,9,8),日次入力!$A$4:$A$1500,"<="&DATE(2026,9,14),日次入力!$C$4:$C$1500,"Meta介護校")=0,"",SUMIFS(日次入力!$D$4:$D$1500,日次入力!$A$4:$A$1500,">="&DATE(2026,9,8),日次入力!$A$4:$A$1500,"<="&DATE(2026,9,14),日次入力!$C$4:$C$1500,"Meta介護校")) | D84: =IF(COUNTIFS(日次入力!$A$4:$A$1500,">="&DATE(2026,9,8),日次入力!$A$4:$A$1500,"<="&DATE(2026,9,14),日次入力!$C$4:$C$1500,"Meta介護校")=0,"",SUMIFS(日次入力!$E$4:$E$1500,日次入力!$A$4:$A$1500,">="&DATE(2026,9,8),日次入力!$A$4:$A$1500,"<="&DATE(2026,9,14),日次入力!$C$4:$C$1500,"Meta介護校")) | E84: =IF(COUNTIFS(日次入力!$A$4:$A$1500,">="&DATE(2026,9,8),日次入力!$A$4:$A$1500,"<="&DATE(2026,9,14),日次入力!$C$4:$C$1500,"Meta介護校")=0,"",SUMIFS(日次入力!$F$4:$F$1500,日次入力!$A$4:$A$1500,">="&DATE(2026,9,8),日次入力!$A$4:$A$1500,"<="&DATE(2026,9,14),日次入力!$C$4:$C$1500,"Meta介護校")) | F84: =IF(COUNTIFS(日次入力!$A$4:$A$1500,">="&DATE(2026,9,8),日次入力!$A$4:$A$1500,"<="&DATE(2026,9,14),日次入力!$C$4:$C$1500,"Meta介護校")=0,"",SUMIFS(日次入力!$G$4:$G$1500,日次入力!$A$4:$A$1500,">="&DATE(2026,9,8),日次入力!$A$4:$A$1500,"<="&DATE(2026,9,14),日次入力!$C$4:$C$1500,"Meta介護校")) | G84: =IFERROR(E84/D84,"") | H84: =IFERROR(C84/E84,"") | I84: =IFERROR(C84/D84*1000,"") | J84: =IFERROR(F84/E84,"") | K84: =IFERROR(C84/F84,"") | L84: =IF(COUNTIFS(日次入力!$A$4:$A$1500,">="&DATE(2026,9,8),日次入力!$A$4:$A$1500,"<="&DATE(2026,9,14),日次入力!$C$4:$C$1500,"Meta介護校")=0,"",SUMIFS(日次入力!$H$4:$H$1500,日次入力!$A$4:$A$1500,">="&DATE(2026,9,8),日次入力!$A$4:$A$1500,"<="&DATE(2026,9,14),日次入力!$C$4:$C$1500,"Meta介護校")) | M84: =IF(L84="","",IFERROR(L84/F84,"")) | N84: =IF(COUNTIFS(日次入力!$A$4:$A$1500,">="&DATE(2026,9,8),日次入力!$A$4:$A$1500,"<="&DATE(2026,9,14),日次入力!$C$4:$C$1500,"Meta介護校")=0,"",SUMIFS(日次入力!$I$4:$I$1500,日次入力!$A$4:$A$1500,">="&DATE(2026,9,8),日次入力!$A$4:$A$1500,"<="&DATE(2026,9,14),日次入力!$C$4:$C$1500,"Meta介護校")) | O84: =IF(N84="","",IFERROR(N84/L84,"")) | P84: =IF(N84=0,"",IFERROR(C84/N84,"")) | Q84: =IF(N84=0,"",IFERROR(IF(C84/N84<=用語集!$B$22,"◎ 許容内","✗ 超過"),"—")) -> — | R84: =IFERROR(用語集!$B$22/P84,"")
A85: W24 | B85: 9/15–9/21 | C85: =IF(COUNTIFS(日次入力!$A$4:$A$1500,">="&DATE(2026,9,15),日次入力!$A$4:$A$1500,"<="&DATE(2026,9,21),日次入力!$C$4:$C$1500,"Meta介護校")=0,"",SUMIFS(日次入力!$D$4:$D$1500,日次入力!$A$4:$A$1500,">="&DATE(2026,9,15),日次入力!$A$4:$A$1500,"<="&DATE(2026,9,21),日次入力!$C$4:$C$1500,"Meta介護校")) | D85: =IF(COUNTIFS(日次入力!$A$4:$A$1500,">="&DATE(2026,9,15),日次入力!$A$4:$A$1500,"<="&DATE(2026,9,21),日次入力!$C$4:$C$1500,"Meta介護校")=0,"",SUMIFS(日次入力!$E$4:$E$1500,日次入力!$A$4:$A$1500,">="&DATE(2026,9,15),日次入力!$A$4:$A$1500,"<="&DATE(2026,9,21),日次入力!$C$4:$C$1500,"Meta介護校")) | E85: =IF(COUNTIFS(日次入力!$A$4:$A$1500,">="&DATE(2026,9,15),日次入力!$A$4:$A$1500,"<="&DATE(2026,9,21),日次入力!$C$4:$C$1500,"Meta介護校")=0,"",SUMIFS(日次入力!$F$4:$F$1500,日次入力!$A$4:$A$1500,">="&DATE(2026,9,15),日次入力!$A$4:$A$1500,"<="&DATE(2026,9,21),日次入力!$C$4:$C$1500,"Meta介護校")) | F85: =IF(COUNTIFS(日次入力!$A$4:$A$1500,">="&DATE(2026,9,15),日次入力!$A$4:$A$1500,"<="&DATE(2026,9,21),日次入力!$C$4:$C$1500,"Meta介護校")=0,"",SUMIFS(日次入力!$G$4:$G$1500,日次入力!$A$4:$A$1500,">="&DATE(2026,9,15),日次入力!$A$4:$A$1500,"<="&DATE(2026,9,21),日次入力!$C$4:$C$1500,"Meta介護校")) | G85: =IFERROR(E85/D85,"") | H85: =IFERROR(C85/E85,"") | I85: =IFERROR(C85/D85*1000,"") | J85: =IFERROR(F85/E85,"") | K85: =IFERROR(C85/F85,"") | L85: =IF(COUNTIFS(日次入力!$A$4:$A$1500,">="&DATE(2026,9,15),日次入力!$A$4:$A$1500,"<="&DATE(2026,9,21),日次入力!$C$4:$C$1500,"Meta介護校")=0,"",SUMIFS(日次入力!$H$4:$H$1500,日次入力!$A$4:$A$1500,">="&DATE(2026,9,15),日次入力!$A$4:$A$1500,"<="&DATE(2026,9,21),日次入力!$C$4:$C$1500,"Meta介護校")) | M85: =IF(L85="","",IFERROR(L85/F85,"")) | N85: =IF(COUNTIFS(日次入力!$A$4:$A$1500,">="&DATE(2026,9,15),日次入力!$A$4:$A$1500,"<="&DATE(2026,9,21),日次入力!$C$4:$C$1500,"Meta介護校")=0,"",SUMIFS(日次入力!$I$4:$I$1500,日次入力!$A$4:$A$1500,">="&DATE(2026,9,15),日次入力!$A$4:$A$1500,"<="&DATE(2026,9,21),日次入力!$C$4:$C$1500,"Meta介護校")) | O85: =IF(N85="","",IFERROR(N85/L85,"")) | P85: =IF(N85=0,"",IFERROR(C85/N85,"")) | Q85: =IF(N85=0,"",IFERROR(IF(C85/N85<=用語集!$B$22,"◎ 許容内","✗ 超過"),"—")) -> — | R85: =IFERROR(用語集!$B$22/P85,"")
A86: W25 | B86: 9/22–9/28 | C86: =IF(COUNTIFS(日次入力!$A$4:$A$1500,">="&DATE(2026,9,22),日次入力!$A$4:$A$1500,"<="&DATE(2026,9,28),日次入力!$C$4:$C$1500,"Meta介護校")=0,"",SUMIFS(日次入力!$D$4:$D$1500,日次入力!$A$4:$A$1500,">="&DATE(2026,9,22),日次入力!$A$4:$A$1500,"<="&DATE(2026,9,28),日次入力!$C$4:$C$1500,"Meta介護校")) | D86: =IF(COUNTIFS(日次入力!$A$4:$A$1500,">="&DATE(2026,9,22),日次入力!$A$4:$A$1500,"<="&DATE(2026,9,28),日次入力!$C$4:$C$1500,"Meta介護校")=0,"",SUMIFS(日次入力!$E$4:$E$1500,日次入力!$A$4:$A$1500,">="&DATE(2026,9,22),日次入力!$A$4:$A$1500,"<="&DATE(2026,9,28),日次入力!$C$4:$C$1500,"Meta介護校")) | E86: =IF(COUNTIFS(日次入力!$A$4:$A$1500,">="&DATE(2026,9,22),日次入力!$A$4:$A$1500,"<="&DATE(2026,9,28),日次入力!$C$4:$C$1500,"Meta介護校")=0,"",SUMIFS(日次入力!$F$4:$F$1500,日次入力!$A$4:$A$1500,">="&DATE(2026,9,22),日次入力!$A$4:$A$1500,"<="&DATE(2026,9,28),日次入力!$C$4:$C$1500,"Meta介護校")) | F86: =IF(COUNTIFS(日次入力!$A$4:$A$1500,">="&DATE(2026,9,22),日次入力!$A$4:$A$1500,"<="&DATE(2026,9,28),日次入力!$C$4:$C$1500,"Meta介護校")=0,"",SUMIFS(日次入力!$G$4:$G$1500,日次入力!$A$4:$A$1500,">="&DATE(2026,9,22),日次入力!$A$4:$A$1500,"<="&DATE(2026,9,28),日次入力!$C$4:$C$1500,"Meta介護校")) | G86: =IFERROR(E86/D86,"") | H86: =IFERROR(C86/E86,"") | I86: =IFERROR(C86/D86*1000,"") | J86: =IFERROR(F86/E86,"") | K86: =IFERROR(C86/F86,"") | L86: =IF(COUNTIFS(日次入力!$A$4:$A$1500,">="&DATE(2026,9,22),日次入力!$A$4:$A$1500,"<="&DATE(2026,9,28),日次入力!$C$4:$C$1500,"Meta介護校")=0,"",SUMIFS(日次入力!$H$4:$H$1500,日次入力!$A$4:$A$1500,">="&DATE(2026,9,22),日次入力!$A$4:$A$1500,"<="&DATE(2026,9,28),日次入力!$C$4:$C$1500,"Meta介護校")) | M86: =IF(L86="","",IFERROR(L86/F86,"")) | N86: =IF(COUNTIFS(日次入力!$A$4:$A$1500,">="&DATE(2026,9,22),日次入力!$A$4:$A$1500,"<="&DATE(2026,9,28),日次入力!$C$4:$C$1500,"Meta介護校")=0,"",SUMIFS(日次入力!$I$4:$I$1500,日次入力!$A$4:$A$1500,">="&DATE(2026,9,22),日次入力!$A$4:$A$1500,"<="&DATE(2026,9,28),日次入力!$C$4:$C$1500,"Meta介護校")) | O86: =IF(N86="","",IFERROR(N86/L86,"")) | P86: =IF(N86=0,"",IFERROR(C86/N86,"")) | Q86: =IF(N86=0,"",IFERROR(IF(C86/N86<=用語集!$B$22,"◎ 許容内","✗ 超過"),"—")) -> — | R86: =IFERROR(用語集!$B$22/P86,"")
A87: W26 | B87: 9/29–10/5 | C87: =IF(COUNTIFS(日次入力!$A$4:$A$1500,">="&DATE(2026,9,29),日次入力!$A$4:$A$1500,"<="&DATE(2026,10,5),日次入力!$C$4:$C$1500,"Meta介護校")=0,"",SUMIFS(日次入力!$D$4:$D$1500,日次入力!$A$4:$A$1500,">="&DATE(2026,9,29),日次入力!$A$4:$A$1500,"<="&DATE(2026,10,5),日次入力!$C$4:$C$1500,"Meta介護校")) | D87: =IF(COUNTIFS(日次入力!$A$4:$A$1500,">="&DATE(2026,9,29),日次入力!$A$4:$A$1500,"<="&DATE(2026,10,5),日次入力!$C$4:$C$1500,"Meta介護校")=0,"",SUMIFS(日次入力!$E$4:$E$1500,日次入力!$A$4:$A$1500,">="&DATE(2026,9,29),日次入力!$A$4:$A$1500,"<="&DATE(2026,10,5),日次入力!$C$4:$C$1500,"Meta介護校")) | E87: =IF(COUNTIFS(日次入力!$A$4:$A$1500,">="&DATE(2026,9,29),日次入力!$A$4:$A$1500,"<="&DATE(2026,10,5),日次入力!$C$4:$C$1500,"Meta介護校")=0,"",SUMIFS(日次入力!$F$4:$F$1500,日次入力!$A$4:$A$1500,">="&DATE(2026,9,29),日次入力!$A$4:$A$1500,"<="&DATE(2026,10,5),日次入力!$C$4:$C$1500,"Meta介護校")) | F87: =IF(COUNTIFS(日次入力!$A$4:$A$1500,">="&DATE(2026,9,29),日次入力!$A$4:$A$1500,"<="&DATE(2026,10,5),日次入力!$C$4:$C$1500,"Meta介護校")=0,"",SUMIFS(日次入力!$G$4:$G$1500,日次入力!$A$4:$A$1500,">="&DATE(2026,9,29),日次入力!$A$4:$A$1500,"<="&DATE(2026,10,5),日次入力!$C$4:$C$1500,"Meta介護校")) | G87: =IFERROR(E87/D87,"") | H87: =IFERROR(C87/E87,"") | I87: =IFERROR(C87/D87*1000,"") | J87: =IFERROR(F87/E87,"") | K87: =IFERROR(C87/F87,"") | L87: =IF(COUNTIFS(日次入力!$A$4:$A$1500,">="&DATE(2026,9,29),日次入力!$A$4:$A$1500,"<="&DATE(2026,10,5),日次入力!$C$4:$C$1500,"Meta介護校")=0,"",SUMIFS(日次入力!$H$4:$H$1500,日次入力!$A$4:$A$1500,">="&DATE(2026,9,29),日次入力!$A$4:$A$1500,"<="&DATE(2026,10,5),日次入力!$C$4:$C$1500,"Meta介護校")) | M87: =IF(L87="","",IFERROR(L87/F87,"")) | N87: =IF(COUNTIFS(日次入力!$A$4:$A$1500,">="&DATE(2026,9,29),日次入力!$A$4:$A$1500,"<="&DATE(2026,10,5),日次入力!$C$4:$C$1500,"Meta介護校")=0,"",SUMIFS(日次入力!$I$4:$I$1500,日次入力!$A$4:$A$1500,">="&DATE(2026,9,29),日次入力!$A$4:$A$1500,"<="&DATE(2026,10,5),日次入力!$C$4:$C$1500,"Meta介護校")) | O87: =IF(N87="","",IFERROR(N87/L87,"")) | P87: =IF(N87=0,"",IFERROR(C87/N87,"")) | Q87: =IF(N87=0,"",IFERROR(IF(C87/N87<=用語集!$B$22,"◎ 許容内","✗ 超過"),"—")) -> — | R87: =IFERROR(用語集!$B$22/P87,"")
A88: W27 | B88: 10/6–10/12 | C88: =IF(COUNTIFS(日次入力!$A$4:$A$1500,">="&DATE(2026,10,6),日次入力!$A$4:$A$1500,"<="&DATE(2026,10,12),日次入力!$C$4:$C$1500,"Meta介護校")=0,"",SUMIFS(日次入力!$D$4:$D$1500,日次入力!$A$4:$A$1500,">="&DATE(2026,10,6),日次入力!$A$4:$A$1500,"<="&DATE(2026,10,12),日次入力!$C$4:$C$1500,"Meta介護校")) | D88: =IF(COUNTIFS(日次入力!$A$4:$A$1500,">="&DATE(2026,10,6),日次入力!$A$4:$A$1500,"<="&DATE(2026,10,12),日次入力!$C$4:$C$1500,"Meta介護校")=0,"",SUMIFS(日次入力!$E$4:$E$1500,日次入力!$A$4:$A$1500,">="&DATE(2026,10,6),日次入力!$A$4:$A$1500,"<="&DATE(2026,10,12),日次入力!$C$4:$C$1500,"Meta介護校")) | E88: =IF(COUNTIFS(日次入力!$A$4:$A$1500,">="&DATE(2026,10,6),日次入力!$A$4:$A$1500,"<="&DATE(2026,10,12),日次入力!$C$4:$C$1500,"Meta介護校")=0,"",SUMIFS(日次入力!$F$4:$F$1500,日次入力!$A$4:$A$1500,">="&DATE(2026,10,6),日次入力!$A$4:$A$1500,"<="&DATE(2026,10,12),日次入力!$C$4:$C$1500,"Meta介護校")) | F88: =IF(COUNTIFS(日次入力!$A$4:$A$1500,">="&DATE(2026,10,6),日次入力!$A$4:$A$1500,"<="&DATE(2026,10,12),日次入力!$C$4:$C$1500,"Meta介護校")=0,"",SUMIFS(日次入力!$G$4:$G$1500,日次入力!$A$4:$A$1500,">="&DATE(2026,10,6),日次入力!$A$4:$A$1500,"<="&DATE(2026,10,12),日次入力!$C$4:$C$1500,"Meta介護校")) | G88: =IFERROR(E88/D88,"") | H88: =IFERROR(C88/E88,"") | I88: =IFERROR(C88/D88*1000,"") | J88: =IFERROR(F88/E88,"") | K88: =IFERROR(C88/F88,"") | L88: =IF(COUNTIFS(日次入力!$A$4:$A$1500,">="&DATE(2026,10,6),日次入力!$A$4:$A$1500,"<="&DATE(2026,10,12),日次入力!$C$4:$C$1500,"Meta介護校")=0,"",SUMIFS(日次入力!$H$4:$H$1500,日次入力!$A$4:$A$1500,">="&DATE(2026,10,6),日次入力!$A$4:$A$1500,"<="&DATE(2026,10,12),日次入力!$C$4:$C$1500,"Meta介護校")) | M88: =IF(L88="","",IFERROR(L88/F88,"")) | N88: =IF(COUNTIFS(日次入力!$A$4:$A$1500,">="&DATE(2026,10,6),日次入力!$A$4:$A$1500,"<="&DATE(2026,10,12),日次入力!$C$4:$C$1500,"Meta介護校")=0,"",SUMIFS(日次入力!$I$4:$I$1500,日次入力!$A$4:$A$1500,">="&DATE(2026,10,6),日次入力!$A$4:$A$1500,"<="&DATE(2026,10,12),日次入力!$C$4:$C$1500,"Meta介護校")) | O88: =IF(N88="","",IFERROR(N88/L88,"")) | P88: =IF(N88=0,"",IFERROR(C88/N88,"")) | Q88: =IF(N88=0,"",IFERROR(IF(C88/N88<=用語集!$B$22,"◎ 許容内","✗ 超過"),"—")) -> — | R88: =IFERROR(用語集!$B$22/P88,"")
A89: W28 | B89: 10/13–10/19 | C89: =IF(COUNTIFS(日次入力!$A$4:$A$1500,">="&DATE(2026,10,13),日次入力!$A$4:$A$1500,"<="&DATE(2026,10,19),日次入力!$C$4:$C$1500,"Meta介護校")=0,"",SUMIFS(日次入力!$D$4:$D$1500,日次入力!$A$4:$A$1500,">="&DATE(2026,10,13),日次入力!$A$4:$A$1500,"<="&DATE(2026,10,19),日次入力!$C$4:$C$1500,"Meta介護校")) | D89: =IF(COUNTIFS(日次入力!$A$4:$A$1500,">="&DATE(2026,10,13),日次入力!$A$4:$A$1500,"<="&DATE(2026,10,19),日次入力!$C$4:$C$1500,"Meta介護校")=0,"",SUMIFS(日次入力!$E$4:$E$1500,日次入力!$A$4:$A$1500,">="&DATE(2026,10,13),日次入力!$A$4:$A$1500,"<="&DATE(2026,10,19),日次入力!$C$4:$C$1500,"Meta介護校")) | E89: =IF(COUNTIFS(日次入力!$A$4:$A$1500,">="&DATE(2026,10,13),日次入力!$A$4:$A$1500,"<="&DATE(2026,10,19),日次入力!$C$4:$C$1500,"Meta介護校")=0,"",SUMIFS(日次入力!$F$4:$F$1500,日次入力!$A$4:$A$1500,">="&DATE(2026,10,13),日次入力!$A$4:$A$1500,"<="&DATE(2026,10,19),日次入力!$C$4:$C$1500,"Meta介護校")) | F89: =IF(COUNTIFS(日次入力!$A$4:$A$1500,">="&DATE(2026,10,13),日次入力!$A$4:$A$1500,"<="&DATE(2026,10,19),日次入力!$C$4:$C$1500,"Meta介護校")=0,"",SUMIFS(日次入力!$G$4:$G$1500,日次入力!$A$4:$A$1500,">="&DATE(2026,10,13),日次入力!$A$4:$A$1500,"<="&DATE(2026,10,19),日次入力!$C$4:$C$1500,"Meta介護校")) | G89: =IFERROR(E89/D89,"") | H89: =IFERROR(C89/E89,"") | I89: =IFERROR(C89/D89*1000,"") | J89: =IFERROR(F89/E89,"") | K89: =IFERROR(C89/F89,"") | L89: =IF(COUNTIFS(日次入力!$A$4:$A$1500,">="&DATE(2026,10,13),日次入力!$A$4:$A$1500,"<="&DATE(2026,10,19),日次入力!$C$4:$C$1500,"Meta介護校")=0,"",SUMIFS(日次入力!$H$4:$H$1500,日次入力!$A$4:$A$1500,">="&DATE(2026,10,13),日次入力!$A$4:$A$1500,"<="&DATE(2026,10,19),日次入力!$C$4:$C$1500,"Meta介護校")) | M89: =IF(L89="","",IFERROR(L89/F89,"")) | N89: =IF(COUNTIFS(日次入力!$A$4:$A$1500,">="&DATE(2026,10,13),日次入力!$A$4:$A$1500,"<="&DATE(2026,10,19),日次入力!$C$4:$C$1500,"Meta介護校")=0,"",SUMIFS(日次入力!$I$4:$I$1500,日次入力!$A$4:$A$1500,">="&DATE(2026,10,13),日次入力!$A$4:$A$1500,"<="&DATE(2026,10,19),日次入力!$C$4:$C$1500,"Meta介護校")) | O89: =IF(N89="","",IFERROR(N89/L89,"")) | P89: =IF(N89=0,"",IFERROR(C89/N89,"")) | Q89: =IF(N89=0,"",IFERROR(IF(C89/N89<=用語集!$B$22,"◎ 許容内","✗ 超過"),"—")) -> — | R89: =IFERROR(用語集!$B$22/P89,"")
A90: W29 | B90: 10/20–10/26 | C90: =IF(COUNTIFS(日次入力!$A$4:$A$1500,">="&DATE(2026,10,20),日次入力!$A$4:$A$1500,"<="&DATE(2026,10,26),日次入力!$C$4:$C$1500,"Meta介護校")=0,"",SUMIFS(日次入力!$D$4:$D$1500,日次入力!$A$4:$A$1500,">="&DATE(2026,10,20),日次入力!$A$4:$A$1500,"<="&DATE(2026,10,26),日次入力!$C$4:$C$1500,"Meta介護校")) | D90: =IF(COUNTIFS(日次入力!$A$4:$A$1500,">="&DATE(2026,10,20),日次入力!$A$4:$A$1500,"<="&DATE(2026,10,26),日次入力!$C$4:$C$1500,"Meta介護校")=0,"",SUMIFS(日次入力!$E$4:$E$1500,日次入力!$A$4:$A$1500,">="&DATE(2026,10,20),日次入力!$A$4:$A$1500,"<="&DATE(2026,10,26),日次入力!$C$4:$C$1500,"Meta介護校")) | E90: =IF(COUNTIFS(日次入力!$A$4:$A$1500,">="&DATE(2026,10,20),日次入力!$A$4:$A$1500,"<="&DATE(2026,10,26),日次入力!$C$4:$C$1500,"Meta介護校")=0,"",SUMIFS(日次入力!$F$4:$F$1500,日次入力!$A$4:$A$1500,">="&DATE(2026,10,20),日次入力!$A$4:$A$1500,"<="&DATE(2026,10,26),日次入力!$C$4:$C$1500,"Meta介護校")) | F90: =IF(COUNTIFS(日次入力!$A$4:$A$1500,">="&DATE(2026,10,20),日次入力!$A$4:$A$1500,"<="&DATE(2026,10,26),日次入力!$C$4:$C$1500,"Meta介護校")=0,"",SUMIFS(日次入力!$G$4:$G$1500,日次入力!$A$4:$A$1500,">="&DATE(2026,10,20),日次入力!$A$4:$A$1500,"<="&DATE(2026,10,26),日次入力!$C$4:$C$1500,"Meta介護校")) | G90: =IFERROR(E90/D90,"") | H90: =IFERROR(C90/E90,"") | I90: =IFERROR(C90/D90*1000,"") | J90: =IFERROR(F90/E90,"") | K90: =IFERROR(C90/F90,"") | L90: =IF(COUNTIFS(日次入力!$A$4:$A$1500,">="&DATE(2026,10,20),日次入力!$A$4:$A$1500,"<="&DATE(2026,10,26),日次入力!$C$4:$C$1500,"Meta介護校")=0,"",SUMIFS(日次入力!$H$4:$H$1500,日次入力!$A$4:$A$1500,">="&DATE(2026,10,20),日次入力!$A$4:$A$1500,"<="&DATE(2026,10,26),日次入力!$C$4:$C$1500,"Meta介護校")) | M90: =IF(L90="","",IFERROR(L90/F90,"")) | N90: =IF(COUNTIFS(日次入力!$A$4:$A$1500,">="&DATE(2026,10,20),日次入力!$A$4:$A$1500,"<="&DATE(2026,10,26),日次入力!$C$4:$C$1500,"Meta介護校")=0,"",SUMIFS(日次入力!$I$4:$I$1500,日次入力!$A$4:$A$1500,">="&DATE(2026,10,20),日次入力!$A$4:$A$1500,"<="&DATE(2026,10,26),日次入力!$C$4:$C$1500,"Meta介護校")) | O90: =IF(N90="","",IFERROR(N90/L90,"")) | P90: =IF(N90=0,"",IFERROR(C90/N90,"")) | Q90: =IF(N90=0,"",IFERROR(IF(C90/N90<=用語集!$B$22,"◎ 許容内","✗ 超過"),"—")) -> — | R90: =IFERROR(用語集!$B$22/P90,"")
A91: W30 | B91: 10/27–11/2 | C91: =IF(COUNTIFS(日次入力!$A$4:$A$1500,">="&DATE(2026,10,27),日次入力!$A$4:$A$1500,"<="&DATE(2026,11,2),日次入力!$C$4:$C$1500,"Meta介護校")=0,"",SUMIFS(日次入力!$D$4:$D$1500,日次入力!$A$4:$A$1500,">="&DATE(2026,10,27),日次入力!$A$4:$A$1500,"<="&DATE(2026,11,2),日次入力!$C$4:$C$1500,"Meta介護校")) | D91: =IF(COUNTIFS(日次入力!$A$4:$A$1500,">="&DATE(2026,10,27),日次入力!$A$4:$A$1500,"<="&DATE(2026,11,2),日次入力!$C$4:$C$1500,"Meta介護校")=0,"",SUMIFS(日次入力!$E$4:$E$1500,日次入力!$A$4:$A$1500,">="&DATE(2026,10,27),日次入力!$A$4:$A$1500,"<="&DATE(2026,11,2),日次入力!$C$4:$C$1500,"Meta介護校")) | E91: =IF(COUNTIFS(日次入力!$A$4:$A$1500,">="&DATE(2026,10,27),日次入力!$A$4:$A$1500,"<="&DATE(2026,11,2),日次入力!$C$4:$C$1500,"Meta介護校")=0,"",SUMIFS(日次入力!$F$4:$F$1500,日次入力!$A$4:$A$1500,">="&DATE(2026,10,27),日次入力!$A$4:$A$1500,"<="&DATE(2026,11,2),日次入力!$C$4:$C$1500,"Meta介護校")) | F91: =IF(COUNTIFS(日次入力!$A$4:$A$1500,">="&DATE(2026,10,27),日次入力!$A$4:$A$1500,"<="&DATE(2026,11,2),日次入力!$C$4:$C$1500,"Meta介護校")=0,"",SUMIFS(日次入力!$G$4:$G$1500,日次入力!$A$4:$A$1500,">="&DATE(2026,10,27),日次入力!$A$4:$A$1500,"<="&DATE(2026,11,2),日次入力!$C$4:$C$1500,"Meta介護校")) | G91: =IFERROR(E91/D91,"") | H91: =IFERROR(C91/E91,"") | I91: =IFERROR(C91/D91*1000,"") | J91: =IFERROR(F91/E91,"") | K91: =IFERROR(C91/F91,"") | L91: =IF(COUNTIFS(日次入力!$A$4:$A$1500,">="&DATE(2026,10,27),日次入力!$A$4:$A$1500,"<="&DATE(2026,11,2),日次入力!$C$4:$C$1500,"Meta介護校")=0,"",SUMIFS(日次入力!$H$4:$H$1500,日次入力!$A$4:$A$1500,">="&DATE(2026,10,27),日次入力!$A$4:$A$1500,"<="&DATE(2026,11,2),日次入力!$C$4:$C$1500,"Meta介護校")) | M91: =IF(L91="","",IFERROR(L91/F91,"")) | N91: =IF(COUNTIFS(日次入力!$A$4:$A$1500,">="&DATE(2026,10,27),日次入力!$A$4:$A$1500,"<="&DATE(2026,11,2),日次入力!$C$4:$C$1500,"Meta介護校")=0,"",SUMIFS(日次入力!$I$4:$I$1500,日次入力!$A$4:$A$1500,">="&DATE(2026,10,27),日次入力!$A$4:$A$1500,"<="&DATE(2026,11,2),日次入力!$C$4:$C$1500,"Meta介護校")) | O91: =IF(N91="","",IFERROR(N91/L91,"")) | P91: =IF(N91=0,"",IFERROR(C91/N91,"")) | Q91: =IF(N91=0,"",IFERROR(IF(C91/N91<=用語集!$B$22,"◎ 許容内","✗ 超過"),"—")) -> — | R91: =IFERROR(用語集!$B$22/P91,"")
A92: W31 | B92: 11/3–11/9 | C92: =IF(COUNTIFS(日次入力!$A$4:$A$1500,">="&DATE(2026,11,3),日次入力!$A$4:$A$1500,"<="&DATE(2026,11,9),日次入力!$C$4:$C$1500,"Meta介護校")=0,"",SUMIFS(日次入力!$D$4:$D$1500,日次入力!$A$4:$A$1500,">="&DATE(2026,11,3),日次入力!$A$4:$A$1500,"<="&DATE(2026,11,9),日次入力!$C$4:$C$1500,"Meta介護校")) | D92: =IF(COUNTIFS(日次入力!$A$4:$A$1500,">="&DATE(2026,11,3),日次入力!$A$4:$A$1500,"<="&DATE(2026,11,9),日次入力!$C$4:$C$1500,"Meta介護校")=0,"",SUMIFS(日次入力!$E$4:$E$1500,日次入力!$A$4:$A$1500,">="&DATE(2026,11,3),日次入力!$A$4:$A$1500,"<="&DATE(2026,11,9),日次入力!$C$4:$C$1500,"Meta介護校")) | E92: =IF(COUNTIFS(日次入力!$A$4:$A$1500,">="&DATE(2026,11,3),日次入力!$A$4:$A$1500,"<="&DATE(2026,11,9),日次入力!$C$4:$C$1500,"Meta介護校")=0,"",SUMIFS(日次入力!$F$4:$F$1500,日次入力!$A$4:$A$1500,">="&DATE(2026,11,3),日次入力!$A$4:$A$1500,"<="&DATE(2026,11,9),日次入力!$C$4:$C$1500,"Meta介護校")) | F92: =IF(COUNTIFS(日次入力!$A$4:$A$1500,">="&DATE(2026,11,3),日次入力!$A$4:$A$1500,"<="&DATE(2026,11,9),日次入力!$C$4:$C$1500,"Meta介護校")=0,"",SUMIFS(日次入力!$G$4:$G$1500,日次入力!$A$4:$A$1500,">="&DATE(2026,11,3),日次入力!$A$4:$A$1500,"<="&DATE(2026,11,9),日次入力!$C$4:$C$1500,"Meta介護校")) | G92: =IFERROR(E92/D92,"") | H92: =IFERROR(C92/E92,"") | I92: =IFERROR(C92/D92*1000,"") | J92: =IFERROR(F92/E92,"") | K92: =IFERROR(C92/F92,"") | L92: =IF(COUNTIFS(日次入力!$A$4:$A$1500,">="&DATE(2026,11,3),日次入力!$A$4:$A$1500,"<="&DATE(2026,11,9),日次入力!$C$4:$C$1500,"Meta介護校")=0,"",SUMIFS(日次入力!$H$4:$H$1500,日次入力!$A$4:$A$1500,">="&DATE(2026,11,3),日次入力!$A$4:$A$1500,"<="&DATE(2026,11,9),日次入力!$C$4:$C$1500,"Meta介護校")) | M92: =IF(L92="","",IFERROR(L92/F92,"")) | N92: =IF(COUNTIFS(日次入力!$A$4:$A$1500,">="&DATE(2026,11,3),日次入力!$A$4:$A$1500,"<="&DATE(2026,11,9),日次入力!$C$4:$C$1500,"Meta介護校")=0,"",SUMIFS(日次入力!$I$4:$I$1500,日次入力!$A$4:$A$1500,">="&DATE(2026,11,3),日次入力!$A$4:$A$1500,"<="&DATE(2026,11,9),日次入力!$C$4:$C$1500,"Meta介護校")) | O92: =IF(N92="","",IFERROR(N92/L92,"")) | P92: =IF(N92=0,"",IFERROR(C92/N92,"")) | Q92: =IF(N92=0,"",IFERROR(IF(C92/N92<=用語集!$B$22,"◎ 許容内","✗ 超過"),"—")) -> — | R92: =IFERROR(用語集!$B$22/P92,"")
A93: W32 | B93: 11/10–11/16 | C93: =IF(COUNTIFS(日次入力!$A$4:$A$1500,">="&DATE(2026,11,10),日次入力!$A$4:$A$1500,"<="&DATE(2026,11,16),日次入力!$C$4:$C$1500,"Meta介護校")=0,"",SUMIFS(日次入力!$D$4:$D$1500,日次入力!$A$4:$A$1500,">="&DATE(2026,11,10),日次入力!$A$4:$A$1500,"<="&DATE(2026,11,16),日次入力!$C$4:$C$1500,"Meta介護校")) | D93: =IF(COUNTIFS(日次入力!$A$4:$A$1500,">="&DATE(2026,11,10),日次入力!$A$4:$A$1500,"<="&DATE(2026,11,16),日次入力!$C$4:$C$1500,"Meta介護校")=0,"",SUMIFS(日次入力!$E$4:$E$1500,日次入力!$A$4:$A$1500,">="&DATE(2026,11,10),日次入力!$A$4:$A$1500,"<="&DATE(2026,11,16),日次入力!$C$4:$C$1500,"Meta介護校")) | E93: =IF(COUNTIFS(日次入力!$A$4:$A$1500,">="&DATE(2026,11,10),日次入力!$A$4:$A$1500,"<="&DATE(2026,11,16),日次入力!$C$4:$C$1500,"Meta介護校")=0,"",SUMIFS(日次入力!$F$4:$F$1500,日次入力!$A$4:$A$1500,">="&DATE(2026,11,10),日次入力!$A$4:$A$1500,"<="&DATE(2026,11,16),日次入力!$C$4:$C$1500,"Meta介護校")) | F93: =IF(COUNTIFS(日次入力!$A$4:$A$1500,">="&DATE(2026,11,10),日次入力!$A$4:$A$1500,"<="&DATE(2026,11,16),日次入力!$C$4:$C$1500,"Meta介護校")=0,"",SUMIFS(日次入力!$G$4:$G$1500,日次入力!$A$4:$A$1500,">="&DATE(2026,11,10),日次入力!$A$4:$A$1500,"<="&DATE(2026,11,16),日次入力!$C$4:$C$1500,"Meta介護校")) | G93: =IFERROR(E93/D93,"") | H93: =IFERROR(C93/E93,"") | I93: =IFERROR(C93/D93*1000,"") | J93: =IFERROR(F93/E93,"") | K93: =IFERROR(C93/F93,"") | L93: =IF(COUNTIFS(日次入力!$A$4:$A$1500,">="&DATE(2026,11,10),日次入力!$A$4:$A$1500,"<="&DATE(2026,11,16),日次入力!$C$4:$C$1500,"Meta介護校")=0,"",SUMIFS(日次入力!$H$4:$H$1500,日次入力!$A$4:$A$1500,">="&DATE(2026,11,10),日次入力!$A$4:$A$1500,"<="&DATE(2026,11,16),日次入力!$C$4:$C$1500,"Meta介護校")) | M93: =IF(L93="","",IFERROR(L93/F93,"")) | N93: =IF(COUNTIFS(日次入力!$A$4:$A$1500,">="&DATE(2026,11,10),日次入力!$A$4:$A$1500,"<="&DATE(2026,11,16),日次入力!$C$4:$C$1500,"Meta介護校")=0,"",SUMIFS(日次入力!$I$4:$I$1500,日次入力!$A$4:$A$1500,">="&DATE(2026,11,10),日次入力!$A$4:$A$1500,"<="&DATE(2026,11,16),日次入力!$C$4:$C$1500,"Meta介護校")) | O93: =IF(N93="","",IFERROR(N93/L93,"")) | P93: =IF(N93=0,"",IFERROR(C93/N93,"")) | Q93: =IF(N93=0,"",IFERROR(IF(C93/N93<=用語集!$B$22,"◎ 許容内","✗ 超過"),"—")) -> — | R93: =IFERROR(用語集!$B$22/P93,"")
A94: W33 | B94: 11/17–11/23 | C94: =IF(COUNTIFS(日次入力!$A$4:$A$1500,">="&DATE(2026,11,17),日次入力!$A$4:$A$1500,"<="&DATE(2026,11,23),日次入力!$C$4:$C$1500,"Meta介護校")=0,"",SUMIFS(日次入力!$D$4:$D$1500,日次入力!$A$4:$A$1500,">="&DATE(2026,11,17),日次入力!$A$4:$A$1500,"<="&DATE(2026,11,23),日次入力!$C$4:$C$1500,"Meta介護校")) | D94: =IF(COUNTIFS(日次入力!$A$4:$A$1500,">="&DATE(2026,11,17),日次入力!$A$4:$A$1500,"<="&DATE(2026,11,23),日次入力!$C$4:$C$1500,"Meta介護校")=0,"",SUMIFS(日次入力!$E$4:$E$1500,日次入力!$A$4:$A$1500,">="&DATE(2026,11,17),日次入力!$A$4:$A$1500,"<="&DATE(2026,11,23),日次入力!$C$4:$C$1500,"Meta介護校")) | E94: =IF(COUNTIFS(日次入力!$A$4:$A$1500,">="&DATE(2026,11,17),日次入力!$A$4:$A$1500,"<="&DATE(2026,11,23),日次入力!$C$4:$C$1500,"Meta介護校")=0,"",SUMIFS(日次入力!$F$4:$F$1500,日次入力!$A$4:$A$1500,">="&DATE(2026,11,17),日次入力!$A$4:$A$1500,"<="&DATE(2026,11,23),日次入力!$C$4:$C$1500,"Meta介護校")) | F94: =IF(COUNTIFS(日次入力!$A$4:$A$1500,">="&DATE(2026,11,17),日次入力!$A$4:$A$1500,"<="&DATE(2026,11,23),日次入力!$C$4:$C$1500,"Meta介護校")=0,"",SUMIFS(日次入力!$G$4:$G$1500,日次入力!$A$4:$A$1500,">="&DATE(2026,11,17),日次入力!$A$4:$A$1500,"<="&DATE(2026,11,23),日次入力!$C$4:$C$1500,"Meta介護校")) | G94: =IFERROR(E94/D94,"") | H94: =IFERROR(C94/E94,"") | I94: =IFERROR(C94/D94*1000,"") | J94: =IFERROR(F94/E94,"") | K94: =IFERROR(C94/F94,"") | L94: =IF(COUNTIFS(日次入力!$A$4:$A$1500,">="&DATE(2026,11,17),日次入力!$A$4:$A$1500,"<="&DATE(2026,11,23),日次入力!$C$4:$C$1500,"Meta介護校")=0,"",SUMIFS(日次入力!$H$4:$H$1500,日次入力!$A$4:$A$1500,">="&DATE(2026,11,17),日次入力!$A$4:$A$1500,"<="&DATE(2026,11,23),日次入力!$C$4:$C$1500,"Meta介護校")) | M94: =IF(L94="","",IFERROR(L94/F94,"")) | N94: =IF(COUNTIFS(日次入力!$A$4:$A$1500,">="&DATE(2026,11,17),日次入力!$A$4:$A$1500,"<="&DATE(2026,11,23),日次入力!$C$4:$C$1500,"Meta介護校")=0,"",SUMIFS(日次入力!$I$4:$I$1500,日次入力!$A$4:$A$1500,">="&DATE(2026,11,17),日次入力!$A$4:$A$1500,"<="&DATE(2026,11,23),日次入力!$C$4:$C$1500,"Meta介護校")) | O94: =IF(N94="","",IFERROR(N94/L94,"")) | P94: =IF(N94=0,"",IFERROR(C94/N94,"")) | Q94: =IF(N94=0,"",IFERROR(IF(C94/N94<=用語集!$B$22,"◎ 許容内","✗ 超過"),"—")) -> — | R94: =IFERROR(用語集!$B$22/P94,"")
A95: W34 | B95: 11/24–11/30 | C95: =IF(COUNTIFS(日次入力!$A$4:$A$1500,">="&DATE(2026,11,24),日次入力!$A$4:$A$1500,"<="&DATE(2026,11,30),日次入力!$C$4:$C$1500,"Meta介護校")=0,"",SUMIFS(日次入力!$D$4:$D$1500,日次入力!$A$4:$A$1500,">="&DATE(2026,11,24),日次入力!$A$4:$A$1500,"<="&DATE(2026,11,30),日次入力!$C$4:$C$1500,"Meta介護校")) | D95: =IF(COUNTIFS(日次入力!$A$4:$A$1500,">="&DATE(2026,11,24),日次入力!$A$4:$A$1500,"<="&DATE(2026,11,30),日次入力!$C$4:$C$1500,"Meta介護校")=0,"",SUMIFS(日次入力!$E$4:$E$1500,日次入力!$A$4:$A$1500,">="&DATE(2026,11,24),日次入力!$A$4:$A$1500,"<="&DATE(2026,11,30),日次入力!$C$4:$C$1500,"Meta介護校")) | E95: =IF(COUNTIFS(日次入力!$A$4:$A$1500,">="&DATE(2026,11,24),日次入力!$A$4:$A$1500,"<="&DATE(2026,11,30),日次入力!$C$4:$C$1500,"Meta介護校")=0,"",SUMIFS(日次入力!$F$4:$F$1500,日次入力!$A$4:$A$1500,">="&DATE(2026,11,24),日次入力!$A$4:$A$1500,"<="&DATE(2026,11,30),日次入力!$C$4:$C$1500,"Meta介護校")) | F95: =IF(COUNTIFS(日次入力!$A$4:$A$1500,">="&DATE(2026,11,24),日次入力!$A$4:$A$1500,"<="&DATE(2026,11,30),日次入力!$C$4:$C$1500,"Meta介護校")=0,"",SUMIFS(日次入力!$G$4:$G$1500,日次入力!$A$4:$A$1500,">="&DATE(2026,11,24),日次入力!$A$4:$A$1500,"<="&DATE(2026,11,30),日次入力!$C$4:$C$1500,"Meta介護校")) | G95: =IFERROR(E95/D95,"") | H95: =IFERROR(C95/E95,"") | I95: =IFERROR(C95/D95*1000,"") | J95: =IFERROR(F95/E95,"") | K95: =IFERROR(C95/F95,"") | L95: =IF(COUNTIFS(日次入力!$A$4:$A$1500,">="&DATE(2026,11,24),日次入力!$A$4:$A$1500,"<="&DATE(2026,11,30),日次入力!$C$4:$C$1500,"Meta介護校")=0,"",SUMIFS(日次入力!$H$4:$H$1500,日次入力!$A$4:$A$1500,">="&DATE(2026,11,24),日次入力!$A$4:$A$1500,"<="&DATE(2026,11,30),日次入力!$C$4:$C$1500,"Meta介護校")) | M95: =IF(L95="","",IFERROR(L95/F95,"")) | N95: =IF(COUNTIFS(日次入力!$A$4:$A$1500,">="&DATE(2026,11,24),日次入力!$A$4:$A$1500,"<="&DATE(2026,11,30),日次入力!$C$4:$C$1500,"Meta介護校")=0,"",SUMIFS(日次入力!$I$4:$I$1500,日次入力!$A$4:$A$1500,">="&DATE(2026,11,24),日次入力!$A$4:$A$1500,"<="&DATE(2026,11,30),日次入力!$C$4:$C$1500,"Meta介護校")) | O95: =IF(N95="","",IFERROR(N95/L95,"")) | P95: =IF(N95=0,"",IFERROR(C95/N95,"")) | Q95: =IF(N95=0,"",IFERROR(IF(C95/N95<=用語集!$B$22,"◎ 許容内","✗ 超過"),"—")) -> — | R95: =IFERROR(用語集!$B$22/P95,"")
A96: W35 | B96: 12/1–12/7 | C96: =IF(COUNTIFS(日次入力!$A$4:$A$1500,">="&DATE(2026,12,1),日次入力!$A$4:$A$1500,"<="&DATE(2026,12,7),日次入力!$C$4:$C$1500,"Meta介護校")=0,"",SUMIFS(日次入力!$D$4:$D$1500,日次入力!$A$4:$A$1500,">="&DATE(2026,12,1),日次入力!$A$4:$A$1500,"<="&DATE(2026,12,7),日次入力!$C$4:$C$1500,"Meta介護校")) | D96: =IF(COUNTIFS(日次入力!$A$4:$A$1500,">="&DATE(2026,12,1),日次入力!$A$4:$A$1500,"<="&DATE(2026,12,7),日次入力!$C$4:$C$1500,"Meta介護校")=0,"",SUMIFS(日次入力!$E$4:$E$1500,日次入力!$A$4:$A$1500,">="&DATE(2026,12,1),日次入力!$A$4:$A$1500,"<="&DATE(2026,12,7),日次入力!$C$4:$C$1500,"Meta介護校")) | E96: =IF(COUNTIFS(日次入力!$A$4:$A$1500,">="&DATE(2026,12,1),日次入力!$A$4:$A$1500,"<="&DATE(2026,12,7),日次入力!$C$4:$C$1500,"Meta介護校")=0,"",SUMIFS(日次入力!$F$4:$F$1500,日次入力!$A$4:$A$1500,">="&DATE(2026,12,1),日次入力!$A$4:$A$1500,"<="&DATE(2026,12,7),日次入力!$C$4:$C$1500,"Meta介護校")) | F96: =IF(COUNTIFS(日次入力!$A$4:$A$1500,">="&DATE(2026,12,1),日次入力!$A$4:$A$1500,"<="&DATE(2026,12,7),日次入力!$C$4:$C$1500,"Meta介護校")=0,"",SUMIFS(日次入力!$G$4:$G$1500,日次入力!$A$4:$A$1500,">="&DATE(2026,12,1),日次入力!$A$4:$A$1500,"<="&DATE(2026,12,7),日次入力!$C$4:$C$1500,"Meta介護校")) | G96: =IFERROR(E96/D96,"") | H96: =IFERROR(C96/E96,"") | I96: =IFERROR(C96/D96*1000,"") | J96: =IFERROR(F96/E96,"") | K96: =IFERROR(C96/F96,"") | L96: =IF(COUNTIFS(日次入力!$A$4:$A$1500,">="&DATE(2026,12,1),日次入力!$A$4:$A$1500,"<="&DATE(2026,12,7),日次入力!$C$4:$C$1500,"Meta介護校")=0,"",SUMIFS(日次入力!$H$4:$H$1500,日次入力!$A$4:$A$1500,">="&DATE(2026,12,1),日次入力!$A$4:$A$1500,"<="&DATE(2026,12,7),日次入力!$C$4:$C$1500,"Meta介護校")) | M96: =IF(L96="","",IFERROR(L96/F96,"")) | N96: =IF(COUNTIFS(日次入力!$A$4:$A$1500,">="&DATE(2026,12,1),日次入力!$A$4:$A$1500,"<="&DATE(2026,12,7),日次入力!$C$4:$C$1500,"Meta介護校")=0,"",SUMIFS(日次入力!$I$4:$I$1500,日次入力!$A$4:$A$1500,">="&DATE(2026,12,1),日次入力!$A$4:$A$1500,"<="&DATE(2026,12,7),日次入力!$C$4:$C$1500,"Meta介護校")) | O96: =IF(N96="","",IFERROR(N96/L96,"")) | P96: =IF(N96=0,"",IFERROR(C96/N96,"")) | Q96: =IF(N96=0,"",IFERROR(IF(C96/N96<=用語集!$B$22,"◎ 許容内","✗ 超過"),"—")) -> — | R96: =IFERROR(用語集!$B$22/P96,"")
A97: W36 | B97: 12/8–12/14 | C97: =IF(COUNTIFS(日次入力!$A$4:$A$1500,">="&DATE(2026,12,8),日次入力!$A$4:$A$1500,"<="&DATE(2026,12,14),日次入力!$C$4:$C$1500,"Meta介護校")=0,"",SUMIFS(日次入力!$D$4:$D$1500,日次入力!$A$4:$A$1500,">="&DATE(2026,12,8),日次入力!$A$4:$A$1500,"<="&DATE(2026,12,14),日次入力!$C$4:$C$1500,"Meta介護校")) | D97: =IF(COUNTIFS(日次入力!$A$4:$A$1500,">="&DATE(2026,12,8),日次入力!$A$4:$A$1500,"<="&DATE(2026,12,14),日次入力!$C$4:$C$1500,"Meta介護校")=0,"",SUMIFS(日次入力!$E$4:$E$1500,日次入力!$A$4:$A$1500,">="&DATE(2026,12,8),日次入力!$A$4:$A$1500,"<="&DATE(2026,12,14),日次入力!$C$4:$C$1500,"Meta介護校")) | E97: =IF(COUNTIFS(日次入力!$A$4:$A$1500,">="&DATE(2026,12,8),日次入力!$A$4:$A$1500,"<="&DATE(2026,12,14),日次入力!$C$4:$C$1500,"Meta介護校")=0,"",SUMIFS(日次入力!$F$4:$F$1500,日次入力!$A$4:$A$1500,">="&DATE(2026,12,8),日次入力!$A$4:$A$1500,"<="&DATE(2026,12,14),日次入力!$C$4:$C$1500,"Meta介護校")) | F97: =IF(COUNTIFS(日次入力!$A$4:$A$1500,">="&DATE(2026,12,8),日次入力!$A$4:$A$1500,"<="&DATE(2026,12,14),日次入力!$C$4:$C$1500,"Meta介護校")=0,"",SUMIFS(日次入力!$G$4:$G$1500,日次入力!$A$4:$A$1500,">="&DATE(2026,12,8),日次入力!$A$4:$A$1500,"<="&DATE(2026,12,14),日次入力!$C$4:$C$1500,"Meta介護校")) | G97: =IFERROR(E97/D97,"") | H97: =IFERROR(C97/E97,"") | I97: =IFERROR(C97/D97*1000,"") | J97: =IFERROR(F97/E97,"") | K97: =IFERROR(C97/F97,"") | L97: =IF(COUNTIFS(日次入力!$A$4:$A$1500,">="&DATE(2026,12,8),日次入力!$A$4:$A$1500,"<="&DATE(2026,12,14),日次入力!$C$4:$C$1500,"Meta介護校")=0,"",SUMIFS(日次入力!$H$4:$H$1500,日次入力!$A$4:$A$1500,">="&DATE(2026,12,8),日次入力!$A$4:$A$1500,"<="&DATE(2026,12,14),日次入力!$C$4:$C$1500,"Meta介護校")) | M97: =IF(L97="","",IFERROR(L97/F97,"")) | N97: =IF(COUNTIFS(日次入力!$A$4:$A$1500,">="&DATE(2026,12,8),日次入力!$A$4:$A$1500,"<="&DATE(2026,12,14),日次入力!$C$4:$C$1500,"Meta介護校")=0,"",SUMIFS(日次入力!$I$4:$I$1500,日次入力!$A$4:$A$1500,">="&DATE(2026,12,8),日次入力!$A$4:$A$1500,"<="&DATE(2026,12,14),日次入力!$C$4:$C$1500,"Meta介護校")) | O97: =IF(N97="","",IFERROR(N97/L97,"")) | P97: =IF(N97=0,"",IFERROR(C97/N97,"")) | Q97: =IF(N97=0,"",IFERROR(IF(C97/N97<=用語集!$B$22,"◎ 許容内","✗ 超過"),"—")) -> — | R97: =IFERROR(用語集!$B$22/P97,"")
A98: W37 | B98: 12/15–12/21 | C98: =IF(COUNTIFS(日次入力!$A$4:$A$1500,">="&DATE(2026,12,15),日次入力!$A$4:$A$1500,"<="&DATE(2026,12,21),日次入力!$C$4:$C$1500,"Meta介護校")=0,"",SUMIFS(日次入力!$D$4:$D$1500,日次入力!$A$4:$A$1500,">="&DATE(2026,12,15),日次入力!$A$4:$A$1500,"<="&DATE(2026,12,21),日次入力!$C$4:$C$1500,"Meta介護校")) | D98: =IF(COUNTIFS(日次入力!$A$4:$A$1500,">="&DATE(2026,12,15),日次入力!$A$4:$A$1500,"<="&DATE(2026,12,21),日次入力!$C$4:$C$1500,"Meta介護校")=0,"",SUMIFS(日次入力!$E$4:$E$1500,日次入力!$A$4:$A$1500,">="&DATE(2026,12,15),日次入力!$A$4:$A$1500,"<="&DATE(2026,12,21),日次入力!$C$4:$C$1500,"Meta介護校")) | E98: =IF(COUNTIFS(日次入力!$A$4:$A$1500,">="&DATE(2026,12,15),日次入力!$A$4:$A$1500,"<="&DATE(2026,12,21),日次入力!$C$4:$C$1500,"Meta介護校")=0,"",SUMIFS(日次入力!$F$4:$F$1500,日次入力!$A$4:$A$1500,">="&DATE(2026,12,15),日次入力!$A$4:$A$1500,"<="&DATE(2026,12,21),日次入力!$C$4:$C$1500,"Meta介護校")) | F98: =IF(COUNTIFS(日次入力!$A$4:$A$1500,">="&DATE(2026,12,15),日次入力!$A$4:$A$1500,"<="&DATE(2026,12,21),日次入力!$C$4:$C$1500,"Meta介護校")=0,"",SUMIFS(日次入力!$G$4:$G$1500,日次入力!$A$4:$A$1500,">="&DATE(2026,12,15),日次入力!$A$4:$A$1500,"<="&DATE(2026,12,21),日次入力!$C$4:$C$1500,"Meta介護校")) | G98: =IFERROR(E98/D98,"") | H98: =IFERROR(C98/E98,"") | I98: =IFERROR(C98/D98*1000,"") | J98: =IFERROR(F98/E98,"") | K98: =IFERROR(C98/F98,"") | L98: =IF(COUNTIFS(日次入力!$A$4:$A$1500,">="&DATE(2026,12,15),日次入力!$A$4:$A$1500,"<="&DATE(2026,12,21),日次入力!$C$4:$C$1500,"Meta介護校")=0,"",SUMIFS(日次入力!$H$4:$H$1500,日次入力!$A$4:$A$1500,">="&DATE(2026,12,15),日次入力!$A$4:$A$1500,"<="&DATE(2026,12,21),日次入力!$C$4:$C$1500,"Meta介護校")) | M98: =IF(L98="","",IFERROR(L98/F98,"")) | N98: =IF(COUNTIFS(日次入力!$A$4:$A$1500,">="&DATE(2026,12,15),日次入力!$A$4:$A$1500,"<="&DATE(2026,12,21),日次入力!$C$4:$C$1500,"Meta介護校")=0,"",SUMIFS(日次入力!$I$4:$I$1500,日次入力!$A$4:$A$1500,">="&DATE(2026,12,15),日次入力!$A$4:$A$1500,"<="&DATE(2026,12,21),日次入力!$C$4:$C$1500,"Meta介護校")) | O98: =IF(N98="","",IFERROR(N98/L98,"")) | P98: =IF(N98=0,"",IFERROR(C98/N98,"")) | Q98: =IF(N98=0,"",IFERROR(IF(C98/N98<=用語集!$B$22,"◎ 許容内","✗ 超過"),"—")) -> — | R98: =IFERROR(用語集!$B$22/P98,"")
A99: W38 | B99: 12/22–12/28 | C99: =IF(COUNTIFS(日次入力!$A$4:$A$1500,">="&DATE(2026,12,22),日次入力!$A$4:$A$1500,"<="&DATE(2026,12,28),日次入力!$C$4:$C$1500,"Meta介護校")=0,"",SUMIFS(日次入力!$D$4:$D$1500,日次入力!$A$4:$A$1500,">="&DATE(2026,12,22),日次入力!$A$4:$A$1500,"<="&DATE(2026,12,28),日次入力!$C$4:$C$1500,"Meta介護校")) | D99: =IF(COUNTIFS(日次入力!$A$4:$A$1500,">="&DATE(2026,12,22),日次入力!$A$4:$A$1500,"<="&DATE(2026,12,28),日次入力!$C$4:$C$1500,"Meta介護校")=0,"",SUMIFS(日次入力!$E$4:$E$1500,日次入力!$A$4:$A$1500,">="&DATE(2026,12,22),日次入力!$A$4:$A$1500,"<="&DATE(2026,12,28),日次入力!$C$4:$C$1500,"Meta介護校")) | E99: =IF(COUNTIFS(日次入力!$A$4:$A$1500,">="&DATE(2026,12,22),日次入力!$A$4:$A$1500,"<="&DATE(2026,12,28),日次入力!$C$4:$C$1500,"Meta介護校")=0,"",SUMIFS(日次入力!$F$4:$F$1500,日次入力!$A$4:$A$1500,">="&DATE(2026,12,22),日次入力!$A$4:$A$1500,"<="&DATE(2026,12,28),日次入力!$C$4:$C$1500,"Meta介護校")) | F99: =IF(COUNTIFS(日次入力!$A$4:$A$1500,">="&DATE(2026,12,22),日次入力!$A$4:$A$1500,"<="&DATE(2026,12,28),日次入力!$C$4:$C$1500,"Meta介護校")=0,"",SUMIFS(日次入力!$G$4:$G$1500,日次入力!$A$4:$A$1500,">="&DATE(2026,12,22),日次入力!$A$4:$A$1500,"<="&DATE(2026,12,28),日次入力!$C$4:$C$1500,"Meta介護校")) | G99: =IFERROR(E99/D99,"") | H99: =IFERROR(C99/E99,"") | I99: =IFERROR(C99/D99*1000,"") | J99: =IFERROR(F99/E99,"") | K99: =IFERROR(C99/F99,"") | L99: =IF(COUNTIFS(日次入力!$A$4:$A$1500,">="&DATE(2026,12,22),日次入力!$A$4:$A$1500,"<="&DATE(2026,12,28),日次入力!$C$4:$C$1500,"Meta介護校")=0,"",SUMIFS(日次入力!$H$4:$H$1500,日次入力!$A$4:$A$1500,">="&DATE(2026,12,22),日次入力!$A$4:$A$1500,"<="&DATE(2026,12,28),日次入力!$C$4:$C$1500,"Meta介護校")) | M99: =IF(L99="","",IFERROR(L99/F99,"")) | N99: =IF(COUNTIFS(日次入力!$A$4:$A$1500,">="&DATE(2026,12,22),日次入力!$A$4:$A$1500,"<="&DATE(2026,12,28),日次入力!$C$4:$C$1500,"Meta介護校")=0,"",SUMIFS(日次入力!$I$4:$I$1500,日次入力!$A$4:$A$1500,">="&DATE(2026,12,22),日次入力!$A$4:$A$1500,"<="&DATE(2026,12,28),日次入力!$C$4:$C$1500,"Meta介護校")) | O99: =IF(N99="","",IFERROR(N99/L99,"")) | P99: =IF(N99=0,"",IFERROR(C99/N99,"")) | Q99: =IF(N99=0,"",IFERROR(IF(C99/N99<=用語集!$B$22,"◎ 許容内","✗ 超過"),"—")) -> — | R99: =IFERROR(用語集!$B$22/P99,"")
A100: W39 | B100: 12/29–1/4 | C100: =IF(COUNTIFS(日次入力!$A$4:$A$1500,">="&DATE(2026,12,29),日次入力!$A$4:$A$1500,"<="&DATE(2027,1,4),日次入力!$C$4:$C$1500,"Meta介護校")=0,"",SUMIFS(日次入力!$D$4:$D$1500,日次入力!$A$4:$A$1500,">="&DATE(2026,12,29),日次入力!$A$4:$A$1500,"<="&DATE(2027,1,4),日次入力!$C$4:$C$1500,"Meta介護校")) | D100: =IF(COUNTIFS(日次入力!$A$4:$A$1500,">="&DATE(2026,12,29),日次入力!$A$4:$A$1500,"<="&DATE(2027,1,4),日次入力!$C$4:$C$1500,"Meta介護校")=0,"",SUMIFS(日次入力!$E$4:$E$1500,日次入力!$A$4:$A$1500,">="&DATE(2026,12,29),日次入力!$A$4:$A$1500,"<="&DATE(2027,1,4),日次入力!$C$4:$C$1500,"Meta介護校")) | E100: =IF(COUNTIFS(日次入力!$A$4:$A$1500,">="&DATE(2026,12,29),日次入力!$A$4:$A$1500,"<="&DATE(2027,1,4),日次入力!$C$4:$C$1500,"Meta介護校")=0,"",SUMIFS(日次入力!$F$4:$F$1500,日次入力!$A$4:$A$1500,">="&DATE(2026,12,29),日次入力!$A$4:$A$1500,"<="&DATE(2027,1,4),日次入力!$C$4:$C$1500,"Meta介護校")) | F100: =IF(COUNTIFS(日次入力!$A$4:$A$1500,">="&DATE(2026,12,29),日次入力!$A$4:$A$1500,"<="&DATE(2027,1,4),日次入力!$C$4:$C$1500,"Meta介護校")=0,"",SUMIFS(日次入力!$G$4:$G$1500,日次入力!$A$4:$A$1500,">="&DATE(2026,12,29),日次入力!$A$4:$A$1500,"<="&DATE(2027,1,4),日次入力!$C$4:$C$1500,"Meta介護校")) | G100: =IFERROR(E100/D100,"") | H100: =IFERROR(C100/E100,"") | I100: =IFERROR(C100/D100*1000,"") | J100: =IFERROR(F100/E100,"") | K100: =IFERROR(C100/F100,"") | L100: =IF(COUNTIFS(日次入力!$A$4:$A$1500,">="&DATE(2026,12,29),日次入力!$A$4:$A$1500,"<="&DATE(2027,1,4),日次入力!$C$4:$C$1500,"Meta介護校")=0,"",SUMIFS(日次入力!$H$4:$H$1500,日次入力!$A$4:$A$1500,">="&DATE(2026,12,29),日次入力!$A$4:$A$1500,"<="&DATE(2027,1,4),日次入力!$C$4:$C$1500,"Meta介護校")) | M100: =IF(L100="","",IFERROR(L100/F100,"")) | N100: =IF(COUNTIFS(日次入力!$A$4:$A$1500,">="&DATE(2026,12,29),日次入力!$A$4:$A$1500,"<="&DATE(2027,1,4),日次入力!$C$4:$C$1500,"Meta介護校")=0,"",SUMIFS(日次入力!$I$4:$I$1500,日次入力!$A$4:$A$1500,">="&DATE(2026,12,29),日次入力!$A$4:$A$1500,"<="&DATE(2027,1,4),日次入力!$C$4:$C$1500,"Meta介護校")) | O100: =IF(N100="","",IFERROR(N100/L100,"")) | P100: =IF(N100=0,"",IFERROR(C100/N100,"")) | Q100: =IF(N100=0,"",IFERROR(IF(C100/N100<=用語集!$B$22,"◎ 許容内","✗ 超過"),"—")) -> — | R100: =IFERROR(用語集!$B$22/P100,"")
A101: W40 | B101: 1/5–1/11 | C101: =IF(COUNTIFS(日次入力!$A$4:$A$1500,">="&DATE(2027,1,5),日次入力!$A$4:$A$1500,"<="&DATE(2027,1,11),日次入力!$C$4:$C$1500,"Meta介護校")=0,"",SUMIFS(日次入力!$D$4:$D$1500,日次入力!$A$4:$A$1500,">="&DATE(2027,1,5),日次入力!$A$4:$A$1500,"<="&DATE(2027,1,11),日次入力!$C$4:$C$1500,"Meta介護校")) | D101: =IF(COUNTIFS(日次入力!$A$4:$A$1500,">="&DATE(2027,1,5),日次入力!$A$4:$A$1500,"<="&DATE(2027,1,11),日次入力!$C$4:$C$1500,"Meta介護校")=0,"",SUMIFS(日次入力!$E$4:$E$1500,日次入力!$A$4:$A$1500,">="&DATE(2027,1,5),日次入力!$A$4:$A$1500,"<="&DATE(2027,1,11),日次入力!$C$4:$C$1500,"Meta介護校")) | E101: =IF(COUNTIFS(日次入力!$A$4:$A$1500,">="&DATE(2027,1,5),日次入力!$A$4:$A$1500,"<="&DATE(2027,1,11),日次入力!$C$4:$C$1500,"Meta介護校")=0,"",SUMIFS(日次入力!$F$4:$F$1500,日次入力!$A$4:$A$1500,">="&DATE(2027,1,5),日次入力!$A$4:$A$1500,"<="&DATE(2027,1,11),日次入力!$C$4:$C$1500,"Meta介護校")) | F101: =IF(COUNTIFS(日次入力!$A$4:$A$1500,">="&DATE(2027,1,5),日次入力!$A$4:$A$1500,"<="&DATE(2027,1,11),日次入力!$C$4:$C$1500,"Meta介護校")=0,"",SUMIFS(日次入力!$G$4:$G$1500,日次入力!$A$4:$A$1500,">="&DATE(2027,1,5),日次入力!$A$4:$A$1500,"<="&DATE(2027,1,11),日次入力!$C$4:$C$1500,"Meta介護校")) | G101: =IFERROR(E101/D101,"") | H101: =IFERROR(C101/E101,"") | I101: =IFERROR(C101/D101*1000,"") | J101: =IFERROR(F101/E101,"") | K101: =IFERROR(C101/F101,"") | L101: =IF(COUNTIFS(日次入力!$A$4:$A$1500,">="&DATE(2027,1,5),日次入力!$A$4:$A$1500,"<="&DATE(2027,1,11),日次入力!$C$4:$C$1500,"Meta介護校")=0,"",SUMIFS(日次入力!$H$4:$H$1500,日次入力!$A$4:$A$1500,">="&DATE(2027,1,5),日次入力!$A$4:$A$1500,"<="&DATE(2027,1,11),日次入力!$C$4:$C$1500,"Meta介護校")) | M101: =IF(L101="","",IFERROR(L101/F101,"")) | N101: =IF(COUNTIFS(日次入力!$A$4:$A$1500,">="&DATE(2027,1,5),日次入力!$A$4:$A$1500,"<="&DATE(2027,1,11),日次入力!$C$4:$C$1500,"Meta介護校")=0,"",SUMIFS(日次入力!$I$4:$I$1500,日次入力!$A$4:$A$1500,">="&DATE(2027,1,5),日次入力!$A$4:$A$1500,"<="&DATE(2027,1,11),日次入力!$C$4:$C$1500,"Meta介護校")) | O101: =IF(N101="","",IFERROR(N101/L101,"")) | P101: =IF(N101=0,"",IFERROR(C101/N101,"")) | Q101: =IF(N101=0,"",IFERROR(IF(C101/N101<=用語集!$B$22,"◎ 許容内","✗ 超過"),"—")) -> — | R101: =IFERROR(用語集!$B$22/P101,"")
A102: W41 | B102: 1/12–1/18 | C102: =IF(COUNTIFS(日次入力!$A$4:$A$1500,">="&DATE(2027,1,12),日次入力!$A$4:$A$1500,"<="&DATE(2027,1,18),日次入力!$C$4:$C$1500,"Meta介護校")=0,"",SUMIFS(日次入力!$D$4:$D$1500,日次入力!$A$4:$A$1500,">="&DATE(2027,1,12),日次入力!$A$4:$A$1500,"<="&DATE(2027,1,18),日次入力!$C$4:$C$1500,"Meta介護校")) | D102: =IF(COUNTIFS(日次入力!$A$4:$A$1500,">="&DATE(2027,1,12),日次入力!$A$4:$A$1500,"<="&DATE(2027,1,18),日次入力!$C$4:$C$1500,"Meta介護校")=0,"",SUMIFS(日次入力!$E$4:$E$1500,日次入力!$A$4:$A$1500,">="&DATE(2027,1,12),日次入力!$A$4:$A$1500,"<="&DATE(2027,1,18),日次入力!$C$4:$C$1500,"Meta介護校")) | E102: =IF(COUNTIFS(日次入力!$A$4:$A$1500,">="&DATE(2027,1,12),日次入力!$A$4:$A$1500,"<="&DATE(2027,1,18),日次入力!$C$4:$C$1500,"Meta介護校")=0,"",SUMIFS(日次入力!$F$4:$F$1500,日次入力!$A$4:$A$1500,">="&DATE(2027,1,12),日次入力!$A$4:$A$1500,"<="&DATE(2027,1,18),日次入力!$C$4:$C$1500,"Meta介護校")) | F102: =IF(COUNTIFS(日次入力!$A$4:$A$1500,">="&DATE(2027,1,12),日次入力!$A$4:$A$1500,"<="&DATE(2027,1,18),日次入力!$C$4:$C$1500,"Meta介護校")=0,"",SUMIFS(日次入力!$G$4:$G$1500,日次入力!$A$4:$A$1500,">="&DATE(2027,1,12),日次入力!$A$4:$A$1500,"<="&DATE(2027,1,18),日次入力!$C$4:$C$1500,"Meta介護校")) | G102: =IFERROR(E102/D102,"") | H102: =IFERROR(C102/E102,"") | I102: =IFERROR(C102/D102*1000,"") | J102: =IFERROR(F102/E102,"") | K102: =IFERROR(C102/F102,"") | L102: =IF(COUNTIFS(日次入力!$A$4:$A$1500,">="&DATE(2027,1,12),日次入力!$A$4:$A$1500,"<="&DATE(2027,1,18),日次入力!$C$4:$C$1500,"Meta介護校")=0,"",SUMIFS(日次入力!$H$4:$H$1500,日次入力!$A$4:$A$1500,">="&DATE(2027,1,12),日次入力!$A$4:$A$1500,"<="&DATE(2027,1,18),日次入力!$C$4:$C$1500,"Meta介護校")) | M102: =IF(L102="","",IFERROR(L102/F102,"")) | N102: =IF(COUNTIFS(日次入力!$A$4:$A$1500,">="&DATE(2027,1,12),日次入力!$A$4:$A$1500,"<="&DATE(2027,1,18),日次入力!$C$4:$C$1500,"Meta介護校")=0,"",SUMIFS(日次入力!$I$4:$I$1500,日次入力!$A$4:$A$1500,">="&DATE(2027,1,12),日次入力!$A$4:$A$1500,"<="&DATE(2027,1,18),日次入力!$C$4:$C$1500,"Meta介護校")) | O102: =IF(N102="","",IFERROR(N102/L102,"")) | P102: =IF(N102=0,"",IFERROR(C102/N102,"")) | Q102: =IF(N102=0,"",IFERROR(IF(C102/N102<=用語集!$B$22,"◎ 許容内","✗ 超過"),"—")) -> — | R102: =IFERROR(用語集!$B$22/P102,"")
...

Sheet 全体集計
A1: 全体集計（週次）── 広告ファネル（広告経由のみ） と 全体成果（広告＋広告外）
A2: 左＝広告経由のみ（商談化率・成約率・CPL・広告CPAは広告効率）／右＝広告＋広告外の総数（事業成果）。すべて媒体別シートから自動集計。
C3: ◀ 広告ファネル（広告経由のみ） | R3: 全体成果（広告＋広告外）▶
A4: 週 | B4: 期間 | C4: 消費金額 | D4: IMP | E4: クリック | F4: CV | G4: CPM | H4: CTR | I4: CPC | J4: CVR | K4: CPL | L4: 広告商談 | M4: 商談化率 | N4: 広告成約 | O4: 広告成約率 | P4: 広告CPA | Q4: 対許容CPA | R4: 広告外商談 | S4: 総商談 | T4: 広告外成約 | U4: 総成約 | V4: 総成約率
A5: 開始前 | B5: 〜4/6 | G5: =IFERROR(C5/D5*1000,"") | H5: =IFERROR(E5/D5,"") | I5: =IFERROR(C5/E5,"") | J5: =IFERROR(F5/E5,"") | K5: =IFERROR(C5/F5,"") | M5: =IF(F5=0,"",IFERROR(L5/F5,"")) | O5: =IF(L5=0,"",IFERROR(N5/L5,"")) | P5: =IF(N5=0,"",C5/N5) | Q5: =IF(N5=0,"",IF(C5/N5<=用語集!$B$22,"◎ 許容内","✗ 超過")) | R5: =週次_媒体別CP!L398 -> 0 | S5: =SUM(L5,R5) -> 0 | T5: =週次_媒体別CP!N398 -> 0 | U5: =SUM(N5,T5) -> 0 | V5: =IF(S5=0,"",IFERROR(U5/S5,""))
A6: W1 | B6: 4/7–4/13 | C6: =SUM(週次_媒体別CP!C6,週次_媒体別CP!C62,週次_媒体別CP!C118,週次_媒体別CP!C174,週次_媒体別CP!C230,週次_媒体別CP!C286,週次_媒体別CP!C342) -> 246127 | D6: =SUM(週次_媒体別CP!D6,週次_媒体別CP!D62,週次_媒体別CP!D118,週次_媒体別CP!D174,週次_媒体別CP!D230,週次_媒体別CP!D286,週次_媒体別CP!D342) -> 864363 | E6: =SUM(週次_媒体別CP!E6,週次_媒体別CP!E62,週次_媒体別CP!E118,週次_媒体別CP!E174,週次_媒体別CP!E230,週次_媒体別CP!E286,週次_媒体別CP!E342) -> 45867 | F6: =SUM(週次_媒体別CP!F6,週次_媒体別CP!F62,週次_媒体別CP!F118,週次_媒体別CP!F174,週次_媒体別CP!F230,週次_媒体別CP!F286,週次_媒体別CP!F342) -> 53 | G6: =IFERROR(C6/D6*1000,"") -> 284.74958 | H6: =IFERROR(E6/D6,"") -> 0.053064511 | I6: =IFERROR(C6/E6,"") -> 5.366102 | J6: =IFERROR(F6/E6,"") -> 0.0011555149 | K6: =IFERROR(C6/F6,"") -> 4643.9057 | L6: =SUM(週次_媒体別CP!L6,週次_媒体別CP!L62,週次_媒体別CP!L118,週次_媒体別CP!L174,週次_媒体別CP!L230,週次_媒体別CP!L286,週次_媒体別CP!L342) -> 1 | M6: =IF(F6=0,"",IFERROR(L6/F6,"")) -> 0.018867925 | N6: =SUM(週次_媒体別CP!N6,週次_媒体別CP!N62,週次_媒体別CP!N118,週次_媒体別CP!N174,週次_媒体別CP!N230,週次_媒体別CP!N286,週次_媒体別CP!N342) -> 0 | O6: =IF(L6=0,"",IFERROR(N6/L6,"")) -> 0 | P6: =IF(N6=0,"",C6/N6) | Q6: =IF(N6=0,"",IF(C6/N6<=用語集!$B$22,"◎ 許容内","✗ 超過")) | R6: =週次_媒体別CP!L399 -> 0 | S6: =SUM(L6,R6) -> 1 | T6: =週次_媒体別CP!N399 -> 0 | U6: =SUM(N6,T6) -> 0 | V6: =IF(S6=0,"",IFERROR(U6/S6,"")) -> 0
A7: W2 | B7: 4/14–4/20 | C7: =SUM(週次_媒体別CP!C7,週次_媒体別CP!C63,週次_媒体別CP!C119,週次_媒体別CP!C175,週次_媒体別CP!C231,週次_媒体別CP!C287,週次_媒体別CP!C343) -> 185135 | D7: =SUM(週次_媒体別CP!D7,週次_媒体別CP!D63,週次_媒体別CP!D119,週次_媒体別CP!D175,週次_媒体別CP!D231,週次_媒体別CP!D287,週次_媒体別CP!D343) -> 1017744 | E7: =SUM(週次_媒体別CP!E7,週次_媒体別CP!E63,週次_媒体別CP!E119,週次_媒体別CP!E175,週次_媒体別CP!E231,週次_媒体別CP!E287,週次_媒体別CP!E343) -> 36125 | F7: =SUM(週次_媒体別CP!F7,週次_媒体別CP!F63,週次_媒体別CP!F119,週次_媒体別CP!F175,週次_媒体別CP!F231,週次_媒体別CP!F287,週次_媒体別CP!F343) -> 90 | G7: =IFERROR(C7/D7*1000,"") -> 181.90724 | H7: =IFERROR(E7/D7,"") -> 0.035495174 | I7: =IFERROR(C7/E7,"") -> 5.1248443 | J7: =IFERROR(F7/E7,"") -> 0.0024913495 | K7: =IFERROR(C7/F7,"") -> 2057.0556 | L7: =SUM(週次_媒体別CP!L7,週次_媒体別CP!L63,週次_媒体別CP!L119,週次_媒体別CP!L175,週次_媒体別CP!L231,週次_媒体別CP!L287,週次_媒体別CP!L343) -> 2 | M7: =IF(F7=0,"",IFERROR(L7/F7,"")) -> 0.022222222 | N7: =SUM(週次_媒体別CP!N7,週次_媒体別CP!N63,週次_媒体別CP!N119,週次_媒体別CP!N175,週次_媒体別CP!N231,週次_媒体別CP!N287,週次_媒体別CP!N343) -> 0 | O7: =IF(L7=0,"",IFERROR(N7/L7,"")) -> 0 | P7: =IF(N7=0,"",C7/N7) | Q7: =IF(N7=0,"",IF(C7/N7<=用語集!$B$22,"◎ 許容内","✗ 超過")) | R7: =週次_媒体別CP!L400 -> 0 | S7: =SUM(L7,R7) -> 2 | T7: =週次_媒体別CP!N400 -> 0 | U7: =SUM(N7,T7) -> 0 | V7: =IF(S7=0,"",IFERROR(U7/S7,"")) -> 0
A8: W3 | B8: 4/21–4/27 | C8: =SUM(週次_媒体別CP!C8,週次_媒体別CP!C64,週次_媒体別CP!C120,週次_媒体別CP!C176,週次_媒体別CP!C232,週次_媒体別CP!C288,週次_媒体別CP!C344) -> 205240 | D8: =SUM(週次_媒体別CP!D8,週次_媒体別CP!D64,週次_媒体別CP!D120,週次_媒体別CP!D176,週次_媒体別CP!D232,週次_媒体別CP!D288,週次_媒体別CP!D344) -> 612481 | E8: =SUM(週次_媒体別CP!E8,週次_媒体別CP!E64,週次_媒体別CP!E120,週次_媒体別CP!E176,週次_媒体別CP!E232,週次_媒体別CP!E288,週次_媒体別CP!E344) -> 25485 | F8: =SUM(週次_媒体別CP!F8,週次_媒体別CP!F64,週次_媒体別CP!F120,週次_媒体別CP!F176,週次_媒体別CP!F232,週次_媒体別CP!F288,週次_媒体別CP!F344) -> 52 | G8: =IFERROR(C8/D8*1000,"") -> 335.09611 | H8: =IFERROR(E8/D8,"") -> 0.041609454 | I8: =IFERROR(C8/E8,"") -> 8.0533647 | J8: =IFERROR(F8/E8,"") -> 0.0020404159 | K8: =IFERROR(C8/F8,"") -> 3946.9231 | L8: =SUM(週次_媒体別CP!L8,週次_媒体別CP!L64,週次_媒体別CP!L120,週次_媒体別CP!L176,週次_媒体別CP!L232,週次_媒体別CP!L288,週次_媒体別CP!L344) -> 2 | M8: =IF(F8=0,"",IFERROR(L8/F8,"")) -> 0.038461538 | N8: =SUM(週次_媒体別CP!N8,週次_媒体別CP!N64,週次_媒体別CP!N120,週次_媒体別CP!N176,週次_媒体別CP!N232,週次_媒体別CP!N288,週次_媒体別CP!N344) -> 0 | O8: =IF(L8=0,"",IFERROR(N8/L8,"")) -> 0 | P8: =IF(N8=0,"",C8/N8) | Q8: =IF(N8=0,"",IF(C8/N8<=用語集!$B$22,"◎ 許容内","✗ 超過")) | R8: =週次_媒体別CP!L401 -> 0 | S8: =SUM(L8,R8) -> 2 | T8: =週次_媒体別CP!N401 -> 0 | U8: =SUM(N8,T8) -> 0 | V8: =IF(S8=0,"",IFERROR(U8/S8,"")) -> 0
A9: W4 | B9: 4/28–5/4 | C9: =SUM(週次_媒体別CP!C9,週次_媒体別CP!C65,週次_媒体別CP!C121,週次_媒体別CP!C177,週次_媒体別CP!C233,週次_媒体別CP!C289,週次_媒体別CP!C345) -> 96706 | D9: =SUM(週次_媒体別CP!D9,週次_媒体別CP!D65,週次_媒体別CP!D121,週次_媒体別CP!D177,週次_媒体別CP!D233,週次_媒体別CP!D289,週次_媒体別CP!D345) -> 246383 | E9: =SUM(週次_媒体別CP!E9,週次_媒体別CP!E65,週次_媒体別CP!E121,週次_媒体別CP!E177,週次_媒体別CP!E233,週次_媒体別CP!E289,週次_媒体別CP!E345) -> 8902 | F9: =SUM(週次_媒体別CP!F9,週次_媒体別CP!F65,週次_媒体別CP!F121,週次_媒体別CP!F177,週次_媒体別CP!F233,週次_媒体別CP!F289,週次_媒体別CP!F345) -> 35 | G9: =IFERROR(C9/D9*1000,"") -> 392.50273 | H9: =IFERROR(E9/D9,"") -> 0.03613074 | I9: =IFERROR(C9/E9,"") -> 10.863401 | J9: =IFERROR(F9/E9,"") -> 0.0039317007 | K9: =IFERROR(C9/F9,"") -> 2763.0286 | L9: =SUM(週次_媒体別CP!L9,週次_媒体別CP!L65,週次_媒体別CP!L121,週次_媒体別CP!L177,週次_媒体別CP!L233,週次_媒体別CP!L289,週次_媒体別CP!L345) -> 1 | M9: =IF(F9=0,"",IFERROR(L9/F9,"")) -> 0.028571429 | N9: =SUM(週次_媒体別CP!N9,週次_媒体別CP!N65,週次_媒体別CP!N121,週次_媒体別CP!N177,週次_媒体別CP!N233,週次_媒体別CP!N289,週次_媒体別CP!N345) -> 0 | O9: =IF(L9=0,"",IFERROR(N9/L9,"")) -> 0 | P9: =IF(N9=0,"",C9/N9) | Q9: =IF(N9=0,"",IF(C9/N9<=用語集!$B$22,"◎ 許容内","✗ 超過")) | R9: =週次_媒体別CP!L402 -> 0 | S9: =SUM(L9,R9) -> 1 | T9: =週次_媒体別CP!N402 -> 0 | U9: =SUM(N9,T9) -> 0 | V9: =IF(S9=0,"",IFERROR(U9/S9,"")) -> 0
A10: W5 | B10: 5/5–5/11 | C10: =SUM(週次_媒体別CP!C10,週次_媒体別CP!C66,週次_媒体別CP!C122,週次_媒体別CP!C178,週次_媒体別CP!C234,週次_媒体別CP!C290,週次_媒体別CP!C346) -> 108252 | D10: =SUM(週次_媒体別CP!D10,週次_媒体別CP!D66,週次_媒体別CP!D122,週次_媒体別CP!D178,週次_媒体別CP!D234,週次_媒体別CP!D290,週次_媒体別CP!D346) -> 26783 | E10: =SUM(週次_媒体別CP!E10,週次_媒体別CP!E66,週次_媒体別CP!E122,週次_媒体別CP!E178,週次_媒体別CP!E234,週次_媒体別CP!E290,週次_媒体別CP!E346) -> 887 | F10: =SUM(週次_媒体別CP!F10,週次_媒体別CP!F66,週次_媒体別CP!F122,週次_媒体別CP!F178,週次_媒体別CP!F234,週次_媒体別CP!F290,週次_媒体別CP!F346) -> 36 | G10: =IFERROR(C10/D10*1000,"") -> 4041.8176 | H10: =IFERROR(E10/D10,"") -> 0.033118023 | I10: =IFERROR(C10/E10,"") -> 122.04284 | J10: =IFERROR(F10/E10,"") -> 0.040586246 | K10: =IFERROR(C10/F10,"") -> 3007 | L10: =SUM(週次_媒体別CP!L10,週次_媒体別CP!L66,週次_媒体別CP!L122,週次_媒体別CP!L178,週次_媒体別CP!L234,週次_媒体別CP!L290,週次_媒体別CP!L346) -> 2 | M10: =IF(F10=0,"",IFERROR(L10/F10,"")) -> 0.055555556 | N10: =SUM(週次_媒体別CP!N10,週次_媒体別CP!N66,週次_媒体別CP!N122,週次_媒体別CP!N178,週次_媒体別CP!N234,週次_媒体別CP!N290,週次_媒体別CP!N346) -> 0 | O10: =IF(L10=0,"",IFERROR(N10/L10,"")) -> 0 | P10: =IF(N10=0,"",C10/N10) | Q10: =IF(N10=0,"",IF(C10/N10<=用語集!$B$22,"◎ 許容内","✗ 超過")) | R10: =週次_媒体別CP!L403 -> 0 | S10: =SUM(L10,R10) -> 2 | T10: =週次_媒体別CP!N403 -> 0 | U10: =SUM(N10,T10) -> 0 | V10: =IF(S10=0,"",IFERROR(U10/S10,"")) -> 0
A11: W6 | B11: 5/12–5/18 | C11: =SUM(週次_媒体別CP!C11,週次_媒体別CP!C67,週次_媒体別CP!C123,週次_媒体別CP!C179,週次_媒体別CP!C235,週次_媒体別CP!C291,週次_媒体別CP!C347) -> 105487 | D11: =SUM(週次_媒体別CP!D11,週次_媒体別CP!D67,週次_媒体別CP!D123,週次_媒体別CP!D179,週次_媒体別CP!D235,週次_媒体別CP!D291,週次_媒体別CP!D347) -> 23573 | E11: =SUM(週次_媒体別CP!E11,週次_媒体別CP!E67,週次_媒体別CP!E123,週次_媒体別CP!E179,週次_媒体別CP!E235,週次_媒体別CP!E291,週次_媒体別CP!E347) -> 816 | F11: =SUM(週次_媒体別CP!F11,週次_媒体別CP!F67,週次_媒体別CP!F123,週次_媒体別CP!F179,週次_媒体別CP!F235,週次_媒体別CP!F291,週次_媒体別CP!F347) -> 31 | G11: =IFERROR(C11/D11*1000,"") -> 4474.9077 | H11: =IFERROR(E11/D11,"") -> 0.034615874 | I11: =IFERROR(C11/E11,"") -> 129.27328 | J11: =IFERROR(F11/E11,"") -> 0.037990196 | K11: =IFERROR(C11/F11,"") -> 3402.8065 | L11: =SUM(週次_媒体別CP!L11,週次_媒体別CP!L67,週次_媒体別CP!L123,週次_媒体別CP!L179,週次_媒体別CP!L235,週次_媒体別CP!L291,週次_媒体別CP!L347) -> 3 | M11: =IF(F11=0,"",IFERROR(L11/F11,"")) -> 0.096774194 | N11: =SUM(週次_媒体別CP!N11,週次_媒体別CP!N67,週次_媒体別CP!N123,週次_媒体別CP!N179,週次_媒体別CP!N235,週次_媒体別CP!N291,週次_媒体別CP!N347) -> 0 | O11: =IF(L11=0,"",IFERROR(N11/L11,"")) -> 0 | P11: =IF(N11=0,"",C11/N11) | Q11: =IF(N11=0,"",IF(C11/N11<=用語集!$B$22,"◎ 許容内","✗ 超過")) | R11: =週次_媒体別CP!L404 -> 0 | S11: =SUM(L11,R11) -> 3 | T11: =週次_媒体別CP!N404 -> 0 | U11: =SUM(N11,T11) -> 0 | V11: =IF(S11=0,"",IFERROR(U11/S11,"")) -> 0
A12: W7 | B12: 5/19–5/25 | C12: =SUM(週次_媒体別CP!C12,週次_媒体別CP!C68,週次_媒体別CP!C124,週次_媒体別CP!C180,週次_媒体別CP!C236,週次_媒体別CP!C292,週次_媒体別CP!C348) -> 124469 | D12: =SUM(週次_媒体別CP!D12,週次_媒体別CP!D68,週次_媒体別CP!D124,週次_媒体別CP!D180,週次_媒体別CP!D236,週次_媒体別CP!D292,週次_媒体別CP!D348) -> 26582 | E12: =SUM(週次_媒体別CP!E12,週次_媒体別CP!E68,週次_媒体別CP!E124,週次_媒体別CP!E180,週次_媒体別CP!E236,週次_媒体別CP!E292,週次_媒体別CP!E348) -> 1063 | F12: =SUM(週次_媒体別CP!F12,週次_媒体別CP!F68,週次_媒体別CP!F124,週次_媒体別CP!F180,週次_媒体別CP!F236,週次_媒体別CP!F292,週次_媒体別CP!F348) -> 54 | G12: =IFERROR(C12/D12*1000,"") -> 4682.4543 | H12: =IFERROR(E12/D12,"") -> 0.039989467 | I12: =IFERROR(C12/E12,"") -> 117.09219 | J12: =IFERROR(F12/E12,"") -> 0.050799624 | K12: =IFERROR(C12/F12,"") -> 2304.9815 | L12: =SUM(週次_媒体別CP!L12,週次_媒体別CP!L68,週次_媒体別CP!L124,週次_媒体別CP!L180,週次_媒体別CP!L236,週次_媒体別CP!L292,週次_媒体別CP!L348) -> 3 | M12: =IF(F12=0,"",IFERROR(L12/F12,"")) -> 0.055555556 | N12: =SUM(週次_媒体別CP!N12,週次_媒体別CP!N68,週次_媒体別CP!N124,週次_媒体別CP!N180,週次_媒体別CP!N236,週次_媒体別CP!N292,週次_媒体別CP!N348) -> 1 | O12: =IF(L12=0,"",IFERROR(N12/L12,"")) -> 0.33333333 | P12: =IF(N12=0,"",C12/N12) -> 124469 | Q12: =IF(N12=0,"",IF(C12/N12<=用語集!$B$22,"◎ 許容内","✗ 超過")) -> ◎ 許容内 | R12: =週次_媒体別CP!L405 -> 0 | S12: =SUM(L12,R12) -> 3 | T12: =週次_媒体別CP!N405 -> 0 | U12: =SUM(N12,T12) -> 1 | V12: =IF(S12=0,"",IFERROR(U12/S12,"")) -> 0.33333333
A13: W8 | B13: 5/26–6/1 | C13: =SUM(週次_媒体別CP!C13,週次_媒体別CP!C69,週次_媒体別CP!C125,週次_媒体別CP!C181,週次_媒体別CP!C237,週次_媒体別CP!C293,週次_媒体別CP!C349) -> 210806 | D13: =SUM(週次_媒体別CP!D13,週次_媒体別CP!D69,週次_媒体別CP!D125,週次_媒体別CP!D181,週次_媒体別CP!D237,週次_媒体別CP!D293,週次_媒体別CP!D349) -> 62430 | E13: =SUM(週次_媒体別CP!E13,週次_媒体別CP!E69,週次_媒体別CP!E125,週次_媒体別CP!E181,週次_媒体別CP!E237,週次_媒体別CP!E293,週次_媒体別CP!E349) -> 1736 | F13: =SUM(週次_媒体別CP!F13,週次_媒体別CP!F69,週次_媒体別CP!F125,週次_媒体別CP!F181,週次_媒体別CP!F237,週次_媒体別CP!F293,週次_媒体別CP!F349) -> 97 | G13: =IFERROR(C13/D13*1000,"") -> 3376.6779 | H13: =IFERROR(E13/D13,"") -> 0.027807144 | I13: =IFERROR(C13/E13,"") -> 121.43203 | J13: =IFERROR(F13/E13,"") -> 0.055875576 | K13: =IFERROR(C13/F13,"") -> 2173.2577 | L13: =SUM(週次_媒体別CP!L13,週次_媒体別CP!L69,週次_媒体別CP!L125,週次_媒体別CP!L181,週次_媒体別CP!L237,週次_媒体別CP!L293,週次_媒体別CP!L349) -> 1 | M13: =IF(F13=0,"",IFERROR(L13/F13,"")) -> 0.010309278 | N13: =SUM(週次_媒体別CP!N13,週次_媒体別CP!N69,週次_媒体別CP!N125,週次_媒体別CP!N181,週次_媒体別CP!N237,週次_媒体別CP!N293,週次_媒体別CP!N349) -> 0 | O13: =IF(L13=0,"",IFERROR(N13/L13,"")) -> 0 | P13: =IF(N13=0,"",C13/N13) | Q13: =IF(N13=0,"",IF(C13/N13<=用語集!$B$22,"◎ 許容内","✗ 超過")) | R13: =週次_媒体別CP!L406 -> 0 | S13: =SUM(L13,R13) -> 1 | T13: =週次_媒体別CP!N406 -> 0 | U13: =SUM(N13,T13) -> 0 | V13: =IF(S13=0,"",IFERROR(U13/S13,"")) -> 0
A14: W9 | B14: 6/2–6/8 | C14: =SUM(週次_媒体別CP!C14,週次_媒体別CP!C70,週次_媒体別CP!C126,週次_媒体別CP!C182,週次_媒体別CP!C238,週次_媒体別CP!C294,週次_媒体別CP!C350) -> 288233 | D14: =SUM(週次_媒体別CP!D14,週次_媒体別CP!D70,週次_媒体別CP!D126,週次_媒体別CP!D182,週次_媒体別CP!D238,週次_媒体別CP!D294,週次_媒体別CP!D350) -> 82142 | E14: =SUM(週次_媒体別CP!E14,週次_媒体別CP!E70,週次_媒体別CP!E126,週次_媒体別CP!E182,週次_媒体別CP!E238,週次_媒体別CP!E294,週次_媒体別CP!E350) -> 1938 | F14: =SUM(週次_媒体別CP!F14,週次_媒体別CP!F70,週次_媒体別CP!F126,週次_媒体別CP!F182,週次_媒体別CP!F238,週次_媒体別CP!F294,週次_媒体別CP!F350) -> 126 | G14: =IFERROR(C14/D14*1000,"") -> 3508.9601 | H14: =IFERROR(E14/D14,"") -> 0.02359329 | I14: =IFERROR(C14/E14,"") -> 148.72704 | J14: =IFERROR(F14/E14,"") -> 0.06501548 | K14: =IFERROR(C14/F14,"") -> 2287.5635 | L14: =SUM(週次_媒体別CP!L14,週次_媒体別CP!L70,週次_媒体別CP!L126,週次_媒体別CP!L182,週次_媒体別CP!L238,週次_媒体別CP!L294,週次_媒体別CP!L350) -> 0 | M14: =IF(F14=0,"",IFERROR(L14/F14,"")) -> 0 | N14: =SUM(週次_媒体別CP!N14,週次_媒体別CP!N70,週次_媒体別CP!N126,週次_媒体別CP!N182,週次_媒体別CP!N238,週次_媒体別CP!N294,週次_媒体別CP!N350) -> 0 | O14: =IF(L14=0,"",IFERROR(N14/L14,"")) | P14: =IF(N14=0,"",C14/N14) | Q14: =IF(N14=0,"",IF(C14/N14<=用語集!$B$22,"◎ 許容内","✗ 超過")) | R14: =週次_媒体別CP!L407 -> 0 | S14: =SUM(L14,R14) -> 0 | T14: =週次_媒体別CP!N407 -> 0 | U14: =SUM(N14,T14) -> 0 | V14: =IF(S14=0,"",IFERROR(U14/S14,""))
A15: W10 | B15: 6/9–6/15 | C15: =SUM(週次_媒体別CP!C15,週次_媒体別CP!C71,週次_媒体別CP!C127,週次_媒体別CP!C183,週次_媒体別CP!C239,週次_媒体別CP!C295,週次_媒体別CP!C351) -> 175781 | D15: =SUM(週次_媒体別CP!D15,週次_媒体別CP!D71,週次_媒体別CP!D127,週次_媒体別CP!D183,週次_媒体別CP!D239,週次_媒体別CP!D295,週次_媒体別CP!D351) -> 45802 | E15: =SUM(週次_媒体別CP!E15,週次_媒体別CP!E71,週次_媒体別CP!E127,週次_媒体別CP!E183,週次_媒体別CP!E239,週次_媒体別CP!E295,週次_媒体別CP!E351) -> 1163 | F15: =SUM(週次_媒体別CP!F15,週次_媒体別CP!F71,週次_媒体別CP!F127,週次_媒体別CP!F183,週次_媒体別CP!F239,週次_媒体別CP!F295,週次_媒体別CP!F351) -> 83 | G15: =IFERROR(C15/D15*1000,"") -> 3837.8455 | H15: =IFERROR(E15/D15,"") -> 0.025391904 | I15: =IFERROR(C15/E15,"") -> 151.14445 | J15: =IFERROR(F15/E15,"") -> 0.071367154 | K15: =IFERROR(C15/F15,"") -> 2117.8434 | L15: =SUM(週次_媒体別CP!L15,週次_媒体別CP!L71,週次_媒体別CP!L127,週次_媒体別CP!L183,週次_媒体別CP!L239,週次_媒体別CP!L295,週次_媒体別CP!L351) -> 0 | M15: =IF(F15=0,"",IFERROR(L15/F15,"")) -> 0 | N15: =SUM(週次_媒体別CP!N15,週次_媒体別CP!N71,週次_媒体別CP!N127,週次_媒体別CP!N183,週次_媒体別CP!N239,週次_媒体別CP!N295,週次_媒体別CP!N351) -> 0 | O15: =IF(L15=0,"",IFERROR(N15/L15,"")) | P15: =IF(N15=0,"",C15/N15) | Q15: =IF(N15=0,"",IF(C15/N15<=用語集!$B$22,"◎ 許容内","✗ 超過")) | R15: =週次_媒体別CP!L408 | S15: =SUM(L15,R15) -> 0 | T15: =週次_媒体別CP!N408 | U15: =SUM(N15,T15) -> 0 | V15: =IF(S15=0,"",IFERROR(U15/S15,""))
A16: W11 | B16: 6/16–6/22 | C16: =SUM(週次_媒体別CP!C16,週次_媒体別CP!C72,週次_媒体別CP!C128,週次_媒体別CP!C184,週次_媒体別CP!C240,週次_媒体別CP!C296,週次_媒体別CP!C352) -> 233161 | D16: =SUM(週次_媒体別CP!D16,週次_媒体別CP!D72,週次_媒体別CP!D128,週次_媒体別CP!D184,週次_媒体別CP!D240,週次_媒体別CP!D296,週次_媒体別CP!D352) -> 79911 | E16: =SUM(週次_媒体別CP!E16,週次_媒体別CP!E72,週次_媒体別CP!E128,週次_媒体別CP!E184,週次_媒体別CP!E240,週次_媒体別CP!E296,週次_媒体別CP!E352) -> 1617 | F16: =SUM(週次_媒体別CP!F16,週次_媒体別CP!F72,週次_媒体別CP!F128,週次_媒体別CP!F184,週次_媒体別CP!F240,週次_媒体別CP!F296,週次_媒体別CP!F352) -> 81 | G16: =IFERROR(C16/D16*1000,"") -> 2917.7585 | H16: =IFERROR(E16/D16,"") -> 0.020235011 | I16: =IFERROR(C16/E16,"") -> 144.19357 | J16: =IFERROR(F16/E16,"") -> 0.050092764 | K16: =IFERROR(C16/F16,"") -> 2878.5309 | L16: =SUM(週次_媒体別CP!L16,週次_媒体別CP!L72,週次_媒体別CP!L128,週次_媒体別CP!L184,週次_媒体別CP!L240,週次_媒体別CP!L296,週次_媒体別CP!L352) -> 5 | M16: =IF(F16=0,"",IFERROR(L16/F16,"")) -> 0.061728395 | N16: =SUM(週次_媒体別CP!N16,週次_媒体別CP!N72,週次_媒体別CP!N128,週次_媒体別CP!N184,週次_媒体別CP!N240,週次_媒体別CP!N296,週次_媒体別CP!N352) -> 0 | O16: =IF(L16=0,"",IFERROR(N16/L16,"")) -> 0 | P16: =IF(N16=0,"",C16/N16) | Q16: =IF(N16=0,"",IF(C16/N16<=用語集!$B$22,"◎ 許容内","✗ 超過")) | R16: =週次_媒体別CP!L409 | S16: =SUM(L16,R16) -> 5 | T16: =週次_媒体別CP!N409 | U16: =SUM(N16,T16) -> 0 | V16: =IF(S16=0,"",IFERROR(U16/S16,"")) -> 0
A17: W12 | B17: 6/23–6/29 | C17: =SUM(週次_媒体別CP!C17,週次_媒体別CP!C73,週次_媒体別CP!C129,週次_媒体別CP!C185,週次_媒体別CP!C241,週次_媒体別CP!C297,週次_媒体別CP!C353) -> 0 | D17: =SUM(週次_媒体別CP!D17,週次_媒体別CP!D73,週次_媒体別CP!D129,週次_媒体別CP!D185,週次_媒体別CP!D241,週次_媒体別CP!D297,週次_媒体別CP!D353) -> 0 | E17: =SUM(週次_媒体別CP!E17,週次_媒体別CP!E73,週次_媒体別CP!E129,週次_媒体別CP!E185,週次_媒体別CP!E241,週次_媒体別CP!E297,週次_媒体別CP!E353) -> 0 | F17: =SUM(週次_媒体別CP!F17,週次_媒体別CP!F73,週次_媒体別CP!F129,週次_媒体別CP!F185,週次_媒体別CP!F241,週次_媒体別CP!F297,週次_媒体別CP!F353) -> 0 | G17: =IFERROR(C17/D17*1000,"") | H17: =IFERROR(E17/D17,"") | I17: =IFERROR(C17/E17,"") | J17: =IFERROR(F17/E17,"") | K17: =IFERROR(C17/F17,"") | L17: =SUM(週次_媒体別CP!L17,週次_媒体別CP!L73,週次_媒体別CP!L129,週次_媒体別CP!L185,週次_媒体別CP!L241,週次_媒体別CP!L297,週次_媒体別CP!L353) -> 0 | M17: =IF(F17=0,"",IFERROR(L17/F17,"")) | N17: =SUM(週次_媒体別CP!N17,週次_媒体別CP!N73,週次_媒体別CP!N129,週次_媒体別CP!N185,週次_媒体別CP!N241,週次_媒体別CP!N297,週次_媒体別CP!N353) -> 0 | O17: =IF(L17=0,"",IFERROR(N17/L17,"")) | P17: =IF(N17=0,"",C17/N17) | Q17: =IF(N17=0,"",IF(C17/N17<=用語集!$B$22,"◎ 許容内","✗ 超過")) | R17: =週次_媒体別CP!L410 | S17: =SUM(L17,R17) -> 0 | T17: =週次_媒体別CP!N410 | U17: =SUM(N17,T17) -> 0 | V17: =IF(S17=0,"",IFERROR(U17/S17,""))
... A57: W52 | B57: 3/30–4/5 | C57: =SUM(週次_媒体別CP!C57,週次_媒体別CP!C113,週次_媒体別CP!C169,週次_媒体別CP!C225,週次_媒体別CP!C281,週次_媒体別CP!C337,週次_媒体別CP!C393) -> 0 | D57: =SUM(週次_媒体別CP!D57,週次_媒体別CP!D113,週次_媒体別CP!D169,週次_媒体別CP!D225,週次_媒体別CP!D281,週次_媒体別CP!D337,週次_媒体別CP!D393) -> 0 | E57: =SUM(週次_媒体別CP!E57,週次_媒体別CP!E113,週次_媒体別CP!E169,週次_媒体別CP!E225,週次_媒体別CP!E281,週次_媒体別CP!E337,週次_媒体別CP!E393) -> 0 | F57: =SUM(週次_媒体別CP!F57,週次_媒体別CP!F113,週次_媒体別CP!F169,週次_媒体別CP!F225,週次_媒体別CP!F281,週次_媒体別CP!F337,週次_媒体別CP!F393) -> 0 | G57: =IFERROR(C57/D57*1000,"") | H57: =IFERROR(E57/D57,"") | I57: =IFERROR(C57/E57,"") | J57: =IFERROR(F57/E57,"") | K57: =IFERROR(C57/F57,"") | L57: =SUM(週次_媒体別CP!L57,週次_媒体別CP!L113,週次_媒体別CP!L169,週次_媒体別CP!L225,週次_媒体別CP!L281,週次_媒体別CP!L337,週次_媒体別CP!L393) -> 0 | M57: =IF(F57=0,"",IFERROR(L57/F57,"")) | N57: =SUM(週次_媒体別CP!N57,週次_媒体別CP!N113,週次_媒体別CP!N169,週次_媒体別CP!N225,週次_媒体別CP!N281,週次_媒体別CP!N337,週次_媒体別CP!N393) -> 0 | O57: =IF(L57=0,"",IFERROR(N57/L57,"")) | P57: =IF(N57=0,"",C57/N57) | Q57: =IF(N57=0,"",IF(C57/N57<=用語集!$B$22,"◎ 許容内","✗ 超過")) | R57: =週次_媒体別CP!L450 | S57: =SUM(L57,R57) -> 0 | T57: =週次_媒体別CP!N450 | U57: =SUM(N57,T57) -> 0 | V57: =IF(S57=0,"",IFERROR(U57/S57,""))
A58: 累計 | C58: =SUM(C5:C57) -> 1979397 | D58: =SUM(D5:D57) -> 3088194 | E58: =SUM(E5:E57) -> 125599 | F58: =SUM(F5:F57) -> 738 | G58: =IFERROR(C58/D58*1000,"") -> 640.95617 | H58: =IFERROR(E58/D58,"") -> 0.040670696 | I58: =IFERROR(C58/E58,"") -> 15.759656 | J58: =IFERROR(F58/E58,"") -> 0.005875843 | K58: =IFERROR(C58/F58,"") -> 2682.1098 | L58: =SUM(L5:L57) -> 20 | M58: =IF(F58=0,"",IFERROR(L58/F58,"")) -> 0.027100271 | N58: =SUM(N5:N57) -> 1 | O58: =IF(L58=0,"",IFERROR(N58/L58,"")) -> 0.05 | P58: =IF(N58=0,"",C58/N58) -> 1979397 | Q58: =IF(N58=0,"",IF(C58/N58<=用語集!$B$22,"◎ 許容内","✗ 超過")) -> ✗ 超過 | R58: =SUM(R5:R57) -> 0 | S58: =SUM(L58,R58) -> 20 | T58: =SUM(T5:T57) -> 0 | U58: =SUM(N58,T58) -> 1 | V58: =IF(S58=0,"",IFERROR(U58/S58,"")) -> 0.05
A60: ※左ブロック（商談化率・成約率・CPL・広告CPA）は広告経由のみ＝目標と比較できる広告効率。右ブロックの総商談・総成約は「広告＋広告外」。広告CPA＝広告費÷広告成約。「開始前（〜4/6）」は広告開始前に展示会・紹介・名刺で得た分を入れる行。レポート実測累計：商談14件（W1〜W7）・成約1件。

Sheet 用語集
A1: 用語集（指標の定義）── レポートに準拠
A2: ※末尾の『成約』『成約率』『1成約あたり広告費』は、レポートの指標をその先（成約）まで拡張したもの。
A3: IMP（インプレッション） | B3: 広告が表示された回数。
A4: クリック（リンククリック） | B4: 広告がクリックされた回数。
A5: CV（コンバージョン） | B5: 成果。本レポートでは資料請求・申込などのリード獲得を指す。
A6: CTR（クリック率） | B6: ＝クリック÷IMP。表示に対しどれだけクリックされたか。
A7: CPC（クリック単価） | B7: ＝消費金額÷クリック。1クリックあたりの費用。
A8: CPM（インプレッション単価） | B8: ＝消費金額÷IMP×1,000。広告を1,000回表示する費用＝表示枠の"仕入れ値"。クリックや成約とは独立で、表示そのものの割高/割安を表す。
A9: CVR（コンバージョン率） | B9: ＝CV÷クリック。クリックがどれだけ成果につながったか。
A10: CPL（リード獲得単価） | B10: ＝消費金額÷CV。1件のリード獲得にかかった費用。
A11: 余裕倍率 | B11: ＝許容CPA÷1成約あたり広告費。1.0超で成約コストが許容内＝余裕あり（大きいほど良い）。例：1成約¥171,000なら307,000÷171,000＝1.8倍。
A12: フリークエンシー | B12: ＝IMP÷リーチ（到達人数）。1人あたり平均で広告を何回見たか。高い（週3〜4回超）と疲弊のサイン。
A13: 商談（個別相談実施数） | B13: 実施日基準。Web会議など個別相談を実施した件数。
A14: 歩留まり（商談化率） | B14: ＝商談数÷CV。リード→商談への転換率。
... A19: その他の目標値 | B19: 1契約あたり広告予算上限（許容CPA）¥307,000／平均FC入金¥1,006,399。
A21: 目標CPL（計画・全体） | B21: 3000
A22: 許容CPA上限（円） | B22: 307000
A23: 契約単価（FC取り分・円） | B23: 800000

Sheet 使い方
A1: 介護校 週次分析テンプレ ─ 使い方
A3: 【毎週やること（5ステップ）】
A4: 1. 入力：「週次_媒体別CP」タブの新しい行に、その週の 広告費・LP訪問(クリック)・リード・商談・成約 を入力する。
A5: 2. 判定：右端の『商談化 判定』『成約 判定』が ◎△✗ で自動表示される（目標は「ダッシュボード」で設定）。
A6: 3. 特定：◎でない段＝その週のボトルネック。まず『商談化率』を見る（上流は健全なので触らない）。
A7: 4. 打ち手：ボトルネックの段に効く施策を1つ実行。商談化なら①初動フォロー<1時間 ②商談予約への導線 ③スコアリング。
A8: 5. 記録：失注理由・流入元(v1/v2)・進行中商談のステータスを別途残し、翌週へ。
A10: 【指標の意味】
A11: CPL＝広告費÷リード／LP CVR＝リード÷LP訪問／商談化率＝商談÷リード／成約率＝成約÷商談
A12: 1成約あたり広告費＝広告費÷成約。これが『許容CPA上限(¥307,000)』を下回れば採算は健全。
A13: ROAS＝FC売上÷広告費。1.0で損益分岐、現状は約1.4（薄利）。
A15: 【目標値（ダッシュボードで変更可）】
... A19: 【注意】数字は手入力（スプレッドシート管理）。LP訪問はクリック数を使い、LINE等の無効クリックは除外する。

Sheet 推移データ
A1: 推移グラフ用データ（媒体別シートに自動連動。空白＝未配信／グラフでギャップ）
A2: 消費金額
A3: 週 | B3: Meta/ウェビナー | C3: Meta/介護校 | D3: Meta/Claude | E3: Google/ウェビナー | F3: Google/常設 | G3: LINE/ウェビナー | H3: LINE/常設
A4: W1 | B4: =IF(ISNUMBER(週次_媒体別CP!C6),週次_媒体別CP!C6,"") -> 87849 | C4: =IF(ISNUMBER(週次_媒体別CP!C62),週次_媒体別CP!C62,"") -> 104849 | D4: =IF(ISNUMBER(週次_媒体別CP!C118),週次_媒体別CP!C118,"") | E4: =IF(ISNUMBER(週次_媒体別CP!C174),週次_媒体別CP!C174,"") -> 13503 | F4: =IF(ISNUMBER(週次_媒体別CP!C230),週次_媒体別CP!C230,"") -> 728 | G4: =IF(ISNUMBER(週次_媒体別CP!C286),週次_媒体別CP!C286,"") -> 13144 | H4: =IF(ISNUMBER(週次_媒体別CP!C342),週次_媒体別CP!C342,"") -> 26054
A5: W2 | B5: =IF(ISNUMBER(週次_媒体別CP!C7),週次_媒体別CP!C7,"") -> 84574 | C5: =IF(ISNUMBER(週次_媒体別CP!C63),週次_媒体別CP!C63,"") -> 45827 | D5: =IF(ISNUMBER(週次_媒体別CP!C119),週次_媒体別CP!C119,"") | E5: =IF(ISNUMBER(週次_媒体別CP!C175),週次_媒体別CP!C175,"") -> 10788 | F5: =IF(ISNUMBER(週次_媒体別CP!C231),週次_媒体別CP!C231,"") -> 2027 | G5: =IF(ISNUMBER(週次_媒体別CP!C287),週次_媒体別CP!C287,"") -> 13490 | H5: =IF(ISNUMBER(週次_媒体別CP!C343),週次_媒体別CP!C343,"") -> 28429
A6: W3 | B6: =IF(ISNUMBER(週次_媒体別CP!C8),週次_媒体別CP!C8,"") -> 77500 | C6: =IF(ISNUMBER(週次_媒体別CP!C64),週次_媒体別CP!C64,"") -> 58556 | D6: =IF(ISNUMBER(週次_媒体別CP!C120),週次_媒体別CP!C120,"") | E6: =IF(ISNUMBER(週次_媒体別CP!C176),週次_媒体別CP!C176,"") -> 21214 | F6: =IF(ISNUMBER(週次_媒体別CP!C232),週次_媒体別CP!C232,"") -> 14652 | G6: =IF(ISNUMBER(週次_媒体別CP!C288),週次_媒体別CP!C288,"") -> 19971 | H6: =IF(ISNUMBER(週次_媒体別CP!C344),週次_媒体別CP!C344,"") -> 13347
A7: W4 | B7: =IF(ISNUMBER(週次_媒体別CP!C9),週次_媒体別CP!C9,"") | C7: =IF(ISNUMBER(週次_媒体別CP!C65),週次_媒体別CP!C65,"") -> 79731 | D7: =IF(ISNUMBER(週次_媒体別CP!C121),週次_媒体別CP!C121,"") | E7: =IF(ISNUMBER(週次_媒体別CP!C177),週次_媒体別CP!C177,"") | F7: =IF(ISNUMBER(週次_媒体別CP!C233),週次_媒体別CP!C233,"") -> 4279 | G7: =IF(ISNUMBER(週次_媒体別CP!C289),週次_媒体別CP!C289,"") | H7: =IF(ISNUMBER(週次_媒体別CP!C345),週次_媒体別CP!C345,"") -> 12696
A8: W5 | B8: =IF(ISNUMBER(週次_媒体別CP!C10),週次_媒体別CP!C10,"") | C8: =IF(ISNUMBER(週次_媒体別CP!C66),週次_媒体別CP!C66,"") -> 105749 | D8: =IF(ISNUMBER(週次_媒体別CP!C122),週次_媒体別CP!C122,"") | E8: =IF(ISNUMBER(週次_媒体別CP!C178),週次_媒体別CP!C178,"") | F8: =IF(ISNUMBER(週次_媒体別CP!C234),週次_媒体別CP!C234,"") -> 2503 | G8: =IF(ISNUMBER(週次_媒体別CP!C290),週次_媒体別CP!C290,"") | H8: =IF(ISNUMBER(週次_媒体別CP!C346),週次_媒体別CP!C346,"")
A9: W6 | B9: =IF(ISNUMBER(週次_媒体別CP!C11),週次_媒体別CP!C11,"") | C9: =IF(ISNUMBER(週次_媒体別CP!C67),週次_媒体別CP!C67,"") -> 105217 | D9: =IF(ISNUMBER(週次_媒体別CP!C123),週次_媒体別CP!C123,"") -> 270 | E9: =IF(ISNUMBER(週次_媒体別CP!C179),週次_媒体別CP!C179,"") | F9: =IF(ISNUMBER(週次_媒体別CP!C235),週次_媒体別CP!C235,"") | G9: =IF(ISNUMBER(週次_媒体別CP!C291),週次_媒体別CP!C291,"") | H9: =IF(ISNUMBER(週次_媒体別CP!C347),週次_媒体別CP!C347,"")
A10: W7 | B10: =IF(ISNUMBER(週次_媒体別CP!C12),週次_媒体別CP!C12,"") | C10: =IF(ISNUMBER(週次_媒体別CP!C68),週次_媒体別CP!C68,"") -> 105644 | D10: =IF(ISNUMBER(週次_媒体別CP!C124),週次_媒体別CP!C124,"") -> 18825 | E10: =IF(ISNUMBER(週次_媒体別CP!C180),週次_媒体別CP!C180,"") | F10: =IF(ISNUMBER(週次_媒体別CP!C236),週次_媒体別CP!C236,"") | G10: =IF(ISNUMBER(週次_媒体別CP!C292),週次_媒体別CP!C292,"") | H10: =IF(ISNUMBER(週次_媒体別CP!C348),週次_媒体別CP!C348,"")
A11: W8 | B11: =IF(ISNUMBER(週次_媒体別CP!C13),週次_媒体別CP!C13,"") -> 63871 | C11: =IF(ISNUMBER(週次_媒体別CP!C69),週次_媒体別CP!C69,"") -> 103424 | D11: =IF(ISNUMBER(週次_媒体別CP!C125),週次_媒体別CP!C125,"") -> 43511 | E11: =IF(ISNUMBER(週次_媒体別CP!C181),週次_媒体別CP!C181,"") | F11: =IF(ISNUMBER(週次_媒体別CP!C237),週次_媒体別CP!C237,"") | G11: =IF(ISNUMBER(週次_媒体別CP!C293),週次_媒体別CP!C293,"") | H11: =IF(ISNUMBER(週次_媒体別CP!C349),週次_媒体別CP!C349,"")
A12: W9 | B12: =IF(ISNUMBER(週次_媒体別CP!C14),週次_媒体別CP!C14,"") -> 103281 | C12: =IF(ISNUMBER(週次_媒体別CP!C70),週次_媒体別CP!C70,"") -> 137186 | D12: =IF(ISNUMBER(週次_媒体別CP!C126),週次_媒体別CP!C126,"") -> 47766 | E12: =IF(ISNUMBER(週次_媒体別CP!C182),週次_媒体別CP!C182,"") | F12: =IF(ISNUMBER(週次_媒体別CP!C238),週次_媒体別CP!C238,"") | G12: =IF(ISNUMBER(週次_媒体別CP!C294),週次_媒体別CP!C294,"") | H12: =IF(ISNUMBER(週次_媒体別CP!C350),週次_媒体別CP!C350,"")
A13: W10 | B13: =IF(ISNUMBER(週次_媒体別CP!C15),週次_媒体別CP!C15,"") -> 36717 | C13: =IF(ISNUMBER(週次_媒体別CP!C71),週次_媒体別CP!C71,"") -> 98142 | D13: =IF(ISNUMBER(週次_媒体別CP!C127),週次_媒体別CP!C127,"") -> 40922 | E13: =IF(ISNUMBER(週次_媒体別CP!C183),週次_媒体別CP!C183,"") | F13: =IF(ISNUMBER(週次_媒体別CP!C239),週次_媒体別CP!C239,"") | G13: =IF(ISNUMBER(週次_媒体別CP!C295),週次_媒体別CP!C295,"") | H13: =IF(ISNUMBER(週次_媒体別CP!C351),週次_媒体別CP!C351,"")
A14: W11 | B14: =IF(ISNUMBER(週次_媒体別CP!C16),週次_媒体別CP!C16,"") -> 91426 | C14: =IF(ISNUMBER(週次_媒体別CP!C72),週次_媒体別CP!C72,"") -> 102707 | D14: =IF(ISNUMBER(週次_媒体別CP!C128),週次_媒体別CP!C128,"") -> 39028 | E14: =IF(ISNUMBER(週次_媒体別CP!C184),週次_媒体別CP!C184,"") | F14: =IF(ISNUMBER(週次_媒体別CP!C240),週次_媒体別CP!C240,"") | G14: =IF(ISNUMBER(週次_媒体別CP!C296),週次_媒体別CP!C296,"") | H14: =IF(ISNUMBER(週次_媒体別CP!C352),週次_媒体別CP!C352,"")
A15: W12 | B15: =IF(ISNUMBER(週次_媒体別CP!C17),週次_媒体別CP!C17,"") | C15: =IF(ISNUMBER(週次_媒体別CP!C73),週次_媒体別CP!C73,"") | D15: =IF(ISNUMBER(週次_媒体別CP!C129),週次_媒体別CP!C129,"") | E15: =IF(ISNUMBER(週次_媒体別CP!C185),週次_媒体別CP!C185,"") | F15: =IF(ISNUMBER(週次_媒体別CP!C241),週次_媒体別CP!C241,"") | G15: =IF(ISNUMBER(週次_媒体別CP!C297),週次_媒体別CP!C297,"") | H15: =IF(ISNUMBER(週次_媒体別CP!C353),週次_媒体別CP!C353,"")
... A55: W52 | B55: =IF(ISNUMBER(週次_媒体別CP!C57),週次_媒体別CP!C57,"") | C55: =IF(ISNUMBER(週次_媒体別CP!C113),週次_媒体別CP!C113,"") | D55: =IF(ISNUMBER(週次_媒体別CP!C169),週次_媒体別CP!C169,"") | E55: =IF(ISNUMBER(週次_媒体別CP!C225),週次_媒体別CP!C225,"") | F55: =IF(ISNUMBER(週次_媒体別CP!C281),週次_媒体別CP!C281,"") | G55: =IF(ISNUMBER(週次_媒体別CP!C337),週次_媒体別CP!C337,"") | H55: =IF(ISNUMBER(週次_媒体別CP!C393),週次_媒体別CP!C393,"")
A57: CV（リード）
A58: 週 | B58: Meta/ウェビナー | C58: Meta/介護校 | D58: Meta/Claude | E58: Google/ウェビナー | F58: Google/常設 | G58: LINE/ウェビナー | H58: LINE/常設
A59: W1 | B59: =IF(ISNUMBER(週次_媒体別CP!F6),週次_媒体別CP!F6,"") -> 35 | C59: =IF(ISNUMBER(週次_媒体別CP!F62),週次_媒体別CP!F62,"") -> 18 | D59: =IF(ISNUMBER(週次_媒体別CP!F118),週次_媒体別CP!F118,"") | E59: =IF(ISNUMBER(週次_媒体別CP!F174),週次_媒体別CP!F174,"") -> 0 | F59: =IF(ISNUMBER(週次_媒体別CP!F230),週次_媒体別CP!F230,"") -> 0 | G59: =IF(ISNUMBER(週次_媒体別CP!F286),週次_媒体別CP!F286,"") -> 0 | H59: =IF(ISNUMBER(週次_媒体別CP!F342),週次_媒体別CP!F342,"") -> 0
A60: W2 | B60: =IF(ISNUMBER(週次_媒体別CP!F7),週次_媒体別CP!F7,"") -> 34 | C60: =IF(ISNUMBER(週次_媒体別CP!F63),週次_媒体別CP!F63,"") -> 51 | D60: =IF(ISNUMBER(週次_媒体別CP!F119),週次_媒体別CP!F119,"") | E60: =IF(ISNUMBER(週次_媒体別CP!F175),週次_媒体別CP!F175,"") -> 4 | F60: =IF(ISNUMBER(週次_媒体別CP!F231),週次_媒体別CP!F231,"") -> 1 | G60: =IF(ISNUMBER(週次_媒体別CP!F287),週次_媒体別CP!F287,"") -> 0 | H60: =IF(ISNUMBER(週次_媒体別CP!F343),週次_媒体別CP!F343,"") -> 0
A61: W3 | B61: =IF(ISNUMBER(週次_媒体別CP!F8),週次_媒体別CP!F8,"") -> 25 | C61: =IF(ISNUMBER(週次_媒体別CP!F64),週次_媒体別CP!F64,"") -> 22 | D61: =IF(ISNUMBER(週次_媒体別CP!F120),週次_媒体別CP!F120,"") | E61: =IF(ISNUMBER(週次_媒体別CP!F176),週次_媒体別CP!F176,"") -> 2 | F61: =IF(ISNUMBER(週次_媒体別CP!F232),週次_媒体別CP!F232,"") -> 3 | G61: =IF(ISNUMBER(週次_媒体別CP!F288),週次_媒体別CP!F288,"") -> 0 | H61: =IF(ISNUMBER(週次_媒体別CP!F344),週次_媒体別CP!F344,"") -> 0
A62: W4 | B62: =IF(ISNUMBER(週次_媒体別CP!F9),週次_媒体別CP!F9,"") | C62: =IF(ISNUMBER(週次_媒体別CP!F65),週次_媒体別CP!F65,"") -> 34 | D62: =IF(ISNUMBER(週次_媒体別CP!F121),週次_媒体別CP!F121,"") | E62: =IF(ISNUMBER(週次_媒体別CP!F177),週次_媒体別CP!F177,"") | F62: =IF(ISNUMBER(週次_媒体別CP!F233),週次_媒体別CP!F233,"") -> 1 | G62: =IF(ISNUMBER(週次_媒体別CP!F289),週次_媒体別CP!F289,"") | H62: =IF(ISNUMBER(週次_媒体別CP!F345),週次_媒体別CP!F345,"") -> 0
A63: W5 | B63: =IF(ISNUMBER(週次_媒体別CP!F10),週次_媒体別CP!F10,"") | C63: =IF(ISNUMBER(週次_媒体別CP!F66),週次_媒体別CP!F66,"") -> 35 | D63: =IF(ISNUMBER(週次_媒体別CP!F122),週次_媒体別CP!F122,"") | E63: =IF(ISNUMBER(週次_媒体別CP!F178),週次_媒体別CP!F178,"") | F63: =IF(ISNUMBER(週次_媒体別CP!F234),週次_媒体別CP!F234,"") -> 1 | G63: =IF(ISNUMBER(週次_媒体別CP!F290),週次_媒体別CP!F290,"") | H63: =IF(ISNUMBER(週次_媒体別CP!F346),週次_媒体別CP!F346,"")
A64: W6 | B64: =IF(ISNUMBER(週次_媒体別CP!F11),週次_媒体別CP!F11,"") | C64: =IF(ISNUMBER(週次_媒体別CP!F67),週次_媒体別CP!F67,"") -> 31 | D64: =IF(ISNUMBER(週次_媒体別CP!F123),週次_媒体別CP!F123,"") -> 0 | E64: =IF(ISNUMBER(週次_媒体別CP!F179),週次_媒体別CP!F179,"") | F64: =IF(ISNUMBER(週次_媒体別CP!F235),週次_媒体別CP!F235,"") | G64: =IF(ISNUMBER(週次_媒体別CP!F291),週次_媒体別CP!F291,"") | H64: =IF(ISNUMBER(週次_媒体別CP!F347),週次_媒体別CP!F347,"")
A65: W7 | B65: =IF(ISNUMBER(週次_媒体別CP!F12),週次_媒体別CP!F12,"") | C65: =IF(ISNUMBER(週次_媒体別CP!F68),週次_媒体別CP!F68,"") -> 41 | D65: =IF(ISNUMBER(週次_媒体別CP!F124),週次_媒体別CP!F124,"") -> 13 | E65: =IF(ISNUMBER(週次_媒体別CP!F180),週次_媒体別CP!F180,"") | F65: =IF(ISNUMBER(週次_媒体別CP!F236),週次_媒体別CP!F236,"") | G65: =IF(ISNUMBER(週次_媒体別CP!F292),週次_媒体別CP!F292,"") | H65: =IF(ISNUMBER(週次_媒体別CP!F348),週次_媒体別CP!F348,"")
A66: W8 | B66: =IF(ISNUMBER(週次_媒体別CP!F13),週次_媒体別CP!F13,"") -> 49 | C66: =IF(ISNUMBER(週次_媒体別CP!F69),週次_媒体別CP!F69,"") -> 25 | D66: =IF(ISNUMBER(週次_媒体別CP!F125),週次_媒体別CP!F125,"") -> 23 | E66: =IF(ISNUMBER(週次_媒体別CP!F181),週次_媒体別CP!F181,"") | F66: =IF(ISNUMBER(週次_媒体別CP!F237),週次_媒体別CP!F237,"") | G66: =IF(ISNUMBER(週次_媒体別CP!F293),週次_媒体別CP!F293,"") | H66: =IF(ISNUMBER(週次_媒体別CP!F349),週次_媒体別CP!F349,"")
A67: W9 | B67: =IF(ISNUMBER(週次_媒体別CP!F14),週次_媒体別CP!F14,"") -> 68 | C67: =IF(ISNUMBER(週次_媒体別CP!F70),週次_媒体別CP!F70,"") -> 28 | D67: =IF(ISNUMBER(週次_媒体別CP!F126),週次_媒体別CP!F126,"") -> 30 | E67: =IF(ISNUMBER(週次_媒体別CP!F182),週次_媒体別CP!F182,"") | F67: =IF(ISNUMBER(週次_媒体別CP!F238),週次_媒体別CP!F238,"") | G67: =IF(ISNUMBER(週次_媒体別CP!F294),週次_媒体別CP!F294,"") | H67: =IF(ISNUMBER(週次_媒体別CP!F350),週次_媒体別CP!F350,"")
A68: W10 | B68: =IF(ISNUMBER(週次_媒体別CP!F15),週次_媒体別CP!F15,"") -> 33 | C68: =IF(ISNUMBER(週次_媒体別CP!F71),週次_媒体別CP!F71,"") -> 19 | D68: =IF(ISNUMBER(週次_媒体別CP!F127),週次_媒体別CP!F127,"") -> 31 | E68: =IF(ISNUMBER(週次_媒体別CP!F183),週次_媒体別CP!F183,"") | F68: =IF(ISNUMBER(週次_媒体別CP!F239),週次_媒体別CP!F239,"") | G68: =IF(ISNUMBER(週次_媒体別CP!F295),週次_媒体別CP!F295,"") | H68: =IF(ISNUMBER(週次_媒体別CP!F351),週次_媒体別CP!F351,"")
A69: W11 | B69: =IF(ISNUMBER(週次_媒体別CP!F16),週次_媒体別CP!F16,"") -> 28 | C69: =IF(ISNUMBER(週次_媒体別CP!F72),週次_媒体別CP!F72,"") -> 26 | D69: =IF(ISNUMBER(週次_媒体別CP!F128),週次_媒体別CP!F128,"") -> 27 | E69: =IF(ISNUMBER(週次_媒体別CP!F184),週次_媒体別CP!F184,"") | F69: =IF(ISNUMBER(週次_媒体別CP!F240),週次_媒体別CP!F240,"") | G69: =IF(ISNUMBER(週次_媒体別CP!F296),週次_媒体別CP!F296,"") | H69: =IF(ISNUMBER(週次_媒体別CP!F352),週次_媒体別CP!F352,"")
A70: W12 | B70: =IF(ISNUMBER(週次_媒体別CP!F17),週次_媒体別CP!F17,"") | C70: =IF(ISNUMBER(週次_媒体別CP!F73),週次_媒体別CP!F73,"") | D70: =IF(ISNUMBER(週次_媒体別CP!F129),週次_媒体別CP!F129,"") | E70: =IF(ISNUMBER(週次_媒体別CP!F185),週次_媒体別CP!F185,"") | F70: =IF(ISNUMBER(週次_媒体別CP!F241),週次_媒体別CP!F241,"") | G70: =IF(ISNUMBER(週次_媒体別CP!F297),週次_媒体別CP!F297,"") | H70: =IF(ISNUMBER(週次_媒体別CP!F353),週次_媒体別CP!F353,"")
... A110: W52 | B110: =IF(ISNUMBER(週次_媒体別CP!F57),週次_媒体別CP!F57,"") | C110: =IF(ISNUMBER(週次_媒体別CP!F113),週次_媒体別CP!F113,"") | D110: =IF(ISNUMBER(週次_媒体別CP!F169),週次_媒体別CP!F169,"") | E110: =IF(ISNUMBER(週次_媒体別CP!F225),週次_媒体別CP!F225,"") | F110: =IF(ISNUMBER(週次_媒体別CP!F281),週次_媒体別CP!F281,"") | G110: =IF(ISNUMBER(週次_媒体別CP!F337),週次_媒体別CP!F337,"") | H110: =IF(ISNUMBER(週次_媒体別CP!F393),週次_媒体別CP!F393,"")
A112: CPL
A113: 週 | B113: Meta/ウェビナー | C113: Meta/介護校 | D113: Meta/Claude | E113: Google/ウェビナー | F113: Google/常設 | G113: LINE/ウェビナー | H113: LINE/常設
A114: W1 | B114: =IF(ISNUMBER(週次_媒体別CP!K6),週次_媒体別CP!K6,"") -> 2509.9714 | C114: =IF(ISNUMBER(週次_媒体別CP!K62),週次_媒体別CP!K62,"") -> 5824.9444 | D114: =IF(ISNUMBER(週次_媒体別CP!K118),週次_媒体別CP!K118,"") | E114: =IF(ISNUMBER(週次_媒体別CP!K174),週次_媒体別CP!K174,"") | F114: =IF(ISNUMBER(週次_媒体別CP!K230),週次_媒体別CP!K230,"") | G114: =IF(ISNUMBER(週次_媒体別CP!K286),週次_媒体別CP!K286,"") | H114: =IF(ISNUMBER(週次_媒体別CP!K342),週次_媒体別CP!K342,"")
A115: W2 | B115: =IF(ISNUMBER(週次_媒体別CP!K7),週次_媒体別CP!K7,"") -> 2487.4706 | C115: =IF(ISNUMBER(週次_媒体別CP!K63),週次_媒体別CP!K63,"") -> 898.56863 | D115: =IF(ISNUMBER(週次_媒体別CP!K119),週次_媒体別CP!K119,"") | E115: =IF(ISNUMBER(週次_媒体別CP!K175),週次_媒体別CP!K175,"") -> 2697 | F115: =IF(ISNUMBER(週次_媒体別CP!K231),週次_媒体別CP!K231,"") -> 2027 | G115: =IF(ISNUMBER(週次_媒体別CP!K287),週次_媒体別CP!K287,"") | H115: =IF(ISNUMBER(週次_媒体別CP!K343),週次_媒体別CP!K343,"")
A116: W3 | B116: =IF(ISNUMBER(週次_媒体別CP!K8),週次_媒体別CP!K8,"") -> 3100 | C116: =IF(ISNUMBER(週次_媒体別CP!K64),週次_媒体別CP!K64,"") -> 2661.6364 | D116: =IF(ISNUMBER(週次_媒体別CP!K120),週次_媒体別CP!K120,"") | E116: =IF(ISNUMBER(週次_媒体別CP!K176),週次_媒体別CP!K176,"") -> 10607 | F116: =IF(ISNUMBER(週次_媒体別CP!K232),週次_媒体別CP!K232,"") -> 4884 | G116: =IF(ISNUMBER(週次_媒体別CP!K288),週次_媒体別CP!K288,"") | H116: =IF(ISNUMBER(週次_媒体別CP!K344),週次_媒体別CP!K344,"")
A117: W4 | B117: =IF(ISNUMBER(週次_媒体別CP!K9),週次_媒体別CP!K9,"") | C117: =IF(ISNUMBER(週次_媒体別CP!K65),週次_媒体別CP!K65,"") -> 2345.0294 | D117: =IF(ISNUMBER(週次_媒体別CP!K121),週次_媒体別CP!K121,"") | E117: =IF(ISNUMBER(週次_媒体別CP!K177),週次_媒体別CP!K177,"") | F117: =IF(ISNUMBER(週次_媒体別CP!K233),週次_媒体別CP!K233,"") -> 4279 | G117: =IF(ISNUMBER(週次_媒体別CP!K289),週次_媒体別CP!K289,"") | H117: =IF(ISNUMBER(週次_媒体別CP!K345),週次_媒体別CP!K345,"")
A118: W5 | B118: =IF(ISNUMBER(週次_媒体別CP!K10),週次_媒体別CP!K10,"") | C118: =IF(ISNUMBER(週次_媒体別CP!K66),週次_媒体別CP!K66,"") -> 3021.4 | D118: =IF(ISNUMBER(週次_媒体別CP!K122),週次_媒体別CP!K122,"") | E118: =IF(ISNUMBER(週次_媒体別CP!K178),週次_媒体別CP!K178,"") | F118: =IF(ISNUMBER(週次_媒体別CP!K234),週次_媒体別CP!K234,"") -> 2503 | G118: =IF(ISNUMBER(週次_媒体別CP!K290),週次_媒体別CP!K290,"") | H118: =IF(ISNUMBER(週次_媒体別CP!K346),週次_媒体別CP!K346,"")
A119: W6 | B119: =IF(ISNUMBER(週次_媒体別CP!K11),週次_媒体別CP!K11,"") | C119: =IF(ISNUMBER(週次_媒体別CP!K67),週次_媒体別CP!K67,"") -> 3394.0968 | D119: =IF(ISNUMBER(週次_媒体別CP!K123),週次_媒体別CP!K123,"") | E119: =IF(ISNUMBER(週次_媒体別CP!K179),週次_媒体別CP!K179,"") | F119: =IF(ISNUMBER(週次_媒体別CP!K235),週次_媒体別CP!K235,"") | G119: =IF(ISNUMBER(週次_媒体別CP!K291),週次_媒体別CP!K291,"") | H119: =IF(ISNUMBER(週次_媒体別CP!K347),週次_媒体別CP!K347,"")
A120: W7 | B120: =IF(ISNUMBER(週次_媒体別CP!K12),週次_媒体別CP!K12,"") | C120: =IF(ISNUMBER(週次_媒体別CP!K68),週次_媒体別CP!K68,"") -> 2576.6829 | D120: =IF(ISNUMBER(週次_媒体別CP!K124),週次_媒体別CP!K124,"") -> 1448.0769 | E120: =IF(ISNUMBER(週次_媒体別CP!K180),週次_媒体別CP!K180,"") | F120: =IF(ISNUMBER(週次_媒体別CP!K236),週次_媒体別CP!K236,"") | G120: =IF(ISNUMBER(週次_媒体別CP!K292),週次_媒体別CP!K292,"") | H120: =IF(ISNUMBER(週次_媒体別CP!K348),週次_媒体別CP!K348,"")
A121: W8 | B121: =IF(ISNUMBER(週次_媒体別CP!K13),週次_媒体別CP!K13,"") -> 1303.4898 | C121: =IF(ISNUMBER(週次_媒体別CP!K69),週次_媒体別CP!K69,"") -> 4136.96 | D121: =IF(ISNUMBER(週次_媒体別CP!K125),週次_媒体別CP!K125,"") -> 1891.7826 | E121: =IF(ISNUMBER(週次_媒体別CP!K181),週次_媒体別CP!K181,"") | F121: =IF(ISNUMBER(週次_媒体別CP!K237),週次_媒体別CP!K237,"") | G121: =IF(ISNUMBER(週次_媒体別CP!K293),週次_媒体別CP!K293,"") | H121: =IF(ISNUMBER(週次_媒体別CP!K349),週次_媒体別CP!K349,"")
A122: W9 | B122: =IF(ISNUMBER(週次_媒体別CP!K14),週次_媒体別CP!K14,"") -> 1518.8382 | C122: =IF(ISNUMBER(週次_媒体別CP!K70),週次_媒体別CP!K70,"") -> 4899.5 | D122: =IF(ISNUMBER(週次_媒体別CP!K126),週次_媒体別CP!K126,"") -> 1592.2 | E122: =IF(ISNUMBER(週次_媒体別CP!K182),週次_媒体別CP!K182,"") | F122: =IF(ISNUMBER(週次_媒体別CP!K238),週次_媒体別CP!K238,"") | G122: =IF(ISNUMBER(週次_媒体別CP!K294),週次_媒体別CP!K294,"") | H122: =IF(ISNUMBER(週次_媒体別CP!K350),週次_媒体別CP!K350,"")
A123: W10 | B123: =IF(ISNUMBER(週次_媒体別CP!K15),週次_媒体別CP!K15,"") -> 1112.6364 | C123: =IF(ISNUMBER(週次_媒体別CP!K71),週次_媒体別CP!K71,"") -> 5165.3684 | D123: =IF(ISNUMBER(週次_媒体別CP!K127),週次_媒体別CP!K127,"") -> 1320.0645 | E123: =IF(ISNUMBER(週次_媒体別CP!K183),週次_媒体別CP!K183,"") | F123: =IF(ISNUMBER(週次_媒体別CP!K239),週次_媒体別CP!K239,"") | G123: =IF(ISNUMBER(週次_媒体別CP!K295),週次_媒体別CP!K295,"") | H123: =IF(ISNUMBER(週次_媒体別CP!K351),週次_媒体別CP!K351,"")
A124: W11 | B124: =IF(ISNUMBER(週次_媒体別CP!K16),週次_媒体別CP!K16,"") -> 3265.2143 | C124: =IF(ISNUMBER(週次_媒体別CP!K72),週次_媒体別CP!K72,"") -> 3950.2692 | D124: =IF(ISNUMBER(週次_媒体別CP!K128),週次_媒体別CP!K128,"") -> 1445.4815 | E124: =IF(ISNUMBER(週次_媒体別CP!K184),週次_媒体別CP!K184,"") | F124: =IF(ISNUMBER(週次_媒体別CP!K240),週次_媒体別CP!K240,"") | G124: =IF(ISNUMBER(週次_媒体別CP!K296),週次_媒体別CP!K296,"") | H124: =IF(ISNUMBER(週次_媒体別CP!K352),週次_媒体別CP!K352,"")
A125: W12 | B125: =IF(ISNUMBER(週次_媒体別CP!K17),週次_媒体別CP!K17,"") | C125: =IF(ISNUMBER(週次_媒体別CP!K73),週次_媒体別CP!K73,"") | D125: =IF(ISNUMBER(週次_媒体別CP!K129),週次_媒体別CP!K129,"") | E125: =IF(ISNUMBER(週次_媒体別CP!K185),週次_媒体別CP!K185,"") | F125: =IF(ISNUMBER(週次_媒体別CP!K241),週次_媒体別CP!K241,"") | G125: =IF(ISNUMBER(週次_媒体別CP!K297),週次_媒体別CP!K297,"") | H125: =IF(ISNUMBER(週次_媒体別CP!K353),週次_媒体別CP!K353,"")
